Workbook

Sheet Read me
A1: CRYPTO ANALYSIS V6
A3: Version 7 — 8 October 2026 (file: Crypto Analysis V7). 38 coins; data as of 2026-10-07 (see Last evaluated per coin).
A4: What it is: a score and a tier for each coin from fifteen retrieved facts. No buy or sell calls. An analytical framework, not financial advice; ratings do not predict price.
A5: Sheets: Grades (the live scorer: enter grades here) | Schedule (when each coin is due for reassessment, and the 52-week calendar) | Evidence (value | source | date behind every grade) | Coin notes (what it does, biggest risk, open point) | Usage method (line 6 workings) | Decisions (every ruling made) | Change log (every change, newest first) | Settings (points, cut-offs, group rules, tiers, basket).
A6: Colors: blue text on yellow = you enter it. Black = calculated.
A7: Rules and steps: Crypto Analysis Method V7.md. Summary: crypto_analysis_summary.py. Coin report: crypto_analysis_report.py. Binder snapshot: crypto_portfolio_snapshot.py. Review schedule: crypto_review_schedule.py.
A8: Check after any change: Group check column shows OK for every coin, and no cell shows an error.
A10: VERSION LOG (newest first)
A11: V7 Review schedule: new Schedule tab. Coins I hold are reassessed every 13 weeks and every other coin every 26 weeks, spread so about two come due each week; a calendar file gives a Monday list. New coins and changes in holdings are placed automatically by crypto_review_schedule.py. Major: new tab; no grade, score or tier changed.
A12: V6.1 GRASS added (38 coins) from Lean_Scoring_Workbook_V5_2_2026-10-07_GRASS and Lean_Evidence_Table_2026-10-07_GRASS: grades, evidence, coin notes, decisions and change log. ETH Last evaluated corrected to 2026-10-07. Minor: a coin added.
A13: V6 Restructure: the Lean V5.2 scoring workbook and evidence table merged into one file; all 15 grades entered on one sheet (Grades); legacy 10-line sheets and columns removed; CoinGecko IDs and Last evaluated added as columns; one change log; one decisions list; four contradictory notes corrected. No grade, score or tier changed. Major: new structure.
A14: V5.2 and earlier: see Change log and Decisions (Lean V5.2 history).

Sheet Grades
A1: GRADES: one row per coin. Enter the group, cap and the 15 grades (A–E, NA, or blank) in the yellow cells; everything else is calculated.
A2: Blank = not retrieved (not scored, lowers coverage). NA = not applicable (removed from the denominator). Score = earned ÷ scored × 100. Below 70% coverage no tier is printed.
H3: Points → | I3: =Settings!$C$12 -> 10 | J3: =Settings!$C$13 -> 5 | K3: =Settings!$C$14 -> 5 | L3: =Settings!$C$15 -> 5 | M3: =Settings!$C$16 -> 10 | N3: =Settings!$C$17 -> 10 | O3: =Settings!$C$18 -> 5 | P3: =Settings!$C$19 -> 5 | Q3: =Settings!$C$20 -> 10 | R3: =Settings!$C$21 -> 5 | S3: =Settings!$C$22 -> 10 | T3: =Settings!$C$23 -> 5 | U3: =Settings!$C$24 -> 5 | V3: =Settings!$C$25 -> 5 | W3: =Settings!$C$26 -> 5
A4: Ticker | B4: Name | C4: Group | D4: Score | E4: Rating (/10) | F4: Coverage | G4: Tier | H4: Cap (3 or 4) | I4: L1 | J4: L2 | K4: L3 | L4: L4 | M4: L5 | N4: L6 | O4: L7 | P4: L8 | Q4: L9 | R4: L10 | S4: L11 | T4: L12 | U4: L13 | V4: L14 | W4: L15 | X4: Last evaluated | Y4: CoinGecko ID | Z4: Applicable | AA4: Scored | AB4: Earned | AC4: Score tier # | AD4: Final tier # | AE4: Group check
A5: BTC | B5: Bitcoin | C5: Money coin | D5: =IF(AA5=0,"",ROUND(AB5/AA5*100,1)) -> 90.3 | E5: =IF(D5="","",ROUND(D5/10,1)) -> 9 | F5: =IF(Z5=0,0,AA5/Z5) -> 1 | G5: =IF(D5="","",IF(F5<Settings!$B$42,"Not rated (low coverage)",CHOOSE(AD5,"Exceptional","Strong","Average/Decent","Weak"))) -> Exceptional | I5: A | J5: A | K5: A | L5: NA | M5: A | N5: C | O5: C | P5: A | Q5: A | R5: A | S5: A | T5: NA | U5: A | V5: A | W5: B | X5: 2026-10-05 | Y5: bitcoin | Z5: =SUMPRODUCT(--(I5:W5<>"NA"),I$3:W$3) -> 90 | AA5: =SUMPRODUCT(--(I5:W5<>""),--(I5:W5<>"NA"),I$3:W$3) -> 90 | AB5: =SUMPRODUCT((I5:W5="A")*Settings!$B$4+(I5:W5="B")*Settings!$B$5+(I5:W5="C")*Settings!$B$6+(I5:W5="D")*Settings!$B$7+(I5:W5="E")*Settings!$B$8,I$3:W$3) -> 81.25 | AC5: =IF(D5="","",IF(D5>=Settings!$B$39,1,IF(D5>=Settings!$B$40,2,IF(D5>=Settings!$B$41,3,4)))) -> 1 | AD5: =IF(AC5="","",IF(H5="",IF(C5="Memecoin",MAX(AC5,3),AC5),IF(H5>=4,MAX(AC5,H5),IF(C5="Memecoin",MAX(AC5,3),MAX(AC5,MIN(H5,AC5+1)))))) -> 1 | AE5: =IF(C5="","",IF(SUMPRODUCT((INDEX(Settings!$B$31:$P$34,MATCH(C5,Settings!$A$31:$A$34,0),0)=1)*(I5:W5<>"NA"))>0,"Group NA missing","OK")) -> OK
A6: ETH | B6: Ethereum | C6: Chain / protocol | D6: =IF(AA6=0,"",ROUND(AB6/AA6*100,1)) -> 86.3 | E6: =IF(D6="","",ROUND(D6/10,1)) -> 8.6 | F6: =IF(Z6=0,0,AA6/Z6) -> 1 | G6: =IF(D6="","",IF(F6<Settings!$B$42,"Not rated (low coverage)",CHOOSE(AD6,"Exceptional","Strong","Average/Decent","Weak"))) -> Strong | I6: A | J6: A | K6: A | L6: B | M6: A | N6: D | O6: C | P6: A | Q6: A | R6: A | S6: A | T6: C | U6: A | V6: A | W6: A | X6: 2026-10-07 | Y6: ethereum | Z6: =SUMPRODUCT(--(I6:W6<>"NA"),I$3:W$3) -> 100 | AA6: =SUMPRODUCT(--(I6:W6<>""),--(I6:W6<>"NA"),I$3:W$3) -> 100 | AB6: =SUMPRODUCT((I6:W6="A")*Settings!$B$4+(I6:W6="B")*Settings!$B$5+(I6:W6="C")*Settings!$B$6+(I6:W6="D")*Settings!$B$7+(I6:W6="E")*Settings!$B$8,I$3:W$3) -> 86.25 | AC6: =IF(D6="","",IF(D6>=Settings!$B$39,1,IF(D6>=Settings!$B$40,2,IF(D6>=Settings!$B$41,3,4)))) -> 2 | AD6: =IF(AC6="","",IF(H6="",IF(C6="Memecoin",MAX(AC6,3),AC6),IF(H6>=4,MAX(AC6,H6),IF(C6="Memecoin",MAX(AC6,3),MAX(AC6,MIN(H6,AC6+1)))))) -> 2 | AE6: =IF(C6="","",IF(SUMPRODUCT((INDEX(Settings!$B$31:$P$34,MATCH(C6,Settings!$A$31:$A$34,0),0)=1)*(I6:W6<>"NA"))>0,"Group NA missing","OK")) -> OK
A7: SOL | B7: Solana | C7: Chain / protocol | D7: =IF(AA7=0,"",ROUND(AB7/AA7*100,1)) -> 80 | E7: =IF(D7="","",ROUND(D7/10,1)) -> 8 | F7: =IF(Z7=0,0,AA7/Z7) -> 1 | G7: =IF(D7="","",IF(F7<Settings!$B$42,"Not rated (low coverage)",CHOOSE(AD7,"Exceptional","Strong","Average/Decent","Weak"))) -> Strong | I7: A | J7: B | K7: D | L7: C | M7: A | N7: D | O7: B | P7: A | Q7: B | R7: A | S7: A | T7: A | U7: A | V7: B | W7: A | X7: 2026-10-05 | Y7: solana | Z7: =SUMPRODUCT(--(I7:W7<>"NA"),I$3:W$3) -> 100 | AA7: =SUMPRODUCT(--(I7:W7<>""),--(I7:W7<>"NA"),I$3:W$3) -> 100 | AB7: =SUMPRODUCT((I7:W7="A")*Settings!$B$4+(I7:W7="B")*Settings!$B$5+(I7:W7="C")*Settings!$B$6+(I7:W7="D")*Settings!$B$7+(I7:W7="E")*Settings!$B$8,I$3:W$3) -> 80 | AC7: =IF(D7="","",IF(D7>=Settings!$B$39,1,IF(D7>=Settings!$B$40,2,IF(D7>=Settings!$B$41,3,4)))) -> 2 | AD7: =IF(AC7="","",IF(H7="",IF(C7="Memecoin",MAX(AC7,3),AC7),IF(H7>=4,MAX(AC7,H7),IF(C7="Memecoin",MAX(AC7,3),MAX(AC7,MIN(H7,AC7+1)))))) -> 2 | AE7: =IF(C7="","",IF(SUMPRODUCT((INDEX(Settings!$B$31:$P$34,MATCH(C7,Settings!$A$31:$A$34,0),0)=1)*(I7:W7<>"NA"))>0,"Group NA missing","OK")) -> OK
A8: XRP | B8: XRP Ledger | C8: Chain / protocol | D8: =IF(AA8=0,"",ROUND(AB8/AA8*100,1)) -> 73.8 | E8: =IF(D8="","",ROUND(D8/10,1)) -> 7.4 | F8: =IF(Z8=0,0,AA8/Z8) -> 1 | G8: =IF(D8="","",IF(F8<Settings!$B$42,"Not rated (low coverage)",CHOOSE(AD8,"Exceptional","Strong","Average/Decent","Weak"))) -> Average/Decent | I8: B | J8: C | K8: C | L8: C | M8: A | N8: D | O8: B | P8: C | Q8: A | R8: C | S8: A | T8: A | U8: A | V8: B | W8: B | X8: 2026-10-05 | Y8: ripple | Z8: =SUMPRODUCT(--(I8:W8<>"NA"),I$3:W$3) -> 100 | AA8: =SUMPRODUCT(--(I8:W8<>""),--(I8:W8<>"NA"),I$3:W$3) -> 100 | AB8: =SUMPRODUCT((I8:W8="A")*Settings!$B$4+(I8:W8="B")*Settings!$B$5+(I8:W8="C")*Settings!$B$6+(I8:W8="D")*Settings!$B$7+(I8:W8="E")*Settings!$B$8,I$3:W$3) -> 73.75 | AC8: =IF(D8="","",IF(D8>=Settings!$B$39,1,IF(D8>=Settings!$B$40,2,IF(D8>=Settings!$B$41,3,4)))) -> 3 | AD8: =IF(AC8="","",IF(H8="",IF(C8="Memecoin",MAX(AC8,3),AC8),IF(H8>=4,MAX(AC8,H8),IF(C8="Memecoin",MAX(AC8,3),MAX(AC8,MIN(H8,AC8+1)))))) -> 3 | AE8: =IF(C8="","",IF(SUMPRODUCT((INDEX(Settings!$B$31:$P$34,MATCH(C8,Settings!$A$31:$A$34,0),0)=1)*(I8:W8<>"NA"))>0,"Group NA missing","OK")) -> OK
A9: NEAR | B9: NEAR Protocol | C9: Chain / protocol | D9: =IF(AA9=0,"",ROUND(AB9/AA9*100,1)) -> 73.7 | E9: =IF(D9="","",ROUND(D9/10,1)) -> 7.4 | F9: =IF(Z9=0,0,AA9/Z9) -> 0.95 | G9: =IF(D9="","",IF(F9<Settings!$B$42,"Not rated (low coverage)",CHOOSE(AD9,"Exceptional","Strong","Average/Decent","Weak"))) -> Average/Decent | H9: 3 | I9: A | J9: A | K9: D | L9: C | M9: A | N9: D | O9: B | P9: C | Q9: B | R9: C | S9: A | T9: A | V9: C | W9: A | X9: 2026-10-05 | Y9: near | Z9: =SUMPRODUCT(--(I9:W9<>"NA"),I$3:W$3) -> 100 | AA9: =SUMPRODUCT(--(I9:W9<>""),--(I9:W9<>"NA"),I$3:W$3) -> 95 | AB9: =SUMPRODUCT((I9:W9="A")*Settings!$B$4+(I9:W9="B")*Settings!$B$5+(I9:W9="C")*Settings!$B$6+(I9:W9="D")*Settings!$B$7+(I9:W9="E")*Settings!$B$8,I$3:W$3) -> 70 | AC9: =IF(D9="","",IF(D9>=Settings!$B$39,1,IF(D9>=Settings!$B$40,2,IF(D9>=Settings!$B$41,3,4)))) -> 3 | AD9: =IF(AC9="","",IF(H9="",IF(C9="Memecoin",MAX(AC9,3),AC9),IF(H9>=4,MAX(AC9,H9),IF(C9="Memecoin",MAX(AC9,3),MAX(AC9,MIN(H9,AC9+1)))))) -> 3 | AE9: =IF(C9="","",IF(SUMPRODUCT((INDEX(Settings!$B$31:$P$34,MATCH(C9,Settings!$A$31:$A$34,0),0)=1)*(I9:W9<>"NA"))>0,"Group NA missing","OK")) -> OK
A10: LINK | B10: Chainlink | C10: Chain / protocol | D10: =IF(AA10=0,"",ROUND(AB10/AA10*100,1)) -> 75 | E10: =IF(D10="","",ROUND(D10/10,1)) -> 7.5 | F10: =IF(Z10=0,0,AA10/Z10) -> 1 | G10: =IF(D10="","",IF(F10<Settings!$B$42,"Not rated (low coverage)",CHOOSE(AD10,"Exceptional","Strong","Average/Decent","Weak"))) -> Strong | I10: B | J10: B | K10: E | L10: A | M10: A | N10: C | O10: C | P10: B | Q10: B | R10: C | S10: A | T10: B | U10: A | V10: B | W10: A | X10: 2026-10-05 | Y10: chainlink | Z10: =SUMPRODUCT(--(I10:W10<>"NA"),I$3:W$3) -> 100 | AA10: =SUMPRODUCT(--(I10:W10<>""),--(I10:W10<>"NA"),I$3:W$3) -> 100 | AB10: =SUMPRODUCT((I10:W10="A")*Settings!$B$4+(I10:W10="B")*Settings!$B$5+(I10:W10="C")*Settings!$B$6+(I10:W10="D")*Settings!$B$7+(I10:W10="E")*Settings!$B$8,I$3:W$3) -> 75 | AC10: =IF(D10="","",IF(D10>=Settings!$B$39,1,IF(D10>=Settings!$B$40,2,IF(D10>=Settings!$B$41,3,4)))) -> 2 | AD10: =IF(AC10="","",IF(H10="",IF(C10="Memecoin",MAX(AC10,3),AC10),IF(H10>=4,MAX(AC10,H10),IF(C10="Memecoin",MAX(AC10,3),MAX(AC10,MIN(H10,AC10+1)))))) -> 2 | AE10: =IF(C10="","",IF(SUMPRODUCT((INDEX(Settings!$B$31:$P$34,MATCH(C10,Settings!$A$31:$A$34,0),0)=1)*(I10:W10<>"NA"))>0,"Group NA missing","OK")) -> OK
A11: UNI | B11: Uniswap | C11: Chain / protocol | D11: =IF(AA11=0,"",ROUND(AB11/AA11*100,1)) -> 73.8 | E11: =IF(D11="","",ROUND(D11/10,1)) -> 7.4 | F11: =IF(Z11=0,0,AA11/Z11) -> 1 | G11: =IF(D11="","",IF(F11<Settings!$B$42,"Not rated (low coverage)",CHOOSE(AD11,"Exceptional","Strong","Average/Decent","Weak"))) -> Average/Decent | I11: B | J11: A | K11: C | L11: D | M11: A | N11: E | O11: B | P11: A | Q11: B | R11: B | S11: A | T11: A | U11: A | V11: C | W11: A | X11: 2026-10-05 | Y11: uniswap | Z11: =SUMPRODUCT(--(I11:W11<>"NA"),I$3:W$3) -> 100 | AA11: =SUMPRODUCT(--(I11:W11<>""),--(I11:W11<>"NA"),I$3:W$3) -> 100 | AB11: =SUMPRODUCT((I11:W11="A")*Settings!$B$4+(I11:W11="B")*Settings!$B$5+(I11:W11="C")*Settings!$B$6+(I11:W11="D")*Settings!$B$7+(I11:W11="E")*Settings!$B$8,I$3:W$3) -> 73.75 | AC11: =IF(D11="","",IF(D11>=Settings!$B$39,1,IF(D11>=Settings!$B$40,2,IF(D11>=Settings!$B$41,3,4)))) -> 3 | AD11: =IF(AC11="","",IF(H11="",IF(C11="Memecoin",MAX(AC11,3),AC11),IF(H11>=4,MAX(AC11,H11),IF(C11="Memecoin",MAX(AC11,3),MAX(AC11,MIN(H11,AC11+1)))))) -> 3 | AE11: =IF(C11="","",IF(SUMPRODUCT((INDEX(Settings!$B$31:$P$34,MATCH(C11,Settings!$A$31:$A$34,0),0)=1)*(I11:W11<>"NA"))>0,"Group NA missing","OK")) -> OK
A12: AAVE | B12: Aave | C12: Chain / protocol | D12: =IF(AA12=0,"",ROUND(AB12/AA12*100,1)) -> 78.9 | E12: =IF(D12="","",ROUND(D12/10,1)) -> 7.9 | F12: =IF(Z12=0,0,AA12/Z12) -> 0.95 | G12: =IF(D12="","",IF(F12<Settings!$B$42,"Not rated (low coverage)",CHOOSE(AD12,"Exceptional","Strong","Average/Decent","Weak"))) -> Strong | I12: A | J12: A | L12: E | M12: A | N12: D | O12: B | P12: B | Q12: A | R12: B | S12: A | T12: B | U12: A | V12: C | W12: A | X12: 2026-10-05 | Y12: aave | Z12: =SUMPRODUCT(--(I12:W12<>"NA"),I$3:W$3) -> 100 | AA12: =SUMPRODUCT(--(I12:W12<>""),--(I12:W12<>"NA"),I$3:W$3) -> 95 | AB12: =SUMPRODUCT((I12:W12="A")*Settings!$B$4+(I12:W12="B")*Settings!$B$5+(I12:W12="C")*Settings!$B$6+(I12:W12="D")*Settings!$B$7+(I12:W12="E")*Settings!$B$8,I$3:W$3) -> 75 | AC12: =IF(D12="","",IF(D12>=Settings!$B$39,1,IF(D12>=Settings!$B$40,2,IF(D12>=Settings!$B$41,3,4)))) -> 2 | AD12: =IF(AC12="","",IF(H12="",IF(C12="Memecoin",MAX(AC12,3),AC12),IF(H12>=4,MAX(AC12,H12),IF(C12="Memecoin",MAX(AC12,3),MAX(AC12,MIN(H12,AC12+1)))))) -> 2 | AE12: =IF(C12="","",IF(SUMPRODUCT((INDEX(Settings!$B$31:$P$34,MATCH(C12,Settings!$A$31:$A$34,0),0)=1)*(I12:W12<>"NA"))>0,"Group NA missing","OK")) -> OK
A13: ONDO | B13: Ondo | C13: Chain / protocol | D13: =IF(AA13=0,"",ROUND(AB13/AA13*100,1)) -> 68.8 | E13: =IF(D13="","",ROUND(D13/10,1)) -> 6.9 | F13: =IF(Z13=0,0,AA13/Z13) -> 1 | G13: =IF(D13="","",IF(F13<Settings!$B$42,"Not rated (low coverage)",CHOOSE(AD13,"Exceptional","Strong","Average/Decent","Weak"))) -> Average/Decent | I13: C | J13: A | K13: E | L13: E | M13: A | N13: C | O13: B | P13: A | Q13: B | R13: D | S13: A | T13: B | U13: A | V13: C | W13: A | X13: 2026-10-05 | Y13: ondo-finance | Z13: =SUMPRODUCT(--(I13:W13<>"NA"),I$3:W$3) -> 100 | AA13: =SUMPRODUCT(--(I13:W13<>""),--(I13:W13<>"NA"),I$3:W$3) -> 100 | AB13: =SUMPRODUCT((I13:W13="A")*Settings!$B$4+(I13:W13="B")*Settings!$B$5+(I13:W13="C")*Settings!$B$6+(I13:W13="D")*Settings!$B$7+(I13:W13="E")*Settings!$B$8,I$3:W$3) -> 68.75 | AC13: =IF(D13="","",IF(D13>=Settings!$B$39,1,IF(D13>=Settings!$B$40,2,IF(D13>=Settings!$B$41,3,4)))) -> 3 | AD13: =IF(AC13="","",IF(H13="",IF(C13="Memecoin",MAX(AC13,3),AC13),IF(H13>=4,MAX(AC13,H13),IF(C13="Memecoin",MAX(AC13,3),MAX(AC13,MIN(H13,AC13+1)))))) -> 3 | AE13: =IF(C13="","",IF(SUMPRODUCT((INDEX(Settings!$B$31:$P$34,MATCH(C13,Settings!$A$31:$A$34,0),0)=1)*(I13:W13<>"NA"))>0,"Group NA missing","OK")) -> OK
A14: TAO | B14: Bittensor | C14: Chain / protocol | D14: =IF(AA14=0,"",ROUND(AB14/AA14*100,1)) -> 68.1 | E14: =IF(D14="","",ROUND(D14/10,1)) -> 6.8 | F14: =IF(Z14=0,0,AA14/Z14) -> 0.94736842 | G14: =IF(D14="","",IF(F14<Settings!$B$42,"Not rated (low coverage)",CHOOSE(AD14,"Exceptional","Strong","Average/Decent","Weak"))) -> Average/Decent | I14: C | J14: B | K14: A | L14: E | M14: A | N14: C | O14: B | P14: B | Q14: C | R14: C | S14: A | T14: NA | V14: C | W14: A | X14: 2026-10-05 | Y14: bittensor | Z14: =SUMPRODUCT(--(I14:W14<>"NA"),I$3:W$3) -> 95 | AA14: =SUMPRODUCT(--(I14:W14<>""),--(I14:W14<>"NA"),I$3:W$3) -> 90 | AB14: =SUMPRODUCT((I14:W14="A")*Settings!$B$4+(I14:W14="B")*Settings!$B$5+(I14:W14="C")*Settings!$B$6+(I14:W14="D")*Settings!$B$7+(I14:W14="E")*Settings!$B$8,I$3:W$3) -> 61.25 | AC14: =IF(D14="","",IF(D14>=Settings!$B$39,1,IF(D14>=Settings!$B$40,2,IF(D14>=Settings!$B$41,3,4)))) -> 3 | AD14: =IF(AC14="","",IF(H14="",IF(C14="Memecoin",MAX(AC14,3),AC14),IF(H14>=4,MAX(AC14,H14),IF(C14="Memecoin",MAX(AC14,3),MAX(AC14,MIN(H14,AC14+1)))))) -> 3 | AE14: =IF(C14="","",IF(SUMPRODUCT((INDEX(Settings!$B$31:$P$34,MATCH(C14,Settings!$A$31:$A$34,0),0)=1)*(I14:W14<>"NA"))>0,"Group NA missing","OK")) -> OK
A15: BNB | B15: BNB | C15: Chain / protocol | D15: =IF(AA15=0,"",ROUND(AB15/AA15*100,1)) -> 71.1 | E15: =IF(D15="","",ROUND(D15/10,1)) -> 7.1 | F15: =IF(Z15=0,0,AA15/Z15) -> 0.95 | G15: =IF(D15="","",IF(F15<Settings!$B$42,"Not rated (low coverage)",CHOOSE(AD15,"Exceptional","Strong","Average/Decent","Weak"))) -> Average/Decent | H15: 3 | I15: A | J15: A | K15: D | L15: C | M15: A | N15: D | O15: C | P15: A | Q15: C | R15: D | S15: A | T15: B | V15: A | W15: B | X15: 2026-10-05 | Y15: binancecoin | Z15: =SUMPRODUCT(--(I15:W15<>"NA"),I$3:W$3) -> 100 | AA15: =SUMPRODUCT(--(I15:W15<>""),--(I15:W15<>"NA"),I$3:W$3) -> 95 | AB15: =SUMPRODUCT((I15:W15="A")*Settings!$B$4+(I15:W15="B")*Settings!$B$5+(I15:W15="C")*Settings!$B$6+(I15:W15="D")*Settings!$B$7+(I15:W15="E")*Settings!$B$8,I$3:W$3) -> 67.5 | AC15: =IF(D15="","",IF(D15>=Settings!$B$39,1,IF(D15>=Settings!$B$40,2,IF(D15>=Settings!$B$41,3,4)))) -> 3 | AD15: =IF(AC15="","",IF(H15="",IF(C15="Memecoin",MAX(AC15,3),AC15),IF(H15>=4,MAX(AC15,H15),IF(C15="Memecoin",MAX(AC15,3),MAX(AC15,MIN(H15,AC15+1)))))) -> 3 | AE15: =IF(C15="","",IF(SUMPRODUCT((INDEX(Settings!$B$31:$P$34,MATCH(C15,Settings!$A$31:$A$34,0),0)=1)*(I15:W15<>"NA"))>0,"Group NA missing","OK")) -> OK
A16: RENDER | B16: Render | C16: Chain / protocol | D16: =IF(AA16=0,"",ROUND(AB16/AA16*100,1)) -> 79.2 | E16: =IF(D16="","",ROUND(D16/10,1)) -> 7.9 | F16: =IF(Z16=0,0,AA16/Z16) -> 0.9 | G16: =IF(D16="","",IF(F16<Settings!$B$42,"Not rated (low coverage)",CHOOSE(AD16,"Exceptional","Strong","Average/Decent","Weak"))) -> Strong | I16: A | J16: A | L16: C | M16: A | N16: A | O16: B | P16: B | Q16: C | R16: C | S16: A | T16: B | V16: C | W16: C | X16: 2026-10-05 | Y16: render-token | Z16: =SUMPRODUCT(--(I16:W16<>"NA"),I$3:W$3) -> 100 | AA16: =SUMPRODUCT(--(I16:W16<>""),--(I16:W16<>"NA"),I$3:W$3) -> 90 | AB16: =SUMPRODUCT((I16:W16="A")*Settings!$B$4+(I16:W16="B")*Settings!$B$5+(I16:W16="C")*Settings!$B$6+(I16:W16="D")*Settings!$B$7+(I16:W16="E")*Settings!$B$8,I$3:W$3) -> 71.25 | AC16: =IF(D16="","",IF(D16>=Settings!$B$39,1,IF(D16>=Settings!$B$40,2,IF(D16>=Settings!$B$41,3,4)))) -> 2 | AD16: =IF(AC16="","",IF(H16="",IF(C16="Memecoin",MAX(AC16,3),AC16),IF(H16>=4,MAX(AC16,H16),IF(C16="Memecoin",MAX(AC16,3),MAX(AC16,MIN(H16,AC16+1)))))) -> 2 | AE16: =IF(C16="","",IF(SUMPRODUCT((INDEX(Settings!$B$31:$P$34,MATCH(C16,Settings!$A$31:$A$34,0),0)=1)*(I16:W16<>"NA"))>0,"Group NA missing","OK")) -> OK
A17: SAND | B17: The Sandbox | C17: Chain / protocol | D17: =IF(AA17=0,"",ROUND(AB17/AA17*100,1)) -> 69.1 | E17: =IF(D17="","",ROUND(D17/10,1)) -> 6.9 | F17: =IF(Z17=0,0,AA17/Z17) -> 0.85 | G17: =IF(D17="","",IF(F17<Settings!$B$42,"Not rated (low coverage)",CHOOSE(AD17,"Exceptional","Strong","Average/Decent","Weak"))) -> Average/Decent | I17: A | J17: A | K17: E | L17: C | M17: B | O17: C | P17: C | Q17: C | R17: C | S17: A | T17: A | V17: D | W17: A | X17: 2026-10-05 | Y17: the-sandbox | Z17: =SUMPRODUCT(--(I17:W17<>"NA"),I$3:W$3) -> 100 | AA17: =SUMPRODUCT(--(I17:W17<>""),--(I17:W17<>"NA"),I$3:W$3) -> 85 | AB17: =SUMPRODUCT((I17:W17="A")*Settings!$B$4+(I17:W17="B")*Settings!$B$5+(I17:W17="C")*Settings!$B$6+(I17:W17="D")*Settings!$B$7+(I17:W17="E")*Settings!$B$8,I$3:W$3) -> 58.75 | AC17: =IF(D17="","",IF(D17>=Settings!$B$39,1,IF(D17>=Settings!$B$40,2,IF(D17>=Settings!$B$41,3,4)))) -> 3 | AD17: =IF(AC17="","",IF(H17="",IF(C17="Memecoin",MAX(AC17,3),AC17),IF(H17>=4,MAX(AC17,H17),IF(C17="Memecoin",MAX(AC17,3),MAX(AC17,MIN(H17,AC17+1)))))) -> 3 | AE17: =IF(C17="","",IF(SUMPRODUCT((INDEX(Settings!$B$31:$P$34,MATCH(C17,Settings!$A$31:$A$34,0),0)=1)*(I17:W17<>"NA"))>0,"Group NA missing","OK")) -> OK
A18: XMR | B18: Monero | C18: Money coin | D18: =IF(AA18=0,"",ROUND(AB18/AA18*100,1)) -> 77.9 | E18: =IF(D18="","",ROUND(D18/10,1)) -> 7.8 | F18: =IF(Z18=0,0,AA18/Z18) -> 0.94444444 | G18: =IF(D18="","",IF(F18<Settings!$B$42,"Not rated (low coverage)",CHOOSE(AD18,"Exceptional","Strong","Average/Decent","Weak"))) -> Strong | I18: A | J18: A | K18: A | L18: NA | M18: A | N18: D | O18: D | P18: B | Q18: C | R18: A | S18: A | T18: NA | V18: B | W18: A | X18: 2026-10-05 | Y18: monero | Z18: =SUMPRODUCT(--(I18:W18<>"NA"),I$3:W$3) -> 90 | AA18: =SUMPRODUCT(--(I18:W18<>""),--(I18:W18<>"NA"),I$3:W$3) -> 85 | AB18: =SUMPRODUCT((I18:W18="A")*Settings!$B$4+(I18:W18="B")*Settings!$B$5+(I18:W18="C")*Settings!$B$6+(I18:W18="D")*Settings!$B$7+(I18:W18="E")*Settings!$B$8,I$3:W$3) -> 66.25 | AC18: =IF(D18="","",IF(D18>=Settings!$B$39,1,IF(D18>=Settings!$B$40,2,IF(D18>=Settings!$B$41,3,4)))) -> 2 | AD18: =IF(AC18="","",IF(H18="",IF(C18="Memecoin",MAX(AC18,3),AC18),IF(H18>=4,MAX(AC18,H18),IF(C18="Memecoin",MAX(AC18,3),MAX(AC18,MIN(H18,AC18+1)))))) -> 2 | AE18: =IF(C18="","",IF(SUMPRODUCT((INDEX(Settings!$B$31:$P$34,MATCH(C18,Settings!$A$31:$A$34,0),0)=1)*(I18:W18<>"NA"))>0,"Group NA missing","OK")) -> OK
A19: ZEC | B19: Zcash | C19: Money coin | D19: =IF(AA19=0,"",ROUND(AB19/AA19*100,1)) -> 89.7 | E19: =IF(D19="","",ROUND(D19/10,1)) -> 9 | F19: =IF(Z19=0,0,AA19/Z19) -> 0.94444444 | G19: =IF(D19="","",IF(F19<Settings!$B$42,"Not rated (low coverage)",CHOOSE(AD19,"Exceptional","Strong","Average/Decent","Weak"))) -> Average/Decent | H19: 3 | I19: A | J19: A | K19: B | L19: NA | M19: A | N19: A | O19: C | P19: B | Q19: B | R19: A | S19: A | T19: NA | V19: B | W19: A | X19: 2026-10-05 | Y19: zcash | Z19: =SUMPRODUCT(--(I19:W19<>"NA"),I$3:W$3) -> 90 | AA19: =SUMPRODUCT(--(I19:W19<>""),--(I19:W19<>"NA"),I$3:W$3) -> 85 | AB19: =SUMPRODUCT((I19:W19="A")*Settings!$B$4+(I19:W19="B")*Settings!$B$5+(I19:W19="C")*Settings!$B$6+(I19:W19="D")*Settings!$B$7+(I19:W19="E")*Settings!$B$8,I$3:W$3) -> 76.25 | AC19: =IF(D19="","",IF(D19>=Settings!$B$39,1,IF(D19>=Settings!$B$40,2,IF(D19>=Settings!$B$41,3,4)))) -> 2 | AD19: =IF(AC19="","",IF(H19="",IF(C19="Memecoin",MAX(AC19,3),AC19),IF(H19>=4,MAX(AC19,H19),IF(C19="Memecoin",MAX(AC19,3),MAX(AC19,MIN(H19,AC19+1)))))) -> 3 | AE19: =IF(C19="","",IF(SUMPRODUCT((INDEX(Settings!$B$31:$P$34,MATCH(C19,Settings!$A$31:$A$34,0),0)=1)*(I19:W19<>"NA"))>0,"Group NA missing","OK")) -> OK
A20: DOGE | B20: Dogecoin | C20: Memecoin | D20: =IF(AA20=0,"",ROUND(AB20/AA20*100,1)) -> 77.9 | E20: =IF(D20="","",ROUND(D20/10,1)) -> 7.8 | F20: =IF(Z20=0,0,AA20/Z20) -> 0.94444444 | G20: =IF(D20="","",IF(F20<Settings!$B$42,"Not rated (low coverage)",CHOOSE(AD20,"Exceptional","Strong","Average/Decent","Weak"))) -> Average/Decent | H20: 3 | I20: A | J20: A | K20: A | L20: NA | M20: A | N20: B | O20: B | P20: B | Q20: A | R20: A | S20: E | T20: NA | V20: B | W20: C | X20: 2026-10-05 | Y20: dogecoin | Z20: =SUMPRODUCT(--(I20:W20<>"NA"),I$3:W$3) -> 90 | AA20: =SUMPRODUCT(--(I20:W20<>""),--(I20:W20<>"NA"),I$3:W$3) -> 85 | AB20: =SUMPRODUCT((I20:W20="A")*Settings!$B$4+(I20:W20="B")*Settings!$B$5+(I20:W20="C")*Settings!$B$6+(I20:W20="D")*Settings!$B$7+(I20:W20="E")*Settings!$B$8,I$3:W$3) -> 66.25 | AC20: =IF(D20="","",IF(D20>=Settings!$B$39,1,IF(D20>=Settings!$B$40,2,IF(D20>=Settings!$B$41,3,4)))) -> 2 | AD20: =IF(AC20="","",IF(H20="",IF(C20="Memecoin",MAX(AC20,3),AC20),IF(H20>=4,MAX(AC20,H20),IF(C20="Memecoin",MAX(AC20,3),MAX(AC20,MIN(H20,AC20+1)))))) -> 3 | AE20: =IF(C20="","",IF(SUMPRODUCT((INDEX(Settings!$B$31:$P$34,MATCH(C20,Settings!$A$31:$A$34,0),0)=1)*(I20:W20<>"NA"))>0,"Group NA missing","OK")) -> OK
A21: SHIB | B21: Shiba Inu | C21: Memecoin | D21: =IF(AA21=0,"",ROUND(AB21/AA21*100,1)) -> 60.9 | E21: =IF(D21="","",ROUND(D21/10,1)) -> 6.1 | F21: =IF(Z21=0,0,AA21/Z21) -> 0.88888889 | G21: =IF(D21="","",IF(F21<Settings!$B$42,"Not rated (low coverage)",CHOOSE(AD21,"Exceptional","Strong","Average/Decent","Weak"))) -> Average/Decent | H21: 3 | I21: A | J21: A | L21: NA | M21: B | N21: B | O21: C | P21: C | Q21: C | R21: C | S21: E | T21: NA | V21: C | W21: B | X21: 2026-10-05 | Y21: shiba-inu | Z21: =SUMPRODUCT(--(I21:W21<>"NA"),I$3:W$3) -> 90 | AA21: =SUMPRODUCT(--(I21:W21<>""),--(I21:W21<>"NA"),I$3:W$3) -> 80 | AB21: =SUMPRODUCT((I21:W21="A")*Settings!$B$4+(I21:W21="B")*Settings!$B$5+(I21:W21="C")*Settings!$B$6+(I21:W21="D")*Settings!$B$7+(I21:W21="E")*Settings!$B$8,I$3:W$3) -> 48.75 | AC21: =IF(D21="","",IF(D21>=Settings!$B$39,1,IF(D21>=Settings!$B$40,2,IF(D21>=Settings!$B$41,3,4)))) -> 3 | AD21: =IF(AC21="","",IF(H21="",IF(C21="Memecoin",MAX(AC21,3),AC21),IF(H21>=4,MAX(AC21,H21),IF(C21="Memecoin",MAX(AC21,3),MAX(AC21,MIN(H21,AC21+1)))))) -> 3 | AE21: =IF(C21="","",IF(SUMPRODUCT((INDEX(Settings!$B$31:$P$34,MATCH(C21,Settings!$A$31:$A$34,0),0)=1)*(I21:W21<>"NA"))>0,"Group NA missing","OK")) -> OK
A22: USDC | B22: USD Coin | C22: Stablecoin / RWA | D22: =IF(AA22=0,"",ROUND(AB22/AA22*100,1)) -> 78.8 | E22: =IF(D22="","",ROUND(D22/10,1)) -> 7.9 | F22: =IF(Z22=0,0,AA22/Z22) -> 1 | G22: =IF(D22="","",IF(F22<Settings!$B$42,"Not rated (low coverage)",CHOOSE(AD22,"Exceptional","Strong","Average/Decent","Weak"))) -> Strong | I22: NA | J22: NA | K22: NA | L22: NA | M22: A | N22: B | O22: D | P22: A | Q22: C | R22: B | S22: A | T22: NA | U22: A | V22: B | W22: NA | X22: 2026-10-05 | Y22: usd-coin | Z22: =SUMPRODUCT(--(I22:W22<>"NA"),I$3:W$3) -> 65 | AA22: =SUMPRODUCT(--(I22:W22<>""),--(I22:W22<>"NA"),I$3:W$3) -> 65 | AB22: =SUMPRODUCT((I22:W22="A")*Settings!$B$4+(I22:W22="B")*Settings!$B$5+(I22:W22="C")*Settings!$B$6+(I22:W22="D")*Settings!$B$7+(I22:W22="E")*Settings!$B$8,I$3:W$3) -> 51.25 | AC22: =IF(D22="","",IF(D22>=Settings!$B$39,1,IF(D22>=Settings!$B$40,2,IF(D22>=Settings!$B$41,3,4)))) -> 2 | AD22: =IF(AC22="","",IF(H22="",IF(C22="Memecoin",MAX(AC22,3),AC22),IF(H22>=4,MAX(AC22,H22),IF(C22="Memecoin",MAX(AC22,3),MAX(AC22,MIN(H22,AC22+1)))))) -> 2 | AE22: =IF(C22="","",IF(SUMPRODUCT((INDEX(Settings!$B$31:$P$34,MATCH(C22,Settings!$A$31:$A$34,0),0)=1)*(I22:W22<>"NA"))>0,"Group NA missing","OK")) -> OK
A23: USDT | B23: Tether | C23: Stablecoin / RWA | D23: =IF(AA23=0,"",ROUND(AB23/AA23*100,1)) -> 70.8 | E23: =IF(D23="","",ROUND(D23/10,1)) -> 7.1 | F23: =IF(Z23=0,0,AA23/Z23) -> 0.92307692 | G23: =IF(D23="","",IF(F23<Settings!$B$42,"Not rated (low coverage)",CHOOSE(AD23,"Exceptional","Strong","Average/Decent","Weak"))) -> Average/Decent | I23: NA | J23: NA | K23: NA | L23: NA | M23: A | N23: C | O23: C | P23: A | Q23: C | R23: E | S23: A | T23: NA | V23: A | W23: NA | X23: 2026-10-05 | Y23: tether | Z23: =SUMPRODUCT(--(I23:W23<>"NA"),I$3:W$3) -> 65 | AA23: =SUMPRODUCT(--(I23:W23<>""),--(I23:W23<>"NA"),I$3:W$3) -> 60 | AB23: =SUMPRODUCT((I23:W23="A")*Settings!$B$4+(I23:W23="B")*Settings!$B$5+(I23:W23="C")*Settings!$B$6+(I23:W23="D")*Settings!$B$7+(I23:W23="E")*Settings!$B$8,I$3:W$3) -> 42.5 | AC23: =IF(D23="","",IF(D23>=Settings!$B$39,1,IF(D23>=Settings!$B$40,2,IF(D23>=Settings!$B$41,3,4)))) -> 3 | AD23: =IF(AC23="","",IF(H23="",IF(C23="Memecoin",MAX(AC23,3),AC23),IF(H23>=4,MAX(AC23,H23),IF(C23="Memecoin",MAX(AC23,3),MAX(AC23,MIN(H23,AC23+1)))))) -> 3 | AE23: =IF(C23="","",IF(SUMPRODUCT((INDEX(Settings!$B$31:$P$34,MATCH(C23,Settings!$A$31:$A$34,0),0)=1)*(I23:W23<>"NA"))>0,"Group NA missing","OK")) -> OK
A24: LTC | B24: Litecoin | C24: Money coin | D24: =IF(AA24=0,"",ROUND(AB24/AA24*100,1)) -> 86.8 | E24: =IF(D24="","",ROUND(D24/10,1)) -> 8.7 | F24: =IF(Z24=0,0,AA24/Z24) -> 0.94444444 | G24: =IF(D24="","",IF(F24<Settings!$B$42,"Not rated (low coverage)",CHOOSE(AD24,"Exceptional","Strong","Average/Decent","Weak"))) -> Strong | I24: A | J24: A | K24: A | L24: NA | M24: A | N24: C | O24: B | P24: C | Q24: A | R24: A | S24: A | T24: NA | V24: C | W24: A | X24: 2026-10-05 | Y24: litecoin | Z24: =SUMPRODUCT(--(I24:W24<>"NA"),I$3:W$3) -> 90 | AA24: =SUMPRODUCT(--(I24:W24<>""),--(I24:W24<>"NA"),I$3:W$3) -> 85 | AB24: =SUMPRODUCT((I24:W24="A")*Settings!$B$4+(I24:W24="B")*Settings!$B$5+(I24:W24="C")*Settings!$B$6+(I24:W24="D")*Settings!$B$7+(I24:W24="E")*Settings!$B$8,I$3:W$3) -> 73.75 | AC24: =IF(D24="","",IF(D24>=Settings!$B$39,1,IF(D24>=Settings!$B$40,2,IF(D24>=Settings!$B$41,3,4)))) -> 2 | AD24: =IF(AC24="","",IF(H24="",IF(C24="Memecoin",MAX(AC24,3),AC24),IF(H24>=4,MAX(AC24,H24),IF(C24="Memecoin",MAX(AC24,3),MAX(AC24,MIN(H24,AC24+1)))))) -> 2 | AE24: =IF(C24="","",IF(SUMPRODUCT((INDEX(Settings!$B$31:$P$34,MATCH(C24,Settings!$A$31:$A$34,0),0)=1)*(I24:W24<>"NA"))>0,"Group NA missing","OK")) -> OK
A25: HYPE | B25: Hyperliquid | C25: Chain / protocol | D25: =IF(AA25=0,"",ROUND(AB25/AA25*100,1)) -> 60.9 | E25: =IF(D25="","",ROUND(D25/10,1)) -> 6.1 | F25: =IF(Z25=0,0,AA25/Z25) -> 0.84210526 | G25: =IF(D25="","",IF(F25<Settings!$B$42,"Not rated (low coverage)",CHOOSE(AD25,"Exceptional","Strong","Average/Decent","Weak"))) -> Average/Decent | I25: D | J25: E | K25: C | L25: A | M25: A | N25: E | O25: B | P25: C | S25: A | T25: NA | U25: A | V25: B | W25: B | X25: 2026-10-05 | Y25: hyperliquid | Z25: =SUMPRODUCT(--(I25:W25<>"NA"),I$3:W$3) -> 95 | AA25: =SUMPRODUCT(--(I25:W25<>""),--(I25:W25<>"NA"),I$3:W$3) -> 80 | AB25: =SUMPRODUCT((I25:W25="A")*Settings!$B$4+(I25:W25="B")*Settings!$B$5+(I25:W25="C")*Settings!$B$6+(I25:W25="D")*Settings!$B$7+(I25:W25="E")*Settings!$B$8,I$3:W$3) -> 48.75 | AC25: =IF(D25="","",IF(D25>=Settings!$B$39,1,IF(D25>=Settings!$B$40,2,IF(D25>=Settings!$B$41,3,4)))) -> 3 | AD25: =IF(AC25="","",IF(H25="",IF(C25="Memecoin",MAX(AC25,3),AC25),IF(H25>=4,MAX(AC25,H25),IF(C25="Memecoin",MAX(AC25,3),MAX(AC25,MIN(H25,AC25+1)))))) -> 3 | AE25: =IF(C25="","",IF(SUMPRODUCT((INDEX(Settings!$B$31:$P$34,MATCH(C25,Settings!$A$31:$A$34,0),0)=1)*(I25:W25<>"NA"))>0,"Group NA missing","OK")) -> OK
A26: QNT | B26: Quant | C26: Chain / protocol | D26: =IF(AA26=0,"",ROUND(AB26/AA26*100,1)) -> 76.7 | E26: =IF(D26="","",ROUND(D26/10,1)) -> 7.7 | F26: =IF(Z26=0,0,AA26/Z26) -> 0.75 | G26: =IF(D26="","",IF(F26<Settings!$B$42,"Not rated (low coverage)",CHOOSE(AD26,"Exceptional","Strong","Average/Decent","Weak"))) -> Strong | I26: A | M26: A | O26: D | P26: B | Q26: C | R26: D | S26: A | T26: B | U26: A | V26: C | W26: A | X26: 2026-10-05 | Y26: quant-network | Z26: =SUMPRODUCT(--(I26:W26<>"NA"),I$3:W$3) -> 100 | AA26: =SUMPRODUCT(--(I26:W26<>""),--(I26:W26<>"NA"),I$3:W$3) -> 75 | AB26: =SUMPRODUCT((I26:W26="A")*Settings!$B$4+(I26:W26="B")*Settings!$B$5+(I26:W26="C")*Settings!$B$6+(I26:W26="D")*Settings!$B$7+(I26:W26="E")*Settings!$B$8,I$3:W$3) -> 57.5 | AC26: =IF(D26="","",IF(D26>=Settings!$B$39,1,IF(D26>=Settings!$B$40,2,IF(D26>=Settings!$B$41,3,4)))) -> 2 | AD26: =IF(AC26="","",IF(H26="",IF(C26="Memecoin",MAX(AC26,3),AC26),IF(H26>=4,MAX(AC26,H26),IF(C26="Memecoin",MAX(AC26,3),MAX(AC26,MIN(H26,AC26+1)))))) -> 2 | AE26: =IF(C26="","",IF(SUMPRODUCT((INDEX(Settings!$B$31:$P$34,MATCH(C26,Settings!$A$31:$A$34,0),0)=1)*(I26:W26<>"NA"))>0,"Group NA missing","OK")) -> OK
A27: IMX | B27: Immutable | C27: Chain / protocol | D27: =IF(AA27=0,"",ROUND(AB27/AA27*100,1)) -> 58.8 | E27: =IF(D27="","",ROUND(D27/10,1)) -> 5.9 | F27: =IF(Z27=0,0,AA27/Z27) -> 0.85 | G27: =IF(D27="","",IF(F27<Settings!$B$42,"Not rated (low coverage)",CHOOSE(AD27,"Exceptional","Strong","Average/Decent","Weak"))) -> Weak | I27: C | J27: A | K27: D | M27: D | N27: D | O27: D | P27: A | Q27: B | S27: A | T27: A | V27: D | W27: B | X27: 2026-10-05 | Y27: immutable-x | Z27: =SUMPRODUCT(--(I27:W27<>"NA"),I$3:W$3) -> 100 | AA27: =SUMPRODUCT(--(I27:W27<>""),--(I27:W27<>"NA"),I$3:W$3) -> 85 | AB27: =SUMPRODUCT((I27:W27="A")*Settings!$B$4+(I27:W27="B")*Settings!$B$5+(I27:W27="C")*Settings!$B$6+(I27:W27="D")*Settings!$B$7+(I27:W27="E")*Settings!$B$8,I$3:W$3) -> 50 | AC27: =IF(D27="","",IF(D27>=Settings!$B$39,1,IF(D27>=Settings!$B$40,2,IF(D27>=Settings!$B$41,3,4)))) -> 4 | AD27: =IF(AC27="","",IF(H27="",IF(C27="Memecoin",MAX(AC27,3),AC27),IF(H27>=4,MAX(AC27,H27),IF(C27="Memecoin",MAX(AC27,3),MAX(AC27,MIN(H27,AC27+1)))))) -> 4 | AE27: =IF(C27="","",IF(SUMPRODUCT((INDEX(Settings!$B$31:$P$34,MATCH(C27,Settings!$A$31:$A$34,0),0)=1)*(I27:W27<>"NA"))>0,"Group NA missing","OK")) -> OK
A28: PAXG | B28: PAX Gold | C28: Stablecoin / RWA | D28: =IF(AA28=0,"",ROUND(AB28/AA28*100,1)) -> 75 | E28: =IF(D28="","",ROUND(D28/10,1)) -> 7.5 | F28: =IF(Z28=0,0,AA28/Z28) -> 0.76923077 | G28: =IF(D28="","",IF(F28<Settings!$B$42,"Not rated (low coverage)",CHOOSE(AD28,"Exceptional","Strong","Average/Decent","Weak"))) -> Strong | I28: NA | J28: NA | K28: NA | L28: NA | M28: A | O28: C | P28: A | Q28: C | R28: C | S28: A | T28: NA | V28: C | W28: NA | X28: 2026-10-05 | Y28: pax-gold | Z28: =SUMPRODUCT(--(I28:W28<>"NA"),I$3:W$3) -> 65 | AA28: =SUMPRODUCT(--(I28:W28<>""),--(I28:W28<>"NA"),I$3:W$3) -> 50 | AB28: =SUMPRODUCT((I28:W28="A")*Settings!$B$4+(I28:W28="B")*Settings!$B$5+(I28:W28="C")*Settings!$B$6+(I28:W28="D")*Settings!$B$7+(I28:W28="E")*Settings!$B$8,I$3:W$3) -> 37.5 | AC28: =IF(D28="","",IF(D28>=Settings!$B$39,1,IF(D28>=Settings!$B$40,2,IF(D28>=Settings!$B$41,3,4)))) -> 2 | AD28: =IF(AC28="","",IF(H28="",IF(C28="Memecoin",MAX(AC28,3),AC28),IF(H28>=4,MAX(AC28,H28),IF(C28="Memecoin",MAX(AC28,3),MAX(AC28,MIN(H28,AC28+1)))))) -> 2 | AE28: =IF(C28="","",IF(SUMPRODUCT((INDEX(Settings!$B$31:$P$34,MATCH(C28,Settings!$A$31:$A$34,0),0)=1)*(I28:W28<>"NA"))>0,"Group NA missing","OK")) -> OK
A29: RED | B29: RedStone | C29: Chain / protocol | D29: =IF(AA29=0,"",ROUND(AB29/AA29*100,1)) -> 46.4 | E29: =IF(D29="","",ROUND(D29/10,1)) -> 4.6 | F29: =IF(Z29=0,0,AA29/Z29) -> 0.7 | G29: =IF(D29="","",IF(F29<Settings!$B$42,"Not rated (low coverage)",CHOOSE(AD29,"Exceptional","Strong","Average/Decent","Weak"))) -> Weak | I29: C | J29: E | K29: E | M29: D | O29: C | P29: A | Q29: C | T29: C | U29: A | V29: E | W29: A | X29: 2026-10-05 | Y29: redstone-oracles | Z29: =SUMPRODUCT(--(I29:W29<>"NA"),I$3:W$3) -> 100 | AA29: =SUMPRODUCT(--(I29:W29<>""),--(I29:W29<>"NA"),I$3:W$3) -> 70 | AB29: =SUMPRODUCT((I29:W29="A")*Settings!$B$4+(I29:W29="B")*Settings!$B$5+(I29:W29="C")*Settings!$B$6+(I29:W29="D")*Settings!$B$7+(I29:W29="E")*Settings!$B$8,I$3:W$3) -> 32.5 | AC29: =IF(D29="","",IF(D29>=Settings!$B$39,1,IF(D29>=Settings!$B$40,2,IF(D29>=Settings!$B$41,3,4)))) -> 4 | AD29: =IF(AC29="","",IF(H29="",IF(C29="Memecoin",MAX(AC29,3),AC29),IF(H29>=4,MAX(AC29,H29),IF(C29="Memecoin",MAX(AC29,3),MAX(AC29,MIN(H29,AC29+1)))))) -> 4 | AE29: =IF(C29="","",IF(SUMPRODUCT((INDEX(Settings!$B$31:$P$34,MATCH(C29,Settings!$A$31:$A$34,0),0)=1)*(I29:W29<>"NA"))>0,"Group NA missing","OK")) -> OK
A30: FET | B30: Artificial Superintelligence Alliance | C30: Chain / protocol | D30: =IF(AA30=0,"",ROUND(AB30/AA30*100,1)) -> 71.4 | E30: =IF(D30="","",ROUND(D30/10,1)) -> 7.1 | F30: =IF(Z30=0,0,AA30/Z30) -> 0.7 | G30: =IF(D30="","",IF(F30<Settings!$B$42,"Not rated (low coverage)",CHOOSE(AD30,"Exceptional","Strong","Average/Decent","Weak"))) -> Average/Decent | H30: 3 | I30: A | J30: A | K30: C | M30: A | O30: B | P30: C | Q30: C | R30: D | T30: B | V30: D | W30: A | X30: 2026-10-05 | Y30: fetch-ai | Z30: =SUMPRODUCT(--(I30:W30<>"NA"),I$3:W$3) -> 100 | AA30: =SUMPRODUCT(--(I30:W30<>""),--(I30:W30<>"NA"),I$3:W$3) -> 70 | AB30: =SUMPRODUCT((I30:W30="A")*Settings!$B$4+(I30:W30="B")*Settings!$B$5+(I30:W30="C")*Settings!$B$6+(I30:W30="D")*Settings!$B$7+(I30:W30="E")*Settings!$B$8,I$3:W$3) -> 50 | AC30: =IF(D30="","",IF(D30>=Settings!$B$39,1,IF(D30>=Settings!$B$40,2,IF(D30>=Settings!$B$41,3,4)))) -> 3 | AD30: =IF(AC30="","",IF(H30="",IF(C30="Memecoin",MAX(AC30,3),AC30),IF(H30>=4,MAX(AC30,H30),IF(C30="Memecoin",MAX(AC30,3),MAX(AC30,MIN(H30,AC30+1)))))) -> 3 | AE30: =IF(C30="","",IF(SUMPRODUCT((INDEX(Settings!$B$31:$P$34,MATCH(C30,Settings!$A$31:$A$34,0),0)=1)*(I30:W30<>"NA"))>0,"Group NA missing","OK")) -> OK
A31: RAY | B31: Raydium | C31: Chain / protocol | D31: =IF(AA31=0,"",ROUND(AB31/AA31*100,1)) -> 55.9 | E31: =IF(D31="","",ROUND(D31/10,1)) -> 5.6 | F31: =IF(Z31=0,0,AA31/Z31) -> 0.89473684 | G31: =IF(D31="","",IF(F31<Settings!$B$42,"Not rated (low coverage)",CHOOSE(AD31,"Exceptional","Strong","Average/Decent","Weak"))) -> Weak | I31: C | J31: A | L31: C | M31: C | N31: E | O31: B | P31: C | Q31: C | R31: C | S31: A | T31: NA | V31: D | W31: A | X31: 2026-10-05 | Y31: raydium | Z31: =SUMPRODUCT(--(I31:W31<>"NA"),I$3:W$3) -> 95 | AA31: =SUMPRODUCT(--(I31:W31<>""),--(I31:W31<>"NA"),I$3:W$3) -> 85 | AB31: =SUMPRODUCT((I31:W31="A")*Settings!$B$4+(I31:W31="B")*Settings!$B$5+(I31:W31="C")*Settings!$B$6+(I31:W31="D")*Settings!$B$7+(I31:W31="E")*Settings!$B$8,I$3:W$3) -> 47.5 | AC31: =IF(D31="","",IF(D31>=Settings!$B$39,1,IF(D31>=Settings!$B$40,2,IF(D31>=Settings!$B$41,3,4)))) -> 4 | AD31: =IF(AC31="","",IF(H31="",IF(C31="Memecoin",MAX(AC31,3),AC31),IF(H31>=4,MAX(AC31,H31),IF(C31="Memecoin",MAX(AC31,3),MAX(AC31,MIN(H31,AC31+1)))))) -> 4 | AE31: =IF(C31="","",IF(SUMPRODUCT((INDEX(Settings!$B$31:$P$34,MATCH(C31,Settings!$A$31:$A$34,0),0)=1)*(I31:W31<>"NA"))>0,"Group NA missing","OK")) -> OK
A32: NIGHT | B32: Midnight | C32: Chain / protocol | D32: =IF(AA32=0,"",ROUND(AB32/AA32*100,1)) -> 70 | E32: =IF(D32="","",ROUND(D32/10,1)) -> 7 | F32: =IF(Z32=0,0,AA32/Z32) -> 0.78947368 | G32: =IF(D32="","",IF(F32<Settings!$B$42,"Not rated (low coverage)",CHOOSE(AD32,"Exceptional","Strong","Average/Decent","Weak"))) -> Average/Decent | H32: 3 | I32: B | J32: A | K32: C | L32: E | M32: A | O32: B | P32: C | Q32: C | S32: A | T32: NA | V32: D | W32: A | X32: 2026-10-05 | Y32: midnight-3 | Z32: =SUMPRODUCT(--(I32:W32<>"NA"),I$3:W$3) -> 95 | AA32: =SUMPRODUCT(--(I32:W32<>""),--(I32:W32<>"NA"),I$3:W$3) -> 75 | AB32: =SUMPRODUCT((I32:W32="A")*Settings!$B$4+(I32:W32="B")*Settings!$B$5+(I32:W32="C")*Settings!$B$6+(I32:W32="D")*Settings!$B$7+(I32:W32="E")*Settings!$B$8,I$3:W$3) -> 52.5 | AC32: =IF(D32="","",IF(D32>=Settings!$B$39,1,IF(D32>=Settings!$B$40,2,IF(D32>=Settings!$B$41,3,4)))) -> 3 | AD32: =IF(AC32="","",IF(H32="",IF(C32="Memecoin",MAX(AC32,3),AC32),IF(H32>=4,MAX(AC32,H32),IF(C32="Memecoin",MAX(AC32,3),MAX(AC32,MIN(H32,AC32+1)))))) -> 3 | AE32: =IF(C32="","",IF(SUMPRODUCT((INDEX(Settings!$B$31:$P$34,MATCH(C32,Settings!$A$31:$A$34,0),0)=1)*(I32:W32<>"NA"))>0,"Group NA missing","OK")) -> OK
A33: POWR | B33: Powerledger | C33: Chain / protocol | D33: =IF(AA33=0,"",ROUND(AB33/AA33*100,1)) -> 51.7 | E33: =IF(D33="","",ROUND(D33/10,1)) -> 5.2 | F33: =IF(Z33=0,0,AA33/Z33) -> 0.75 | G33: =IF(D33="","",IF(F33<Settings!$B$42,"Not rated (low coverage)",CHOOSE(AD33,"Exceptional","Strong","Average/Decent","Weak"))) -> Weak | I33: C | J33: D | M33: E | O33: D | P33: A | Q33: D | S33: A | T33: B | U33: A | V33: E | W33: A | X33: 2026-10-05 | Y33: power-ledger | Z33: =SUMPRODUCT(--(I33:W33<>"NA"),I$3:W$3) -> 100 | AA33: =SUMPRODUCT(--(I33:W33<>""),--(I33:W33<>"NA"),I$3:W$3) -> 75 | AB33: =SUMPRODUCT((I33:W33="A")*Settings!$B$4+(I33:W33="B")*Settings!$B$5+(I33:W33="C")*Settings!$B$6+(I33:W33="D")*Settings!$B$7+(I33:W33="E")*Settings!$B$8,I$3:W$3) -> 38.75 | AC33: =IF(D33="","",IF(D33>=Settings!$B$39,1,IF(D33>=Settings!$B$40,2,IF(D33>=Settings!$B$41,3,4)))) -> 4 | AD33: =IF(AC33="","",IF(H33="",IF(C33="Memecoin",MAX(AC33,3),AC33),IF(H33>=4,MAX(AC33,H33),IF(C33="Memecoin",MAX(AC33,3),MAX(AC33,MIN(H33,AC33+1)))))) -> 4 | AE33: =IF(C33="","",IF(SUMPRODUCT((INDEX(Settings!$B$31:$P$34,MATCH(C33,Settings!$A$31:$A$34,0),0)=1)*(I33:W33<>"NA"))>0,"Group NA missing","OK")) -> OK
A34: PEPE | B34: Pepe | C34: Memecoin | D34: =IF(AA34=0,"",ROUND(AB34/AA34*100,1)) -> 71.4 | E34: =IF(D34="","",ROUND(D34/10,1)) -> 7.1 | F34: =IF(Z34=0,0,AA34/Z34) -> 0.77777778 | G34: =IF(D34="","",IF(F34<Settings!$B$42,"Not rated (low coverage)",CHOOSE(AD34,"Exceptional","Strong","Average/Decent","Weak"))) -> Average/Decent | H34: 3 | I34: A | J34: A | K34: A | L34: NA | M34: A | O34: C | P34: A | R34: A | S34: E | T34: NA | U34: E | V34: C | W34: A | X34: 2026-10-05 | Y34: pepe | Z34: =SUMPRODUCT(--(I34:W34<>"NA"),I$3:W$3) -> 90 | AA34: =SUMPRODUCT(--(I34:W34<>""),--(I34:W34<>"NA"),I$3:W$3) -> 70 | AB34: =SUMPRODUCT((I34:W34="A")*Settings!$B$4+(I34:W34="B")*Settings!$B$5+(I34:W34="C")*Settings!$B$6+(I34:W34="D")*Settings!$B$7+(I34:W34="E")*Settings!$B$8,I$3:W$3) -> 50 | AC34: =IF(D34="","",IF(D34>=Settings!$B$39,1,IF(D34>=Settings!$B$40,2,IF(D34>=Settings!$B$41,3,4)))) -> 3 | AD34: =IF(AC34="","",IF(H34="",IF(C34="Memecoin",MAX(AC34,3),AC34),IF(H34>=4,MAX(AC34,H34),IF(C34="Memecoin",MAX(AC34,3),MAX(AC34,MIN(H34,AC34+1)))))) -> 3 | AE34: =IF(C34="","",IF(SUMPRODUCT((INDEX(Settings!$B$31:$P$34,MATCH(C34,Settings!$A$31:$A$34,0),0)=1)*(I34:W34<>"NA"))>0,"Group NA missing","OK")) -> OK
A35: CRO | B35: Cronos | C35: Chain / protocol | D35: =IF(AA35=0,"",ROUND(AB35/AA35*100,1)) -> 47.4 | E35: =IF(D35="","",ROUND(D35/10,1)) -> 4.7 | F35: =IF(Z35=0,0,AA35/Z35) -> 0.95 | G35: =IF(D35="","",IF(F35<Settings!$B$42,"Not rated (low coverage)",CHOOSE(AD35,"Exceptional","Strong","Average/Decent","Weak"))) -> Weak | H35: 3 | I35: C | J35: D | K35: E | M35: D | N35: E | O35: D | P35: D | Q35: B | R35: D | S35: A | T35: A | U35: A | V35: C | W35: C | X35: 2026-10-05 | Y35: crypto-com-chain | Z35: =SUMPRODUCT(--(I35:W35<>"NA"),I$3:W$3) -> 100 | AA35: =SUMPRODUCT(--(I35:W35<>""),--(I35:W35<>"NA"),I$3:W$3) -> 95 | AB35: =SUMPRODUCT((I35:W35="A")*Settings!$B$4+(I35:W35="B")*Settings!$B$5+(I35:W35="C")*Settings!$B$6+(I35:W35="D")*Settings!$B$7+(I35:W35="E")*Settings!$B$8,I$3:W$3) -> 45 | AC35: =IF(D35="","",IF(D35>=Settings!$B$39,1,IF(D35>=Settings!$B$40,2,IF(D35>=Settings!$B$41,3,4)))) -> 4 | AD35: =IF(AC35="","",IF(H35="",IF(C35="Memecoin",MAX(AC35,3),AC35),IF(H35>=4,MAX(AC35,H35),IF(C35="Memecoin",MAX(AC35,3),MAX(AC35,MIN(H35,AC35+1)))))) -> 4 | AE35: =IF(C35="","",IF(SUMPRODUCT((INDEX(Settings!$B$31:$P$34,MATCH(C35,Settings!$A$31:$A$34,0),0)=1)*(I35:W35<>"NA"))>0,"Group NA missing","OK")) -> OK
A36: AVAX | B36: Avalanche | C36: Chain / protocol | D36: =IF(AA36=0,"",ROUND(AB36/AA36*100,1)) -> 78.9 | E36: =IF(D36="","",ROUND(D36/10,1)) -> 7.9 | F36: =IF(Z36=0,0,AA36/Z36) -> 0.95 | G36: =IF(D36="","",IF(F36<Settings!$B$42,"Not rated (low coverage)",CHOOSE(AD36,"Exceptional","Strong","Average/Decent","Weak"))) -> Strong | I36: B | J36: B | K36: C | L36: B | M36: A | N36: D | O36: C | P36: A | Q36: A | S36: A | T36: A | U36: A | V36: C | W36: A | X36: 2026-10-05 | Y36: avalanche-2 | Z36: =SUMPRODUCT(--(I36:W36<>"NA"),I$3:W$3) -> 100 | AA36: =SUMPRODUCT(--(I36:W36<>""),--(I36:W36<>"NA"),I$3:W$3) -> 95 | AB36: =SUMPRODUCT((I36:W36="A")*Settings!$B$4+(I36:W36="B")*Settings!$B$5+(I36:W36="C")*Settings!$B$6+(I36:W36="D")*Settings!$B$7+(I36:W36="E")*Settings!$B$8,I$3:W$3) -> 75 | AC36: =IF(D36="","",IF(D36>=Settings!$B$39,1,IF(D36>=Settings!$B$40,2,IF(D36>=Settings!$B$41,3,4)))) -> 2 | AD36: =IF(AC36="","",IF(H36="",IF(C36="Memecoin",MAX(AC36,3),AC36),IF(H36>=4,MAX(AC36,H36),IF(C36="Memecoin",MAX(AC36,3),MAX(AC36,MIN(H36,AC36+1)))))) -> 2 | AE36: =IF(C36="","",IF(SUMPRODUCT((INDEX(Settings!$B$31:$P$34,MATCH(C36,Settings!$A$31:$A$34,0),0)=1)*(I36:W36<>"NA"))>0,"Group NA missing","OK")) -> OK
A37: HBAR | B37: Hedera | C37: Chain / protocol | D37: =IF(AA37=0,"",ROUND(AB37/AA37*100,1)) -> 72.2 | E37: =IF(D37="","",ROUND(D37/10,1)) -> 7.2 | F37: =IF(Z37=0,0,AA37/Z37) -> 0.9 | G37: =IF(D37="","",IF(F37<Settings!$B$42,"Not rated (low coverage)",CHOOSE(AD37,"Exceptional","Strong","Average/Decent","Weak"))) -> Average/Decent | I37: A | J37: A | K37: D | L37: E | M37: A | N37: E | O37: C | P37: A | Q37: A | S37: A | T37: A | V37: C | W37: B | X37: 2026-10-05 | Y37: hedera-hashgraph | Z37: =SUMPRODUCT(--(I37:W37<>"NA"),I$3:W$3) -> 100 | AA37: =SUMPRODUCT(--(I37:W37<>""),--(I37:W37<>"NA"),I$3:W$3) -> 90 | AB37: =SUMPRODUCT((I37:W37="A")*Settings!$B$4+(I37:W37="B")*Settings!$B$5+(I37:W37="C")*Settings!$B$6+(I37:W37="D")*Settings!$B$7+(I37:W37="E")*Settings!$B$8,I$3:W$3) -> 65 | AC37: =IF(D37="","",IF(D37>=Settings!$B$39,1,IF(D37>=Settings!$B$40,2,IF(D37>=Settings!$B$41,3,4)))) -> 3 | AD37: =IF(AC37="","",IF(H37="",IF(C37="Memecoin",MAX(AC37,3),AC37),IF(H37>=4,MAX(AC37,H37),IF(C37="Memecoin",MAX(AC37,3),MAX(AC37,MIN(H37,AC37+1)))))) -> 3 | AE37: =IF(C37="","",IF(SUMPRODUCT((INDEX(Settings!$B$31:$P$34,MATCH(C37,Settings!$A$31:$A$34,0),0)=1)*(I37:W37<>"NA"))>0,"Group NA missing","OK")) -> OK
A38: CAKE | B38: PancakeSwap | C38: Chain / protocol | D38: =IF(AA38=0,"",ROUND(AB38/AA38*100,1)) -> 54.4 | E38: =IF(D38="","",ROUND(D38/10,1)) -> 5.4 | F38: =IF(Z38=0,0,AA38/Z38) -> 0.85 | G38: =IF(D38="","",IF(F38<Settings!$B$42,"Not rated (low coverage)",CHOOSE(AD38,"Exceptional","Strong","Average/Decent","Weak"))) -> Weak | I38: B | J38: A | L38: C | M38: D | N38: E | O38: D | P38: A | Q38: C | S38: A | T38: D | V38: D | W38: A | X38: 2026-10-05 | Y38: pancakeswap-token | Z38: =SUMPRODUCT(--(I38:W38<>"NA"),I$3:W$3) -> 100 | AA38: =SUMPRODUCT(--(I38:W38<>""),--(I38:W38<>"NA"),I$3:W$3) -> 85 | AB38: =SUMPRODUCT((I38:W38="A")*Settings!$B$4+(I38:W38="B")*Settings!$B$5+(I38:W38="C")*Settings!$B$6+(I38:W38="D")*Settings!$B$7+(I38:W38="E")*Settings!$B$8,I$3:W$3) -> 46.25 | AC38: =IF(D38="","",IF(D38>=Settings!$B$39,1,IF(D38>=Settings!$B$40,2,IF(D38>=Settings!$B$41,3,4)))) -> 4 | AD38: =IF(AC38="","",IF(H38="",IF(C38="Memecoin",MAX(AC38,3),AC38),IF(H38>=4,MAX(AC38,H38),IF(C38="Memecoin",MAX(AC38,3),MAX(AC38,MIN(H38,AC38+1)))))) -> 4 | AE38: =IF(C38="","",IF(SUMPRODUCT((INDEX(Settings!$B$31:$P$34,MATCH(C38,Settings!$A$31:$A$34,0),0)=1)*(I38:W38<>"NA"))>0,"Group NA missing","OK")) -> OK
A39: SKY | B39: Sky | C39: Chain / protocol | D39: =IF(AA39=0,"",ROUND(AB39/AA39*100,1)) -> 64.1 | E39: =IF(D39="","",ROUND(D39/10,1)) -> 6.4 | F39: =IF(Z39=0,0,AA39/Z39) -> 0.8 | G39: =IF(D39="","",IF(F39<Settings!$B$42,"Not rated (low coverage)",CHOOSE(AD39,"Exceptional","Strong","Average/Decent","Weak"))) -> Average/Decent | I39: A | J39: A | L39: C | M39: D | N39: E | P39: A | Q39: C | S39: A | T39: B | V39: C | W39: A | X39: 2026-10-05 | Y39: sky | Z39: =SUMPRODUCT(--(I39:W39<>"NA"),I$3:W$3) -> 100 | AA39: =SUMPRODUCT(--(I39:W39<>""),--(I39:W39<>"NA"),I$3:W$3) -> 80 | AB39: =SUMPRODUCT((I39:W39="A")*Settings!$B$4+(I39:W39="B")*Settings!$B$5+(I39:W39="C")*Settings!$B$6+(I39:W39="D")*Settings!$B$7+(I39:W39="E")*Settings!$B$8,I$3:W$3) -> 51.25 | AC39: =IF(D39="","",IF(D39>=Settings!$B$39,1,IF(D39>=Settings!$B$40,2,IF(D39>=Settings!$B$41,3,4)))) -> 3 | AD39: =IF(AC39="","",IF(H39="",IF(C39="Memecoin",MAX(AC39,3),AC39),IF(H39>=4,MAX(AC39,H39),IF(C39="Memecoin",MAX(AC39,3),MAX(AC39,MIN(H39,AC39+1)))))) -> 3 | AE39: =IF(C39="","",IF(SUMPRODUCT((INDEX(Settings!$B$31:$P$34,MATCH(C39,Settings!$A$31:$A$34,0),0)=1)*(I39:W39<>"NA"))>0,"Group NA missing","OK")) -> OK
A40: XLM | B40: Stellar | C40: Chain / protocol | D40: =IF(AA40=0,"",ROUND(AB40/AA40*100,1)) -> 76.3 | E40: =IF(D40="","",ROUND(D40/10,1)) -> 7.6 | F40: =IF(Z40=0,0,AA40/Z40) -> 1 | G40: =IF(D40="","",IF(F40<Settings!$B$42,"Not rated (low coverage)",CHOOSE(AD40,"Exceptional","Strong","Average/Decent","Weak"))) -> Strong | I40: B | J40: B | K40: C | L40: D | M40: A | N40: B | O40: B | P40: A | Q40: A | R40: B | S40: A | T40: C | U40: A | V40: C | W40: D | X40: 2026-10-06 | Y40: stellar | Z40: =SUMPRODUCT(--(I40:W40<>"NA"),I$3:W$3) -> 100 | AA40: =SUMPRODUCT(--(I40:W40<>""),--(I40:W40<>"NA"),I$3:W$3) -> 100 | AB40: =SUMPRODUCT((I40:W40="A")*Settings!$B$4+(I40:W40="B")*Settings!$B$5+(I40:W40="C")*Settings!$B$6+(I40:W40="D")*Settings!$B$7+(I40:W40="E")*Settings!$B$8,I$3:W$3) -> 76.25 | AC40: =IF(D40="","",IF(D40>=Settings!$B$39,1,IF(D40>=Settings!$B$40,2,IF(D40>=Settings!$B$41,3,4)))) -> 2 | AD40: =IF(AC40="","",IF(H40="",IF(C40="Memecoin",MAX(AC40,3),AC40),IF(H40>=4,MAX(AC40,H40),IF(C40="Memecoin",MAX(AC40,3),MAX(AC40,MIN(H40,AC40+1)))))) -> 2 | AE40: =IF(C40="","",IF(SUMPRODUCT((INDEX(Settings!$B$31:$P$34,MATCH(C40,Settings!$A$31:$A$34,0),0)=1)*(I40:W40<>"NA"))>0,"Group NA missing","OK")) -> OK
A41: ENA | B41: Ethena | C41: Chain / protocol | D41: =IF(AA41=0,"",ROUND(AB41/AA41*100,1)) -> 57.5 | E41: =IF(D41="","",ROUND(D41/10,1)) -> 5.8 | F41: =IF(Z41=0,0,AA41/Z41) -> 1 | G41: =IF(D41="","",IF(F41<Settings!$B$42,"Not rated (low coverage)",CHOOSE(AD41,"Exceptional","Strong","Average/Decent","Weak"))) -> Weak | I41: B | J41: C | K41: E | L41: E | M41: B | N41: E | O41: D | P41: A | Q41: C | R41: D | S41: A | T41: A | U41: A | V41: C | W41: A | X41: 2026-10-06 | Y41: ethena | Z41: =SUMPRODUCT(--(I41:W41<>"NA"),I$3:W$3) -> 100 | AA41: =SUMPRODUCT(--(I41:W41<>""),--(I41:W41<>"NA"),I$3:W$3) -> 100 | AB41: =SUMPRODUCT((I41:W41="A")*Settings!$B$4+(I41:W41="B")*Settings!$B$5+(I41:W41="C")*Settings!$B$6+(I41:W41="D")*Settings!$B$7+(I41:W41="E")*Settings!$B$8,I$3:W$3) -> 57.5 | AC41: =IF(D41="","",IF(D41>=Settings!$B$39,1,IF(D41>=Settings!$B$40,2,IF(D41>=Settings!$B$41,3,4)))) -> 4 | AD41: =IF(AC41="","",IF(H41="",IF(C41="Memecoin",MAX(AC41,3),AC41),IF(H41>=4,MAX(AC41,H41),IF(C41="Memecoin",MAX(AC41,3),MAX(AC41,MIN(H41,AC41+1)))))) -> 4 | AE41: =IF(C41="","",IF(SUMPRODUCT((INDEX(Settings!$B$31:$P$34,MATCH(C41,Settings!$A$31:$A$34,0),0)=1)*(I41:W41<>"NA"))>0,"Group NA missing","OK")) -> OK
A42: GRASS | B42: Grass | C42: Chain / protocol | D42: =IF(AA42=0,"",ROUND(AB42/AA42*100,1)) -> 60.9 | E42: =IF(D42="","",ROUND(D42/10,1)) -> 6.1 | F42: =IF(Z42=0,0,AA42/Z42) -> 0.8 | G42: =IF(D42="","",IF(F42<Settings!$B$42,"Not rated (low coverage)",CHOOSE(AD42,"Exceptional","Strong","Average/Decent","Weak"))) -> Average/Decent | I42: B | J42: D | K42: D | M42: C | O42: C | P42: A | Q42: C | R42: C | S42: A | T42: C | V42: D | W42: A | X42: 2026-10-07 | Y42: grass | Z42: =SUMPRODUCT(--(I42:W42<>"NA"),I$3:W$3) -> 100 | AA42: =SUMPRODUCT(--(I42:W42<>""),--(I42:W42<>"NA"),I$3:W$3) -> 80 | AB42: =SUMPRODUCT((I42:W42="A")*Settings!$B$4+(I42:W42="B")*Settings!$B$5+(I42:W42="C")*Settings!$B$6+(I42:W42="D")*Settings!$B$7+(I42:W42="E")*Settings!$B$8,I$3:W$3) -> 48.75 | AC42: =IF(D42="","",IF(D42>=Settings!$B$39,1,IF(D42>=Settings!$B$40,2,IF(D42>=Settings!$B$41,3,4)))) -> 3 | AD42: =IF(AC42="","",IF(H42="",IF(C42="Memecoin",MAX(AC42,3),AC42),IF(H42>=4,MAX(AC42,H42),IF(C42="Memecoin",MAX(AC42,3),MAX(AC42,MIN(H42,AC42+1)))))) -> 3 | AE42: =IF(C42="","",IF(SUMPRODUCT((INDEX(Settings!$B$31:$P$34,MATCH(C42,Settings!$A$31:$A$34,0),0)=1)*(I42:W42<>"NA"))>0,"Group NA missing","OK")) -> OK

Sheet Schedule
A1: SCHEDULE: when each coin is due for reassessment
A2: Held coins every 13 weeks, every other coin every 26 weeks; slots are spread so about the same number comes due each week. Written by crypto_review_schedule.py: run it after any coin is added or reassessed, or after buying or selling a coin, then re-import the calendar file.
A3: Schedule written 2026-10-08 (week of 2026-10-05).
J5: CALENDAR: the next 52 weeks
A6: Ticker | B6: Held | C6: Every (weeks) | D6: Last evaluated | E6: Next review (week of) | F6: Status | G6: Tier | H6: Last evaluated when scheduled | J6: Week of (Monday) | K6: Coins I hold (quarterly) | L6: Other coins (twice a year) | M6: Count
A7: BTC | B7: yes | C7: =IF(B7="yes",13,26) -> 13 | D7: =IFERROR(INDEX(Grades!$X:$X,MATCH(A7,Grades!$A:$A,0)),"") -> 2026-10-05 | E7: 46307 | F7: =IF(E7="","",IF(E7<TODAY()-WEEKDAY(TODAY(),3),"Overdue",IF(E7=TODAY()-WEEKDAY(TODAY(),3),"This week",IF(E7=TODAY()-WEEKDAY(TODAY(),3)+7,"Next week","")))) -> Next week | G7: =IFERROR(INDEX(Grades!$G:$G,MATCH(A7,Grades!$A:$A,0)),"") -> Exceptional | H7: 46300 | J7: 46300 | M7: 0
A8: ETH | B8: yes | C8: =IF(B8="yes",13,26) -> 13 | D8: =IFERROR(INDEX(Grades!$X:$X,MATCH(A8,Grades!$A:$A,0)),"") -> 2026-10-07 | E8: 46314 | F8: =IF(E8="","",IF(E8<TODAY()-WEEKDAY(TODAY(),3),"Overdue",IF(E8=TODAY()-WEEKDAY(TODAY(),3),"This week",IF(E8=TODAY()-WEEKDAY(TODAY(),3)+7,"Next week","")))) | G8: =IFERROR(INDEX(Grades!$G:$G,MATCH(A8,Grades!$A:$A,0)),"") -> Strong | H8: 46302 | J8: 46307 | K8: BTC, ENA | M8: 2
A9: SOL | B9: yes | C9: =IF(B9="yes",13,26) -> 13 | D9: =IFERROR(INDEX(Grades!$X:$X,MATCH(A9,Grades!$A:$A,0)),"") -> 2026-10-05 | E9: 46321 | F9: =IF(E9="","",IF(E9<TODAY()-WEEKDAY(TODAY(),3),"Overdue",IF(E9=TODAY()-WEEKDAY(TODAY(),3),"This week",IF(E9=TODAY()-WEEKDAY(TODAY(),3)+7,"Next week","")))) | G9: =IFERROR(INDEX(Grades!$G:$G,MATCH(A9,Grades!$A:$A,0)),"") -> Strong | H9: 46300 | J9: 46314 | K9: ETH | L9: XRP | M9: 2
A10: XRP | B10: no | C10: =IF(B10="yes",13,26) -> 26 | D10: =IFERROR(INDEX(Grades!$X:$X,MATCH(A10,Grades!$A:$A,0)),"") -> 2026-10-05 | E10: 46314 | F10: =IF(E10="","",IF(E10<TODAY()-WEEKDAY(TODAY(),3),"Overdue",IF(E10=TODAY()-WEEKDAY(TODAY(),3),"This week",IF(E10=TODAY()-WEEKDAY(TODAY(),3)+7,"Next week","")))) | G10: =IFERROR(INDEX(Grades!$G:$G,MATCH(A10,Grades!$A:$A,0)),"") -> Average/Decent | H10: 46300 | J10: 46321 | K10: SOL | L10: UNI | M10: 2
A11: NEAR | B11: yes | C11: =IF(B11="yes",13,26) -> 13 | D11: =IFERROR(INDEX(Grades!$X:$X,MATCH(A11,Grades!$A:$A,0)),"") -> 2026-10-05 | E11: 46328 | F11: =IF(E11="","",IF(E11<TODAY()-WEEKDAY(TODAY(),3),"Overdue",IF(E11=TODAY()-WEEKDAY(TODAY(),3),"This week",IF(E11=TODAY()-WEEKDAY(TODAY(),3)+7,"Next week","")))) | G11: =IFERROR(INDEX(Grades!$G:$G,MATCH(A11,Grades!$A:$A,0)),"") -> Average/Decent | H11: 46300 | J11: 46328 | K11: NEAR | L11: AAVE | M11: 2
A12: LINK | B12: yes | C12: =IF(B12="yes",13,26) -> 13 | D12: =IFERROR(INDEX(Grades!$X:$X,MATCH(A12,Grades!$A:$A,0)),"") -> 2026-10-05 | E12: 46335 | F12: =IF(E12="","",IF(E12<TODAY()-WEEKDAY(TODAY(),3),"Overdue",IF(E12=TODAY()-WEEKDAY(TODAY(),3),"This week",IF(E12=TODAY()-WEEKDAY(TODAY(),3)+7,"Next week","")))) | G12: =IFERROR(INDEX(Grades!$G:$G,MATCH(A12,Grades!$A:$A,0)),"") -> Strong | H12: 46300 | J12: 46335 | K12: LINK | L12: TAO | M12: 2
A13: UNI | B13: no | C13: =IF(B13="yes",13,26) -> 26 | D13: =IFERROR(INDEX(Grades!$X:$X,MATCH(A13,Grades!$A:$A,0)),"") -> 2026-10-05 | E13: 46321 | F13: =IF(E13="","",IF(E13<TODAY()-WEEKDAY(TODAY(),3),"Overdue",IF(E13=TODAY()-WEEKDAY(TODAY(),3),"This week",IF(E13=TODAY()-WEEKDAY(TODAY(),3)+7,"Next week","")))) | G13: =IFERROR(INDEX(Grades!$G:$G,MATCH(A13,Grades!$A:$A,0)),"") -> Average/Decent | H13: 46300 | J13: 46342 | K13: ONDO | L13: BNB | M13: 2
A14: AAVE | B14: no | C14: =IF(B14="yes",13,26) -> 26 | D14: =IFERROR(INDEX(Grades!$X:$X,MATCH(A14,Grades!$A:$A,0)),"") -> 2026-10-05 | E14: 46328 | F14: =IF(E14="","",IF(E14<TODAY()-WEEKDAY(TODAY(),3),"Overdue",IF(E14=TODAY()-WEEKDAY(TODAY(),3),"This week",IF(E14=TODAY()-WEEKDAY(TODAY(),3)+7,"Next week","")))) | G14: =IFERROR(INDEX(Grades!$G:$G,MATCH(A14,Grades!$A:$A,0)),"") -> Strong | H14: 46300 | J14: 46349 | K14: LTC | L14: RENDER | M14: 2
A15: ONDO | B15: yes | C15: =IF(B15="yes",13,26) -> 13 | D15: =IFERROR(INDEX(Grades!$X:$X,MATCH(A15,Grades!$A:$A,0)),"") -> 2026-10-05 | E15: 46342 | F15: =IF(E15="","",IF(E15<TODAY()-WEEKDAY(TODAY(),3),"Overdue",IF(E15=TODAY()-WEEKDAY(TODAY(),3),"This week",IF(E15=TODAY()-WEEKDAY(TODAY(),3)+7,"Next week","")))) | G15: =IFERROR(INDEX(Grades!$G:$G,MATCH(A15,Grades!$A:$A,0)),"") -> Average/Decent | H15: 46300 | J15: 46356 | K15: HYPE | L15: SAND | M15: 2
A16: TAO | B16: no | C16: =IF(B16="yes",13,26) -> 26 | D16: =IFERROR(INDEX(Grades!$X:$X,MATCH(A16,Grades!$A:$A,0)),"") -> 2026-10-05 | E16: 46335 | F16: =IF(E16="","",IF(E16<TODAY()-WEEKDAY(TODAY(),3),"Overdue",IF(E16=TODAY()-WEEKDAY(TODAY(),3),"This week",IF(E16=TODAY()-WEEKDAY(TODAY(),3)+7,"Next week","")))) | G16: =IFERROR(INDEX(Grades!$G:$G,MATCH(A16,Grades!$A:$A,0)),"") -> Average/Decent | H16: 46300 | J16: 46363 | K16: QNT | L16: XMR | M16: 2
A17: BNB | B17: no | C17: =IF(B17="yes",13,26) -> 26 | D17: =IFERROR(INDEX(Grades!$X:$X,MATCH(A17,Grades!$A:$A,0)),"") -> 2026-10-05 | E17: 46342 | F17: =IF(E17="","",IF(E17<TODAY()-WEEKDAY(TODAY(),3),"Overdue",IF(E17=TODAY()-WEEKDAY(TODAY(),3),"This week",IF(E17=TODAY()-WEEKDAY(TODAY(),3)+7,"Next week","")))) | G17: =IFERROR(INDEX(Grades!$G:$G,MATCH(A17,Grades!$A:$A,0)),"") -> Average/Decent | H17: 46300 | J17: 46370 | K17: PAXG | L17: ZEC | M17: 2
A18: RENDER | B18: no | C18: =IF(B18="yes",13,26) -> 26 | D18: =IFERROR(INDEX(Grades!$X:$X,MATCH(A18,Grades!$A:$A,0)),"") -> 2026-10-05 | E18: 46349 | F18: =IF(E18="","",IF(E18<TODAY()-WEEKDAY(TODAY(),3),"Overdue",IF(E18=TODAY()-WEEKDAY(TODAY(),3),"This week",IF(E18=TODAY()-WEEKDAY(TODAY(),3)+7,"Next week","")))) | G18: =IFERROR(INDEX(Grades!$G:$G,MATCH(A18,Grades!$A:$A,0)),"") -> Strong | H18: 46300 | J18: 46377 | K18: AVAX | L18: DOGE | M18: 2
A19: SAND | B19: no | C19: =IF(B19="yes",13,26) -> 26 | D19: =IFERROR(INDEX(Grades!$X:$X,MATCH(A19,Grades!$A:$A,0)),"") -> 2026-10-05 | E19: 46356 | F19: =IF(E19="","",IF(E19<TODAY()-WEEKDAY(TODAY(),3),"Overdue",IF(E19=TODAY()-WEEKDAY(TODAY(),3),"This week",IF(E19=TODAY()-WEEKDAY(TODAY(),3)+7,"Next week","")))) | G19: =IFERROR(INDEX(Grades!$G:$G,MATCH(A19,Grades!$A:$A,0)),"") -> Average/Decent | H19: 46300 | J19: 46384 | K19: HBAR | L19: SHIB | M19: 2
A20: XMR | B20: no | C20: =IF(B20="yes",13,26) -> 26 | D20: =IFERROR(INDEX(Grades!$X:$X,MATCH(A20,Grades!$A:$A,0)),"") -> 2026-10-05 | E20: 46363 | F20: =IF(E20="","",IF(E20<TODAY()-WEEKDAY(TODAY(),3),"Overdue",IF(E20=TODAY()-WEEKDAY(TODAY(),3),"This week",IF(E20=TODAY()-WEEKDAY(TODAY(),3)+7,"Next week","")))) | G20: =IFERROR(INDEX(Grades!$G:$G,MATCH(A20,Grades!$A:$A,0)),"") -> Strong | H20: 46300 | J20: 46391 | K20: XLM | L20: USDC | M20: 2
A21: ZEC | B21: no | C21: =IF(B21="yes",13,26) -> 26 | D21: =IFERROR(INDEX(Grades!$X:$X,MATCH(A21,Grades!$A:$A,0)),"") -> 2026-10-05 | E21: 46370 | F21: =IF(E21="","",IF(E21<TODAY()-WEEKDAY(TODAY(),3),"Overdue",IF(E21=TODAY()-WEEKDAY(TODAY(),3),"This week",IF(E21=TODAY()-WEEKDAY(TODAY(),3)+7,"Next week","")))) | G21: =IFERROR(INDEX(Grades!$G:$G,MATCH(A21,Grades!$A:$A,0)),"") -> Average/Decent | H21: 46300 | J21: 46398 | K21: BTC, ENA | M21: 2
A22: DOGE | B22: no | C22: =IF(B22="yes",13,26) -> 26 | D22: =IFERROR(INDEX(Grades!$X:$X,MATCH(A22,Grades!$A:$A,0)),"") -> 2026-10-05 | E22: 46377 | F22: =IF(E22="","",IF(E22<TODAY()-WEEKDAY(TODAY(),3),"Overdue",IF(E22=TODAY()-WEEKDAY(TODAY(),3),"This week",IF(E22=TODAY()-WEEKDAY(TODAY(),3)+7,"Next week","")))) | G22: =IFERROR(INDEX(Grades!$G:$G,MATCH(A22,Grades!$A:$A,0)),"") -> Average/Decent | H22: 46300 | J22: 46405 | K22: ETH | L22: USDT | M22: 2
A23: SHIB | B23: no | C23: =IF(B23="yes",13,26) -> 26 | D23: =IFERROR(INDEX(Grades!$X:$X,MATCH(A23,Grades!$A:$A,0)),"") -> 2026-10-05 | E23: 46384 | F23: =IF(E23="","",IF(E23<TODAY()-WEEKDAY(TODAY(),3),"Overdue",IF(E23=TODAY()-WEEKDAY(TODAY(),3),"This week",IF(E23=TODAY()-WEEKDAY(TODAY(),3)+7,"Next week","")))) | G23: =IFERROR(INDEX(Grades!$G:$G,MATCH(A23,Grades!$A:$A,0)),"") -> Average/Decent | H23: 46300 | J23: 46412 | K23: SOL | L23: IMX | M23: 2
A24: USDC | B24: no | C24: =IF(B24="yes",13,26) -> 26 | D24: =IFERROR(INDEX(Grades!$X:$X,MATCH(A24,Grades!$A:$A,0)),"") -> 2026-10-05 | E24: 46391 | F24: =IF(E24="","",IF(E24<TODAY()-WEEKDAY(TODAY(),3),"Overdue",IF(E24=TODAY()-WEEKDAY(TODAY(),3),"This week",IF(E24=TODAY()-WEEKDAY(TODAY(),3)+7,"Next week","")))) | G24: =IFERROR(INDEX(Grades!$G:$G,MATCH(A24,Grades!$A:$A,0)),"") -> Strong | H24: 46300 | J24: 46419 | K24: NEAR | L24: RED | M24: 2
A25: USDT | B25: no | C25: =IF(B25="yes",13,26) -> 26 | D25: =IFERROR(INDEX(Grades!$X:$X,MATCH(A25,Grades!$A:$A,0)),"") -> 2026-10-05 | E25: 46405 | F25: =IF(E25="","",IF(E25<TODAY()-WEEKDAY(TODAY(),3),"Overdue",IF(E25=TODAY()-WEEKDAY(TODAY(),3),"This week",IF(E25=TODAY()-WEEKDAY(TODAY(),3)+7,"Next week","")))) | G25: =IFERROR(INDEX(Grades!$G:$G,MATCH(A25,Grades!$A:$A,0)),"") -> Average/Decent | H25: 46300 | J25: 46426 | K25: LINK | L25: FET | M25: 2
A26: LTC | B26: yes | C26: =IF(B26="yes",13,26) -> 13 | D26: =IFERROR(INDEX(Grades!$X:$X,MATCH(A26,Grades!$A:$A,0)),"") -> 2026-10-05 | E26: 46349 | F26: =IF(E26="","",IF(E26<TODAY()-WEEKDAY(TODAY(),3),"Overdue",IF(E26=TODAY()-WEEKDAY(TODAY(),3),"This week",IF(E26=TODAY()-WEEKDAY(TODAY(),3)+7,"Next week","")))) | G26: =IFERROR(INDEX(Grades!$G:$G,MATCH(A26,Grades!$A:$A,0)),"") -> Strong | H26: 46300 | J26: 46433 | K26: ONDO | L26: RAY | M26: 2
A27: HYPE | B27: yes | C27: =IF(B27="yes",13,26) -> 13 | D27: =IFERROR(INDEX(Grades!$X:$X,MATCH(A27,Grades!$A:$A,0)),"") -> 2026-10-05 | E27: 46356 | F27: =IF(E27="","",IF(E27<TODAY()-WEEKDAY(TODAY(),3),"Overdue",IF(E27=TODAY()-WEEKDAY(TODAY(),3),"This week",IF(E27=TODAY()-WEEKDAY(TODAY(),3)+7,"Next week","")))) | G27: =IFERROR(INDEX(Grades!$G:$G,MATCH(A27,Grades!$A:$A,0)),"") -> Average/Decent | H27: 46300 | J27: 46440 | K27: LTC | L27: NIGHT | M27: 2
A28: QNT | B28: yes | C28: =IF(B28="yes",13,26) -> 13 | D28: =IFERROR(INDEX(Grades!$X:$X,MATCH(A28,Grades!$A:$A,0)),"") -> 2026-10-05 | E28: 46363 | F28: =IF(E28="","",IF(E28<TODAY()-WEEKDAY(TODAY(),3),"Overdue",IF(E28=TODAY()-WEEKDAY(TODAY(),3),"This week",IF(E28=TODAY()-WEEKDAY(TODAY(),3)+7,"Next week","")))) | G28: =IFERROR(INDEX(Grades!$G:$G,MATCH(A28,Grades!$A:$A,0)),"") -> Strong | H28: 46300 | J28: 46447 | K28: HYPE | L28: POWR | M28: 2
A29: IMX | B29: no | C29: =IF(B29="yes",13,26) -> 26 | D29: =IFERROR(INDEX(Grades!$X:$X,MATCH(A29,Grades!$A:$A,0)),"") -> 2026-10-05 | E29: 46412 | F29: =IF(E29="","",IF(E29<TODAY()-WEEKDAY(TODAY(),3),"Overdue",IF(E29=TODAY()-WEEKDAY(TODAY(),3),"This week",IF(E29=TODAY()-WEEKDAY(TODAY(),3)+7,"Next week","")))) | G29: =IFERROR(INDEX(Grades!$G:$G,MATCH(A29,Grades!$A:$A,0)),"") -> Weak | H29: 46300 | J29: 46454 | K29: QNT | L29: PEPE | M29: 2
A30: PAXG | B30: yes | C30: =IF(B30="yes",13,26) -> 13 | D30: =IFERROR(INDEX(Grades!$X:$X,MATCH(A30,Grades!$A:$A,0)),"") -> 2026-10-05 | E30: 46370 | F30: =IF(E30="","",IF(E30<TODAY()-WEEKDAY(TODAY(),3),"Overdue",IF(E30=TODAY()-WEEKDAY(TODAY(),3),"This week",IF(E30=TODAY()-WEEKDAY(TODAY(),3)+7,"Next week","")))) | G30: =IFERROR(INDEX(Grades!$G:$G,MATCH(A30,Grades!$A:$A,0)),"") -> Strong | H30: 46300 | J30: 46461 | K30: PAXG | L30: CRO | M30: 2
A31: RED | B31: no | C31: =IF(B31="yes",13,26) -> 26 | D31: =IFERROR(INDEX(Grades!$X:$X,MATCH(A31,Grades!$A:$A,0)),"") -> 2026-10-05 | E31: 46419 | F31: =IF(E31="","",IF(E31<TODAY()-WEEKDAY(TODAY(),3),"Overdue",IF(E31=TODAY()-WEEKDAY(TODAY(),3),"This week",IF(E31=TODAY()-WEEKDAY(TODAY(),3)+7,"Next week","")))) | G31: =IFERROR(INDEX(Grades!$G:$G,MATCH(A31,Grades!$A:$A,0)),"") -> Weak | H31: 46300 | J31: 46468 | K31: AVAX | L31: CAKE | M31: 2
A32: FET | B32: no | C32: =IF(B32="yes",13,26) -> 26 | D32: =IFERROR(INDEX(Grades!$X:$X,MATCH(A32,Grades!$A:$A,0)),"") -> 2026-10-05 | E32: 46426 | F32: =IF(E32="","",IF(E32<TODAY()-WEEKDAY(TODAY(),3),"Overdue",IF(E32=TODAY()-WEEKDAY(TODAY(),3),"This week",IF(E32=TODAY()-WEEKDAY(TODAY(),3)+7,"Next week","")))) | G32: =IFERROR(INDEX(Grades!$G:$G,MATCH(A32,Grades!$A:$A,0)),"") -> Average/Decent | H32: 46300 | J32: 46475 | K32: HBAR | L32: SKY | M32: 2
A33: RAY | B33: no | C33: =IF(B33="yes",13,26) -> 26 | D33: =IFERROR(INDEX(Grades!$X:$X,MATCH(A33,Grades!$A:$A,0)),"") -> 2026-10-05 | E33: 46433 | F33: =IF(E33="","",IF(E33<TODAY()-WEEKDAY(TODAY(),3),"Overdue",IF(E33=TODAY()-WEEKDAY(TODAY(),3),"This week",IF(E33=TODAY()-WEEKDAY(TODAY(),3)+7,"Next week","")))) | G33: =IFERROR(INDEX(Grades!$G:$G,MATCH(A33,Grades!$A:$A,0)),"") -> Weak | H33: 46300 | J33: 46482 | K33: XLM | L33: GRASS | M33: 2
A34: NIGHT | B34: no | C34: =IF(B34="yes",13,26) -> 26 | D34: =IFERROR(INDEX(Grades!$X:$X,MATCH(A34,Grades!$A:$A,0)),"") -> 2026-10-05 | E34: 46440 | F34: =IF(E34="","",IF(E34<TODAY()-WEEKDAY(TODAY(),3),"Overdue",IF(E34=TODAY()-WEEKDAY(TODAY(),3),"This week",IF(E34=TODAY()-WEEKDAY(TODAY(),3)+7,"Next week","")))) | G34: =IFERROR(INDEX(Grades!$G:$G,MATCH(A34,Grades!$A:$A,0)),"") -> Average/Decent | H34: 46300 | J34: 46489 | K34: BTC, ENA | M34: 2
A35: POWR | B35: no | C35: =IF(B35="yes",13,26) -> 26 | D35: =IFERROR(INDEX(Grades!$X:$X,MATCH(A35,Grades!$A:$A,0)),"") -> 2026-10-05 | E35: 46447 | F35: =IF(E35="","",IF(E35<TODAY()-WEEKDAY(TODAY(),3),"Overdue",IF(E35=TODAY()-WEEKDAY(TODAY(),3),"This week",IF(E35=TODAY()-WEEKDAY(TODAY(),3)+7,"Next week","")))) | G35: =IFERROR(INDEX(Grades!$G:$G,MATCH(A35,Grades!$A:$A,0)),"") -> Weak | H35: 46300 | J35: 46496 | K35: ETH | L35: XRP | M35: 2
A36: PEPE | B36: no | C36: =IF(B36="yes",13,26) -> 26 | D36: =IFERROR(INDEX(Grades!$X:$X,MATCH(A36,Grades!$A:$A,0)),"") -> 2026-10-05 | E36: 46454 | F36: =IF(E36="","",IF(E36<TODAY()-WEEKDAY(TODAY(),3),"Overdue",IF(E36=TODAY()-WEEKDAY(TODAY(),3),"This week",IF(E36=TODAY()-WEEKDAY(TODAY(),3)+7,"Next week","")))) | G36: =IFERROR(INDEX(Grades!$G:$G,MATCH(A36,Grades!$A:$A,0)),"") -> Average/Decent | H36: 46300 | J36: 46503 | K36: SOL | L36: UNI | M36: 2
A37: CRO | B37: no | C37: =IF(B37="yes",13,26) -> 26 | D37: =IFERROR(INDEX(Grades!$X:$X,MATCH(A37,Grades!$A:$A,0)),"") -> 2026-10-05 | E37: 46461 | F37: =IF(E37="","",IF(E37<TODAY()-WEEKDAY(TODAY(),3),"Overdue",IF(E37=TODAY()-WEEKDAY(TODAY(),3),"This week",IF(E37=TODAY()-WEEKDAY(TODAY(),3)+7,"Next week","")))) | G37: =IFERROR(INDEX(Grades!$G:$G,MATCH(A37,Grades!$A:$A,0)),"") -> Weak | H37: 46300 | J37: 46510 | K37: NEAR | L37: AAVE | M37: 2
A38: AVAX | B38: yes | C38: =IF(B38="yes",13,26) -> 13 | D38: =IFERROR(INDEX(Grades!$X:$X,MATCH(A38,Grades!$A:$A,0)),"") -> 2026-10-05 | E38: 46377 | F38: =IF(E38="","",IF(E38<TODAY()-WEEKDAY(TODAY(),3),"Overdue",IF(E38=TODAY()-WEEKDAY(TODAY(),3),"This week",IF(E38=TODAY()-WEEKDAY(TODAY(),3)+7,"Next week","")))) | G38: =IFERROR(INDEX(Grades!$G:$G,MATCH(A38,Grades!$A:$A,0)),"") -> Strong | H38: 46300 | J38: 46517 | K38: LINK | L38: TAO | M38: 2
A39: HBAR | B39: yes | C39: =IF(B39="yes",13,26) -> 13 | D39: =IFERROR(INDEX(Grades!$X:$X,MATCH(A39,Grades!$A:$A,0)),"") -> 2026-10-05 | E39: 46384 | F39: =IF(E39="","",IF(E39<TODAY()-WEEKDAY(TODAY(),3),"Overdue",IF(E39=TODAY()-WEEKDAY(TODAY(),3),"This week",IF(E39=TODAY()-WEEKDAY(TODAY(),3)+7,"Next week","")))) | G39: =IFERROR(INDEX(Grades!$G:$G,MATCH(A39,Grades!$A:$A,0)),"") -> Average/Decent | H39: 46300 | J39: 46524 | K39: ONDO | L39: BNB | M39: 2
A40: CAKE | B40: no | C40: =IF(B40="yes",13,26) -> 26 | D40: =IFERROR(INDEX(Grades!$X:$X,MATCH(A40,Grades!$A:$A,0)),"") -> 2026-10-05 | E40: 46468 | F40: =IF(E40="","",IF(E40<TODAY()-WEEKDAY(TODAY(),3),"Overdue",IF(E40=TODAY()-WEEKDAY(TODAY(),3),"This week",IF(E40=TODAY()-WEEKDAY(TODAY(),3)+7,"Next week","")))) | G40: =IFERROR(INDEX(Grades!$G:$G,MATCH(A40,Grades!$A:$A,0)),"") -> Weak | H40: 46300 | J40: 46531 | K40: LTC | L40: RENDER | M40: 2
A41: SKY | B41: no | C41: =IF(B41="yes",13,26) -> 26 | D41: =IFERROR(INDEX(Grades!$X:$X,MATCH(A41,Grades!$A:$A,0)),"") -> 2026-10-05 | E41: 46475 | F41: =IF(E41="","",IF(E41<TODAY()-WEEKDAY(TODAY(),3),"Overdue",IF(E41=TODAY()-WEEKDAY(TODAY(),3),"This week",IF(E41=TODAY()-WEEKDAY(TODAY(),3)+7,"Next week","")))) | G41: =IFERROR(INDEX(Grades!$G:$G,MATCH(A41,Grades!$A:$A,0)),"") -> Average/Decent | H41: 46300 | J41: 46538 | K41: HYPE | L41: SAND | M41: 2
A42: XLM | B42: yes | C42: =IF(B42="yes",13,26) -> 13 | D42: =IFERROR(INDEX(Grades!$X:$X,MATCH(A42,Grades!$A:$A,0)),"") -> 2026-10-06 | E42: 46391 | F42: =IF(E42="","",IF(E42<TODAY()-WEEKDAY(TODAY(),3),"Overdue",IF(E42=TODAY()-WEEKDAY(TODAY(),3),"This week",IF(E42=TODAY()-WEEKDAY(TODAY(),3)+7,"Next week","")))) | G42: =IFERROR(INDEX(Grades!$G:$G,MATCH(A42,Grades!$A:$A,0)),"") -> Strong | H42: 46301 | J42: 46545 | K42: QNT | L42: XMR | M42: 2
A43: ENA | B43: yes | C43: =IF(B43="yes",13,26) -> 13 | D43: =IFERROR(INDEX(Grades!$X:$X,MATCH(A43,Grades!$A:$A,0)),"") -> 2026-10-06 | E43: 46307 | F43: =IF(E43="","",IF(E43<TODAY()-WEEKDAY(TODAY(),3),"Overdue",IF(E43=TODAY()-WEEKDAY(TODAY(),3),"This week",IF(E43=TODAY()-WEEKDAY(TODAY(),3)+7,"Next week","")))) -> Next week | G43: =IFERROR(INDEX(Grades!$G:$G,MATCH(A43,Grades!$A:$A,0)),"") -> Weak | H43: 46301 | J43: 46552 | K43: PAXG | L43: ZEC | M43: 2
A44: GRASS | B44: no | C44: =IF(B44="yes",13,26) -> 26 | D44: =IFERROR(INDEX(Grades!$X:$X,MATCH(A44,Grades!$A:$A,0)),"") -> 2026-10-07 | E44: 46482 | F44: =IF(E44="","",IF(E44<TODAY()-WEEKDAY(TODAY(),3),"Overdue",IF(E44=TODAY()-WEEKDAY(TODAY(),3),"This week",IF(E44=TODAY()-WEEKDAY(TODAY(),3)+7,"Next week","")))) | G44: =IFERROR(INDEX(Grades!$G:$G,MATCH(A44,Grades!$A:$A,0)),"") -> Average/Decent | H44: 46302 | J44: 46559 | K44: AVAX | L44: DOGE | M44: 2
J45: 46566 | K45: HBAR | L45: SHIB | M45: 2
J46: 46573 | K46: XLM | L46: USDC | M46: 2
J47: 46580 | K47: BTC, ENA | M47: 2
J48: 46587 | K48: ETH | L48: USDT | M48: 2
J49: 46594 | K49: SOL | L49: IMX | M49: 2
J50: 46601 | K50: NEAR | L50: RED | M50: 2
J51: 46608 | K51: LINK | L51: FET | M51: 2
J52: 46615 | K52: ONDO | L52: RAY | M52: 2
J53: 46622 | K53: LTC | L53: NIGHT | M53: 2
J54: 46629 | K54: HYPE | L54: POWR | M54: 2
J55: 46636 | K55: QNT | L55: PEPE | M55: 2
J56: 46643 | K56: PAXG | L56: CRO | M56: 2
J57: 46650 | K57: AVAX | L57: CAKE | M57: 2
J58: 46657 | K58: HBAR | L58: SKY | M58: 2
J59: 46664 | K59: XLM | L59: GRASS | M59: 2

Sheet Evidence
A1: EVIDENCE: one row per coin per line, written as value | source | date. The Grades sheet holds the grades; if the two ever disagree, Grades wins.
A3: Ticker | B3: Line | C3: Line name | D3: Grade | E3: Evidence (value | source | date)
A4: BTC | B4: L1 | C4: Supply dilution (MC / FDV) | D4: A | E4: MC/FDV 0.957 (market cap $1.721T ÷ FDV on max supply $1.798T) | TradingView; CoinGecko FDV on total supply gives 1.00 (also A) | 2026-10-05
A5: BTC | B5: L2 | C5: New supply, next 90 days (% of circulating) | D5: A | E5: Scheduled issuance 3.125 BTC x 144 blocks x 90 days = 40,500 BTC = 0.20% of 20.094M circulating; realized 90-day supply growth 0.20% (matches) | CoinGecko history | 2026-10-05
A6: BTC | B6: L3 | C6: Insider share (team, investors, foundation) | D6: A | E6: Fair launch, no premine, no investor allocation (protocol design). DropsTab and Tokenomist pages loaded but returned no extractable BTC raise or vesting data | 2026-10-05
A7: BTC | B7: L4 | C7: Holder value capture (fees burned, bought back, paid out) | D7: NA | E7: Not applicable for money coins (no fee-capture mechanism)
A8: BTC | B8: L5 | C8: US exit liquidity (2% depth ÷ $100K) | D8: A | E8: At least 555x: bid depth within 2% of at least $55.5M (Coinbase $28.9M, Kraken $24.5M, Binance.US $2.0M; USD and USDT pairs). Lower bound: Kraken USD book did not reach the 2% mark within 500 levels. Earlier snapshot showed 930x; both A | Live order books | 2026-10-05
A9: BTC | B9: L6 | C9: Usage trend (90-day) | D9: C | E9: Lower of fees (USD) +20.9% [A] and fees in native token -6.9% [C] (borderline †, within 5 pts of the D cut-off). 30-day averages 90 days apart; low-confidence fee series (~$240K/day) | DefiLlama + CoinGecko | 2026-10-05
A10: BTC | B10: L7 | C10: Social sentiment | D10: C | E10: TradingView sentiment 73 (step D) | Galaxy Score 65.6 (step B) | mean of steps = C | TradingView | 2026-10-05
A11: BTC | B11: L8 | C11: Incident record (24 months) | D11: A | E11: Graded on the coin's own direct loss (standing decision; confirmed 2026-10-05). No Bitcoin network exploit, halt or loss found in 24 months. CVE-2024-52911 (Bitcoin Core memory-safety bug, fixed in v29.0 Apr 2025, disclosed May 2026): no consensus impact, no exploitation, no loss. FOR CONTEXT ONLY, NOT GRADED (third-party incidents involving BTC, DefiLlama chain = Bitcoin): Coldcard hardware wallet, 30 Jul-3 Aug 2026, ~1,816 BTC (~$116M), firmware seed-generation flaw; Duelbits 24 Sep 2026 $7.0M; RRWallet 6 Aug 2026 $2.0M; TeleSwap 15 Jul 2026 $0.7M; THORChain DEX 15 May 2026 $10.7M; Bisq 1 May 2026 $0.55M; Trust Wallet 25 Dec 2025 $8.5M; SBI Crypto 24 Sep 2025 $21M; BigONE 16 Jul 2025 $27M; WOO X 24 Jul 2025 $14M; Nobitex 18 Jun 2025 $82M; Phemex 23 Jan 2025 $85M; M2 Exchange 31 Oct 2024 $13.7M. False positive: 'Bitcoin Mission' $1.3M Apr 2025 (an Arbitrum DeFi site). If third-party losses were counted, the Coldcard loss would also raise a 90-day incident flag; they are not counted. | DefiLlama /hacks (name and chain), TRM Labs, The Block | 2026-10-05
A12: BTC | B12: L9 | C12: US regulatory status | D12: A | E12: ETF-approved (spot BTC ETFs, SEC, Jan 2024) | CFTC commodity treatment | no enforcement found. A reported SEC/CFTC 'digital commodity' interpretation of 17 Mar 2026 rests on one secondary source and is not relied on | web search | 2026-10-05
A13: BTC | B13: L10 | C13: Admin control | D13: A | E13: No admin, mint or upgrade key (protocol design); no admin path | 2026-10-05
A14: BTC | B14: L11 | C14: Purpose: use beyond trading in a live product | D14: A | E14: Yes: DefiLlama Bitcoin chain fees $196K on 2026-10-04; 30-day average $240K a day | DefiLlama | 2026-10-05
... A75: NEAR | B75: L12 | C75: Backers: raised from outside investors | D75: A | E75: Raised $656.7M (Tokenomist 2026-10-05)
A76: NEAR | B76: L13 | C76: Adoption: production use by government or major company | E76: Blank: Sweep found NEAR Intents volume and the 1 Oct exploit; no government or major-company production use found.
A77: NEAR | B77: L14 | C77: Size: market cap | D77: C | E77: market cap $6.90B | CoinGecko
A78: NEAR | B78: L15 | C78: Market-share trend (90-day dominance) | D78: A | E78: market cap +168% over 90 days; relative to top-20 basket +101% | CoinGecko history
A79: LINK | B79: L1 | C79: Supply dilution (MC / FDV) | D79: B | E79: MC/FDV 0.75
A80: LINK | B80: L2 | C80: New supply, next 90 days (% of circulating) | D80: B | E80: Circulating +2.9% Jun to Oct-26 (727.1M to 748.1M)
A81: LINK | B81: L3 | C81: Insider share (team, investors, foundation) | D81: E | E81: 65% managed by the company
A82: LINK | B82: L4 | C82: Holder value capture (fees burned, bought back, paid out) | D82: A | E82: 98.6% of fees to holders | DefiLlama 30-day fees vs holders revenue
A83: LINK | B83: L5 | C83: US exit liquidity (2% depth ÷ $100K) | D83: A | E83: 34.2x ($3.42M within 2%, Coinbase+Kraken+Binance.US) | Live order books 2026-10-05
A84: LINK | B84: L6 | C84: Usage trend (90-day) | D84: C | E84: Excluding liquid-staking and receipt tokens (Syrup etc.): 90-day TVL in LINK terms -2.8% (-23.9% if only LSTs removed). Judgement-sensitive | DefiLlama tokensInUsd ÷ CoinGecko price, 2026-10-05
A85: LINK | B85: L7 | C85: Social sentiment | D85: C | E85: Sentiment 78% | Galaxy 67.9
A86: LINK | B86: L8 | C86: Incident record (24 months) | D86: B | E86: 9 yrs live | Nov-25 Moonwell feed glitch $1M | audits/bounty not re-verified
A87: LINK | B87: L9 | C87: US regulatory status | D87: B | E87: Spot ETFs approved | no enforcement | commodity status unconfirmed
A88: LINK | B88: L10 | C88: Admin control | D88: C | E88: Token contract immutable | service upgrades via Labs-run keys | time-lock U
... A110: AAVE | B110: L2 | C110: New supply, next 90 days (% of circulating) | D110: A | E110: ~0% unlock; under 1M AAVE left
A111: AAVE | B111: L3 | C111: Insider share (team, investors, foundation) | E111: Insider share not retrieved
A112: AAVE | B112: L4 | C112: Holder value capture (fees burned, bought back, paid out) | D112: E | E112: 0% of fees to holders | DefiLlama 30-day fees vs holders revenue
A113: AAVE | B113: L5 | C113: US exit liquidity (2% depth ÷ $100K) | D113: A | E113: 19.2x ($1.92M within 2%, Coinbase+Kraken+Binance.US) | Live order books 2026-10-05
A114: AAVE | B114: L6 | C114: Usage trend (90-day) | D114: D | E114: Excl. LSTs and receipts: native-token TVL -29.9% (-35.4% if only LSTs removed, which would be E). Grade kept at D, at the boundary | DefiLlama tokensInUsd ÷ CoinGecko price, 2026-10-05
A115: AAVE | B115: L7 | C115: Social sentiment | D115: B | E115: Sentiment 88% | Galaxy 61.2
A116: AAVE | B116: L8 | C116: Incident record (24 months) | D116: B | E116: User decision 2026-10-05: direct loss only (Aave V3 $862K, Mar 2026, fully returned); Kelp bad debt not counted | DefiLlama hacks; user
A117: AAVE | B117: L9 | C117: US regulatory status | D117: A | E117: SEC told Aave Labs it would not recommend enforcement (Dec 16, 2025)
A118: AAVE | B118: L10 | C118: Admin control | D118: B | E118: DAO + timelock | Guardian freeze | rsETH LTV vote preceded the incident
A119: AAVE | B119: L11 | C119: Purpose: use beyond trading in a live product | D119: A | E119: Yes: DefiLlama protocol fees retrieved 2026-10-05 (holder revenue for UNI, AAVE, LINK, RAY).
A120: AAVE | B120: L12 | C120: Backers: raised from outside investors | D120: B | E120: Raised $65.2M (Tokenomist 2026-10-05)
A121: AAVE | B121: L13 | C121: Adoption: production use by government or major company | D121: A | E121: Recent-news sweep: AAVE strong; RED and HYPE weak | Web search 2026-10-05
A122: AAVE | B122: L14 | C122: Size: market cap | D122: C | E122: market cap $2.85B | CoinGecko
A123: AAVE | B123: L15 | C123: Market-share trend (90-day dominance) | D123: A | E123: market cap +113% over 90 days; relative to top-20 basket +59% | CoinGecko history
... A150: TAO | B150: L12 | C150: Backers: raised from outside investors | D150: NA | E150: No raise recorded (fair launch, money coin, memecoin or stablecoin): not applicable
A151: TAO | B151: L13 | C151: Adoption: production use by government or major company | E151: Blank: Not researched or nothing found in this pass.
A152: TAO | B152: L14 | C152: Size: market cap | D152: C | E152: market cap $3.47B | CoinGecko
A153: TAO | B153: L15 | C153: Market-share trend (90-day dominance) | D153: A | E153: market cap +71% over 90 days; relative to top-20 basket +28% | CoinGecko history
A154: BNB | B154: L1 | C154: Supply dilution (MC / FDV) | D154: A | E154: MC/FDV 1.00
A155: BNB | B155: L2 | C155: New supply, next 90 days (% of circulating) | D155: A | E155: No unlocks; net supply shrinking from burns
A156: BNB | B156: L3 | C156: Insider share (team, investors, foundation) | D156: D | E156: Insiders 50% at launch (team 40%, angels 10%)
A157: BNB | B157: L4 | C157: Holder value capture (fees burned, bought back, paid out) | D157: C | E157: 10.0% of fees burned | DefiLlama 30-day fees vs holders revenue
A158: BNB | B158: L5 | C158: US exit liquidity (2% depth ÷ $100K) | D158: A | E158: 19.6x ($1.96M within 2%, Coinbase+Kraken+Binance.US) | Live order books 2026-10-05
A159: BNB | B159: L6 | C159: Usage trend (90-day) | D159: D | E159: 90-day TVL in native token terms -14.1% (dollar TVL +16.7%): price-neutral re-score | DefiLlama TVL ÷ CoinGecko token price, 2026-10-05
A160: BNB | B160: L7 | C160: Social sentiment | D160: C | E160: Sentiment 80% | Galaxy 58
A161: BNB | B161: L8 | C161: Incident record (24 months) | D161: A | E161: 6 yrs mainnet | no downtime 2025–26 | Oct-22 bridge exploit outside 24 mo
A162: BNB | B162: L9 | C162: US regulatory status | D162: C | E162: Many licenses (VARA, France, Italy, Spain, Poland), MiCA U | enforcement carried by the cap (P8)
A163: BNB | B163: L10 | C163: Admin control | D163: D | E163: 40–45 validators | foundation-led forks | emergency halt precedent (2022)
... A165: BNB | B165: L12 | C165: Backers: raised from outside investors | D165: B | E165: $35M: includes Binance exchange Series A ($10M, 2017) and Google Cloud round ($10M, 2024); company-level counts by user decision | dropstab.com 2026-10-05
A166: BNB | B166: L13 | C166: Adoption: production use by government or major company | E166: Blank: Small Nasdaq companies hold BNB as treasury (not use); Bhutan government and DK Bank run Binance Pay for tourists (Binance product).
A167: BNB | B167: L14 | C167: Size: market cap | D167: A | E167: market cap $104.97B | CoinGecko
A168: BNB | B168: L15 | C168: Market-share trend (90-day dominance) | D168: B | E168: market cap +35% over 90 days; relative to top-20 basket +1% | CoinGecko history
A169: RENDER | B169: L1 | C169: Supply dilution (MC / FDV) | D169: A | E169: MC/FDV 0.81–0.97, both ≥0.80
A170: RENDER | B170: L2 | C170: New supply, next 90 days (% of circulating) | D170: A | E170: Next unlock ~0.2% of circulating (issuance not retrieved)
A171: RENDER | B171: L3 | C171: Insider share (team, investors, foundation) | E171: Insider share not retrieved
A172: RENDER | B172: L4 | C172: Holder value capture (fees burned, bought back, paid out) | D172: C | E172: 95% to holders; capped at C (fees < $1M/mo) | DefiLlama 30-day fees vs holders revenue
A173: RENDER | B173: L5 | C173: US exit liquidity (2% depth ÷ $100K) | D173: A | E173: 10.6x ($1.06M within 2%, Coinbase+Kraken+Binance.US) | Live order books 2026-10-05
A174: RENDER | B174: L6 | C174: Usage trend (90-day) | D174: A | E174: BME fees +259% (90d), tiny base | DefiLlama 2026-10-05
A175: RENDER | B175: L7 | C175: Social sentiment | D175: B | E175: Sentiment 86% | Galaxy 64.2
A176: RENDER | B176: L8 | C176: Incident record (24 months) | D176: B | E176: No exploit found | migration completed | audits not re-verified
A177: RENDER | B177: L9 | C177: US regulatory status | D177: C | E177: Status unclear | no enforcement found
A178: RENDER | B178: L10 | C178: Admin control | D178: C | E178: Foundation-led with RNP votes | multisig not retrieved
A179: RENDER | B179: L11 | C179: Purpose: use beyond trading in a live product | D179: A | E179: Yes: DefiLlama protocol fees retrieved 2026-10-05 (holder revenue for UNI, AAVE, LINK, RAY).
A180: RENDER | B180: L12 | C180: Backers: raised from outside investors | D180: B | E180: Raised $30.0M (Tokenomist 2026-10-05)
A181: RENDER | B181: L13 | C181: Adoption: production use by government or major company | E181: Blank: Studio and Apple Vision Pro projects via OTOY; no confirmed named production contract.
A182: RENDER | B182: L14 | C182: Size: market cap | D182: C | E182: market cap $1.07B | CoinGecko
A183: RENDER | B183: L15 | C183: Market-share trend (90-day dominance) | D183: C | E183: market cap +32% over 90 days; relative to top-20 basket -1% | CoinGecko history
A184: SAND | B184: L1 | C184: Supply dilution (MC / FDV) | D184: A | E184: MC/FDV 0.98 (0.89 on Tokenomist)
A185: SAND | B185: L2 | C185: New supply, next 90 days (% of circulating) | D185: A | E185: Fully vested Aug-25
A186: SAND | B186: L3 | C186: Insider share (team, investors, foundation) | D186: E | E186: 88% to insiders, investors, reserves
A187: SAND | B187: L4 | C187: Holder value capture (fees burned, bought back, paid out) | D187: C | E187: 5% fee: half to stakers, half to Foundation; volumes small
A188: SAND | B188: L5 | C188: US exit liquidity (2% depth ÷ $100K) | D188: B | E188: 5.7x ($0.57M within 2%, Coinbase+Kraken+Binance.US) | Live order books 2026-10-05
A189: SAND | B189: L6 | C189: Usage trend (90-day) | E189: No 30 or 90-day change retrieved
A190: SAND | B190: L7 | C190: Social sentiment | D190: C | E190: Sentiment 80% | Galaxy 55.7
A191: SAND | B191: L8 | C191: Incident record (24 months) | D191: C | E191: User decisions 2026-10-05: SHIB stays C (treated as remediated); FET stays C; SAND no Cap 4 (unbacked mint treated as resolved); QNT OK (date discrepancy Apr vs Jul left as is) | User
A192: SAND | B192: L9 | C192: US regulatory status | D192: C | E192: Status unclear | no enforcement found | Korean cautions lifted Oct 2
A193: SAND | B193: L10 | C193: Admin control | D193: C | E193: Multisig removed bridge peers fast | L2 mint config flawed | time-lock U
A194: SAND | B194: L11 | C194: Purpose: use beyond trading in a live product | D194: A | E194: Yes: CoinGecko describes SAND as the utility token for transactions in The Sandbox. No DefiLlama series.
A195: SAND | B195: L12 | C195: Backers: raised from outside investors | D195: A | E195: Raised $121.9M (Tokenomist 2026-10-05)
A196: SAND | B196: L13 | C196: Adoption: production use by government or major company | E196: Blank: Not researched or nothing found in this pass.
A197: SAND | B197: L14 | C197: Size: market cap | D197: D | E197: market cap $0.21B | CoinGecko
A198: SAND | B198: L15 | C198: Market-share trend (90-day dominance) | D198: A | E198: market cap +60% over 90 days; relative to top-20 basket +20% | CoinGecko history
A199: XMR | B199: L1 | C199: Supply dilution (MC / FDV) | D199: A | E199: MC/FDV ≈1.00
A200: XMR | B200: L2 | C200: New supply, next 90 days (% of circulating) | D200: A | E200: Tail emission ~0.84% a year
A201: XMR | B201: L3 | C201: Insider share (team, investors, foundation) | D201: A | E201: Fair launch, no premine
A202: XMR | B202: L4 | C202: Holder value capture (fees burned, bought back, paid out) | D202: NA | E202: Not applicable for money coins (no fee-capture mechanism)
A203: XMR | B203: L5 | C203: US exit liquidity (2% depth ÷ $100K) | D203: A | E203: 10.8x ($1.08M within 2%, Kraken) | Live order books 2026-10-05
A204: XMR | B204: L6 | C204: Usage trend (90-day) | D204: D | E204: Lower of fees (USD) +38.3% [A] and fees in native token -16.9% [D] | DefiLlama + CoinGecko, 2026-10-05
A205: XMR | B205: L7 | C205: Social sentiment | D205: D | E205: Sentiment 79% | Galaxy 45.4
A206: XMR | B206: L8 | C206: Incident record (24 months) | D206: B | E206: 12 yrs live | Aug/Sep-25 Qubic reorgs (6 blocks) | no funds lost
A207: XMR | B207: L9 | C207: US regulatory status | D207: C | E207: Delisting carried by the cap (P8) | no enforcement vs asset | EU AMLR Jul-27
A208: XMR | B208: L10 | C208: Admin control | D208: A | E208: No admin path
... A210: XMR | B210: L12 | C210: Backers: raised from outside investors | D210: NA | E210: No raise recorded (fair launch, money coin, memecoin or stablecoin): not applicable
...

Sheet Coin notes
A1: COIN NOTES: the plain-language part of each report (what it does, biggest risk, open point, caps applied).
A3: Ticker | B3: What it does | C3: Biggest risk | D3: Open point | E3: Caps applied
A4: BTC | B4: The first and largest cryptocurrency: a fixed-supply digital money network secured by proof-of-work mining. | C4: Security budget is almost all block subsidy (fees <1% of miner revenue) with a mining-pool Nakamoto coefficient of 3. | D4: Line 8 graded on direct loss only; third-party incidents on Bitcoin (Coldcard ~$116M Jul 2026, and others) are listed in the evidence for context, not graded. Fragile: 90.3, only 0.3 above the Exceptional line. | E4: None
A5: ETH | B5: A smart-contract platform on which applications, stablecoins and tokenized assets run; ETH pays fees and secures the network through staking. | C5: L1 fee revenue is down 69% YoY, so the valuation rests on adoption rather than cash flow. | D5: L6 usage is borderline (native-token TVL -10.2%; C if -9.9%); L12 counts the 2014 public ICO ($18.66M) by user decision; L7 sentiment supplied by user (TradingView 429). | E5: None
A6: SOL | B6: A high-throughput Layer 1 used for payments, trading and stablecoin settlement. | C6: Network revenue fell 87% in H1-26 as memecoin fees faded, and the decentralization data I found is 15 months old. | E6: None
A7: XRP | B7: A Layer 1 ledger built for fast payments and cross-border settlement, developed with Ripple. | C7: On-ledger fees are about $1.5M a year against a $94B market cap, and monthly escrow releases of up to 1B XRP weigh on supply. | E7: None
A8: NEAR | B8: A sharded proof-of-stake Layer 1 (mainnet 2020) building chain abstraction and AI infrastructure; its NEAR Intents product routes cross-chain swaps. | C8: NEAR Intents lost $3.8M to an exploit on Oct 1 (funds reportedly returned), and gas fees are tiny against a $6B market cap. | D8: Post-mortem of the Oct 1 Intents exploit. | E8: Limited to Average/Decent: Material incident remediated within 90 days (Oct 1, 2026 exploit)
A9: LINK | B9: A decentralized oracle network that delivers outside data and cross-chain messages to smart contracts. | C9: Staked LINK (~$0.65B) is about 0.6% of the $110B value secured, and 65% of supply is Labs-managed with no disclosed release schedule. | E9: None
A10: UNI | B10: The largest decentralized exchange: users swap tokens through shared liquidity pools. | C10: Protocol takes only ~9.5% of trading fees (Jan–Jul-26), and burn figures vary widely by source and week. | E10: None
A11: AAVE | B11: The largest decentralized lending market: users deposit assets to earn interest and borrow against collateral. | C11: Gross protocol revenue fell 66% year on year, and the April rsETH incident showed risk-parameter and bad-debt exposure. | D11: Final close-out of the Kelp bad debt. | E11: None
A12: ONDO | B12: A platform that tokenizes US Treasuries and stocks (OUSG, USDY, Ondo Global Markets); the ONDO token governs it. | C12: About half the supply is still locked, with a ~1.7B unlock (35% of circulating) on Jan 18, 2027, and ONDO carries no revenue or asset rights. | E12: None
A13: TAO | B13: A network of AI subnets that pay miners and validators for machine-learning work. | C13: Emissions worth ~$409M a year dwarf estimated external revenue of $1.3–10.5M, so activity is largely subsidized. | E13: None
A14: BNB | B14: The native token of Binance's BNB Chain and a fee-discount token on the Binance exchange. | C14: Binance remains under U.S. compliance monitors, and early-2026 reports of Iran-linked flows keep regulatory risk live. | D14: DOJ monitor status and US-venue depth. | E14: Limited to Average/Decent: Active enforcement: DOJ plea terms and monitor
A15: RENDER | B15: A decentralized network where GPU owners sell rendering and AI compute. | C15: Burns are only ~0.2% of market cap a year and protocol revenue is undisclosed, so demand is hard to size. | E15: None
A16: SAND | B16: A user-generated metaverse where people build and trade LAND and game assets. | C16: Last reported daily users were in the low hundreds, and 88% of supply was allocated to insiders, investors and company or foundation reserves. | E16: None
A17: XMR | B17: A privacy coin where every transaction is private by default. | C17: Regulated access is shrinking (Binance, OKX, Kraken EEA delisted; EU AMLR bars providers from July 2027) and FCMP++ is still on stressnet. | E17: None
A18: ZEC | B18: A privacy coin with optional shielded transactions that use zero-knowledge proofs. | C18: Venue access can be removed by rule (EU AMLR from 10-Jul-2027), and the 2026 Orchard flaw shows hidden-inflation risk that cannot be fully excluded in shielded pools. | D18: Completion of the Orchard migration. | E18: Limited to Average/Decent: Material flaw remediated within 90 days (patched Jul 28, 2026)
A19: DOGE | B19: A proof-of-work coin that began as a joke and is used for tipping and payments. | C19: Fees are 0.06% of miner revenue, on-chain activity is down about 41% YoY, and one pool holds about 34% of hashrate. | E19: Limited to Average/Decent: Memecoin cap
A20: SHIB | B20: An Ethereum memecoin with an ecosystem around it (ShibaSwap, Shibarium Layer 2). | C20: Supply is concentrated (62.7% in ten addresses unadjusted) and the 2025 Shibarium key compromise shows weak operational security. | E20: Limited to Average/Decent: Memecoin cap
A21: USDC | B21: A US-dollar stablecoin issued by Circle and backed by cash and Treasuries. | C21: Issuer freeze and mint controls are centralized by design, and a Wisconsin complaint over a refused seizure warrant is unresolved. | D21: Outcome of the Wisconsin complaint. | E21: None
A22: USDT | B22: The largest US-dollar stablecoin, issued by Tether and used for trading and transfers. | C22: Reserves include gold, about 98.9K BTC and $13.45B of secured loans (3.3× the $4.11B buffer), and S&P rates peg stability 5 (weak). | E22: None
A23: LTC | B23: A proof-of-work payments coin launched in 2011 as a faster "silver to Bitcoin's gold". | C23: Security spend and usage depend on a subsidy and merged mining, with no verified growth. | E23: None
A24: HYPE | B24: A high-performance blockchain built around an on-chain perpetual-futures exchange; HYPE pays fees and is staked. | C24: Team and foundation unlocks, a small validator set and oracle-manipulation incidents. | E24: None
A25: QNT | B25: A company-run platform (Overledger) that connects blockchains and bank systems; QNT is needed to license it. | C25: A July 2026 reserve-pool exploit through a single-key admin account, and an unverified +284% three-month rally. | D25: Cause of the +284% three-month move. | E25: None
A26: IMX | B26: A gaming-focused blockchain platform (Immutable zkEVM and the original Immutable X) for NFTs and game assets. | C26: US-venue depth of about 1× a $100K position, and weak usage. | E26: None
A27: PAXG | B27: An ERC-20 token backed one-for-one by a fine troy ounce of London Good Delivery gold held by Paxos. | C27: Reliance on the issuer for custody, redemption and freezes, and unverified attestations. | E27: None
A28: RED | B28: A modular blockchain oracle that delivers price data to DeFi apps across many chains. | C28: Competition from Chainlink and Pyth, small size, and unverified depth on US venues. | E28: None
A29: FET | B29: The merged token of the ASI Alliance (Fetch.ai and SingularityNET, with CUDOS): decentralized AI agents and data. | C29: A $1.56M token-converter exploit on Sep 19, 2026 and the Ocean dispute over 286M FET. | D29: Post-mortem and fix for the Sep 19 converter exploit. | E29: Limited to Average/Decent: Material incident within 90 days (Sep 19, 2026 converter exploit, $1.56M; remediation not confirmed)
A30: RAY | B30: The main automated market maker and token launchpad on Solana; RAY is staked and receives fee buybacks. | C30: A June 2026 legacy-pool exploit and multisig control without a timelock. | E30: None
A31: NIGHT | B31: A privacy-focused blockchain with selective disclosure, built by the Cardano team; NIGHT generates DUST, the fee resource. | C31: A July 2026 bridge exploit that took ~515M NIGHT, and an unproven new network. | D31: Follow-up on the Wanchain bridge exploit; sentiment and Galaxy Score could not be re-pulled (TradingView rate limit). | E31: Limited to Average/Decent: Material incident within 90 days (Jul 20, 2026 Wanchain bridge exploit, ~$9–10M)
A32: POWR | B32: A platform for trading renewable energy peer to peer, with the POWR token used on its network. | C32: Minimal usage, small market cap and unverified liquidity. | E32: None
A33: PEPE | B33: An Ethereum memecoin based on the Pepe the Frog meme, with no utility and no mint authority. | C33: Pure sentiment: a memecoin cycle turn and anonymous-team supply. | E33: Limited to Average/Decent: Memecoin cap
A34: CRO | B34: The native token of Crypto.com's Cronos chain, used for fees, staking and exchange discounts. | C34: The $66–75M Tectonic exploit on Aug 30, 2026, a chain rollback by validators, and 70% of supply sitting in a company-controlled reserve. | D34: Post-mortem of the Tectonic exploit. | E34: Limited to Average/Decent: Material incident within 90 days (Aug 30, 2026 Tectonic exploit, $66–75M; chain state restored)
A35: XLM | B35: A payments-focused blockchain whose lumen (XLM) pays network fees; Stellar hosts stablecoins, remittance rails and tokenized funds such as Franklin Templeton's BENJI. | C35: Third-party DeFi exploits on Stellar (Blend/YieldBlox $10.97M in Feb 2026, Comet $717K in Aug 2026), a foundation holding 29% of supply, and weak 90-day relative market-share growth. | D35: Score is 76.3, only 1.3 above the Strong line (75): L8 graded D (if Blend/YieldBlox counted) or L6 graded C would move XLM to Average/Decent; L12 D or L2 C would leave it exactly at 75.0 (still Strong). L7 inputs supplied by user. | E35: None
A36: ENA | B36: The governance and staking token of Ethena, a synthetic-dollar protocol (USDe, USDtb) backed by delta-hedged crypto and tokenized Treasuries held with off-exchange custodians. | C36: Control sits with a team multisig and Foundation consent rights over ~20% of supply (StablecoinX); 70% insider allocation; no payout to ENA holders until USDe supply passes $7.5B; ENA price up ~3x in 90 days. | D36: Score 57.5 is 2.5 below the Average/Decent line (Weak). Recheck CoinGecko vs TradingView circulating supply after the Oct 5 unlock (StablecoinX 3.03B excluded by user decision; L1 and L2 depend on it). L13 A rests on Anchorage/BUIDL; Aladdin integration not counted. L4 changes once USDe passes $7.5B (now ~$4.8B). | E36: None
A37: GRASS | B37: The token of Grass, a Solana DePIN network where users sell unused internet bandwidth; its commercial arm sells web data to AI labs, with attested revenue of $32.1M through Q2 2026. | C37: Mint authority still active (Squads 2-of-4 multisig, timelock 0), 47% of supply held by team and early investors with monthly unlocks of about 1.7% of market cap, and revenue that accrues to Foundation entities rather than to holders. | D37: Score 60.9 is only 0.9 above the Weak line (60). L4, L6 and L13 are blank: a D or E on any of them moves GRASS to Weak (L6 = C gives 59.7). L7 uses CoinGecko votes as a stand-in for TradingView sentiment (429); L10 graded only on the mint authority (Squads 2-of-4, no timelock); upgrade authorities not checked. | E37: None

Sheet Usage method
A1: Usage line (L6) rule: final grade = the lower of the price-free measure and the native-token measure. Borderline (†) = within 5 points of a cut-off.
A3: Coin | B3: Price-free measure | C3: Price-free value % | D3: Price-free grade | E3: Native-token measure | F3: Native-token value % | G3: Native-token grade | H3: Final grade | I3: Borderline | J3: Previous grade
A4: ETH | B4: stablecoin supply | C4: -3.3 | D4: C | E4: TVL in native token | F4: -10.2 | G4: D | H4: D | I4: yes (†) | J4: D
A5: SOL | B5: stablecoin supply | C5: 10.6 | D5: A | E5: TVL in native token | F5: -11.7 | G5: D | H5: D | I5: yes | J5: D
A6: XRP | B6: stablecoin supply | C6: 44.6 | D6: A | E6: TVL in native token | F6: -13.8 | G6: D | H6: D | I6: yes | J6: D
A7: BNB | B7: stablecoin supply | C7: -4.9 | D7: C | E7: TVL in native token | F7: -14.1 | G7: D | H7: D | I7: yes | J7: D
A8: TAO | B8: fees in TAO terms | C8: -8.1 | D8: C | E8: TVL in native token | F8: 869.9 | G8: A | H8: C | I8: yes | J8: A
A9: NEAR | B9: stablecoin supply | C9: -8.3 | D9: C | E9: TVL in native token | F9: -18.9 | G9: D | H9: D | I9: yes | J9: D
A10: HYPE | B10: stablecoin supply | C10: 23.4 | D10: A | E10: TVL in native token | F10: -37.3 | G10: E | H10: E | J10: E
A11: CRO | B11: stablecoin supply | C11: -23 | D11: D | E11: TVL in native token | F11: -46 | G11: E | H11: E | J11: E
A12: IMX | B12: stablecoin supply | C12: -2.5 | D12: C | E12: TVL in native token | F12: -20.4 | G12: D | H12: D | I12: yes | J12: D
A13: AAVE | B13: fees (USD) | C13: 26.1 | D13: A | E13: TVL in native token | F13: -29.9 | G13: D | H13: D | I13: yes | J13: D
A14: UNI | B14: fees (USD) | C14: 282.8 | D14: A | E14: TVL in native token | F14: -53.9 | G14: E | H14: E | J14: E
A15: LINK | B15: fees (USD) | C15: -8 | D15: C | E15: TVL in native token | F15: -2.8 | G15: C | H15: C | I15: yes | J15: C
A16: RAY | B16: fees (USD) | C16: 669.1 | D16: A | E16: TVL in native token | F16: -52.2 | G16: E | H16: E | J16: E
A17: SHIB | B17: fees (USD) | C17: 829.4 | D17: A | E17: TVL in native token | F17: 7.5 | G17: B | H17: B | I17: yes | J17: B
A18: BTC | B18: fees (USD) | C18: 20.9 | D18: A | E18: fees in native token | F18: -6.9 | G18: C | H18: C | I18: yes | J18: A
A19: LTC | B19: fees (USD) | C19: 37.8 | D19: A | E19: fees in native token | F19: -1.6 | G19: C | H19: C | I19: yes | J19: A
A20: XMR | B20: fees (USD) | C20: 38.3 | D20: A | E20: fees in native token | F20: -16.9 | G20: D | H20: D | J20: A
A21: ZEC | B21: fees (USD) | C21: 524.4 | D21: A | E21: fees in native token | F21: 103.8 | G21: A | H21: A | J21: A
A22: ONDO | B22: fees (USD) | C22: 20.2 | D22: A | E22: fees in native token | F22: -3.7 | G22: C | H22: C | I22: yes | J22: C
A23: RENDER | B23: fees (USD) | C23: 204.6 | D23: A | E23: fees in native token | F23: 195.9 | G23: A | H23: A | J23: A
A24: XLM | B24: stablecoin supply | C24: 9.1 | D24: B | E24: TVL in native token | F24: 9.1 | G24: B | H24: B | I24: yes (†)
A25: ENA | B25: fees (USD) | C25: 13.3 | D25: A | E25: TVL in native token | F25: -63.9 | G25: E | H25: E | I25: yes (†)
A27: Not re-tested: DOGE (no fee series on DefiLlama; keeps its earlier grade). PAXG, PEPE, SAND, FET, QNT, NIGHT, RED, POWR, GRASS have no usage series. USDT/USDC use stablecoin supply. Fee series for BTC, LTC, XMR, ZEC are small (a few $K to ~$200K a day), so treat them as low-confidence.

Sheet Decisions
A1: DECISIONS AND METHOD NOTES: every ruling made while building the system, so it is never asked twice.
A3: Topic / coin | B3: Decision or value | C3: Detail
A4: L11 Purpose (goal and soundness) | B4: 10 | C4: Yes/no: the token has a documented use other than trading, in a live product, backed by a named source (DefiLlama fee/TVL series, CoinGecko description). Yes = A, No = E. Blank where no source was retrieved.
A5: L12 Backers | B5: 5 | C5: Total raised from outside investors per DropsTab or Tokenomist: A >=$100M, B $25-<100M, C $5-<25M, D >$0-<5M. NA where no raise is recorded (fair launches, money coins, memecoins, stablecoins). Blank where no raise page was found.
A6: L13 Adoption | B6: 5 | C6: Yes/no: used or held by a government, central bank or major corporation in documented production use (not an MoU, pilot or ETF listing). Yes = A, No = E, blank = not yet researched.
A7: COIN | B7: L11 / L12 / L13 evidence
A8: BTC | B8: L11 yes: DefiLlama Bitcoin chain fees $196K on 2026-10-04 (30-day average $240K a day). L12 NA: no raise recorded. L13 yes: US government holds ~328K BTC; Strategic Bitcoin Reserve created by Executive Order 14233, 6 Mar 2025 (bit.com, blockeden.xyz, The Block). Funded from seizures, no purchases yet. Counted as government holding (user decision 2026-10-05).
A9: ETH, SOL, BNB, XRP, NEAR, TAO, HYPE, CRO, IMX | B9: L11 yes: native fee/gas asset, DefiLlama chain fees and TVL retrieved 2026-10-05.
A10: LINK, UNI, AAVE, RAY, RENDER, ONDO | B10: L11 yes: DefiLlama protocol fees retrieved 2026-10-05 (holder revenue for UNI, AAVE, LINK, RAY).
A11: XMR, ZEC, LTC | B11: L11 yes: base payment asset with DefiLlama fee series (small: ~$0.4K-$3K/day for LTC, XMR, ZEC).
A12: USDC, USDT, PAXG | B12: L11 yes: payment/settlement stablecoins (DefiLlama supply); PAXG represents 1 oz of London Good Delivery gold (CoinGecko).
A13: SAND | B13: L11 yes: CoinGecko describes SAND as the utility token for transactions in The Sandbox. No DefiLlama series.
A14: PEPE | B14: L11 NO: CoinGecko describes a meme token with no function; no DefiLlama protocol or chain.
A15: DOGE, SHIB | B15: Superseded: see 'DOGE, SHIB (purpose)' below (No, user decision 2026-10-05).
A16: FET, QNT, NIGHT, POWR, RED | B16: L11 BLANK: descriptions describe the organisation, not the token function; no usage series.
A17: Backers (L12) | B17: SOL $359.7M, NEAR $656.7M, UNI $181.0M, SAND $121.9M, IMX $291.4M (A); AAVE $65.2M, FET $66.0M, ONDO $34.0M, LINK $32.0M, RENDER $30.0M (B); RED $22.5M (C). Source: Tokenomist 2026-10-05. BNB, XRP, QNT, NIGHT, POWR, CRO have no Tokenomist page: blank. ETH and RAY show $0 raise on Tokenomist: NA.
A18: L13 ADOPTION RESEARCH (2026-10-05) | C18: Rule: Yes only for documented production use or holding by a government, central bank or major company. Pilots, MoUs, ETFs and treasury purchases by small companies do not count.
A19: BTC | B19: YES | C19: US government holds ~328K BTC; Strategic Bitcoin Reserve, Executive Order 14233, 6 Mar 2025 (bit.com, blockeden.xyz, The Block). Funded from seizures; no purchases yet. Counted as government holding (user decision 2026-10-05).
A20: ETH | B20: YES | C20: JPMorgan tokenized money-market funds MONY (Dec 2025) and JLTXX (May 2026) on public Ethereum, ~$800M (cryptobriefing); BlackRock BUIDL, Fidelity and others.
A21: SOL | B21: YES | C21: Visa settles USDC on Solana ($3.5B+ annualised), PayPal PYUSD, Fiserv FIUSD, Western Union USDPT (Messari data via mexc/Blockonomi, Feb-Mar 2026).
A22: XRP | B22: YES (weak) | C22: SBI and some banks use Ripple On-Demand Liquidity (XRP as bridge); BBVA, DBS, DZ Bank, Intesa live on Ripple Custody. Most bank use is Ripple software, not XRP. Sources are crypto media.
A23: LINK | B23: YES | C23: DTCC production tokenized collateral workflows; UBS in-production tokenized fund workflow; US Department of Commerce macro data on-chain (Chainlink blog, Crowdfund Insider). Partly self-reported.
A24: USDC | B24: YES | C24: Visa data: ~70% of adjusted stablecoin settlement volume H1 2026; Visa/Stripe/BlackRock integrations (Cobo, Visa).
A25: ONDO | B25: YES | C25: BlackRock BUIDL is OUSG primary reserve; 6 May 2026 settlement across JPMorgan Kinexys, Mastercard MTN and XRPL; Franklin Templeton tokenized ETFs (Mar 2026).
A26: UNI | B26: YES | C26: BlackRock BUIDL tradable on UniswapX since 11 Feb 2026; BlackRock bought UNI (Cointelegraph, Uniswap Labs release).
A27: CRO | B27: YES (weak) | C27: Trump Media bought $105M of CRO and integrates it into Truth Social rewards (Blockworks). Related-party and treasury-style; borderline.
A28: POWR | B28: YES (weak) | C28: TraceX integrated with ERCOT for renewable-energy certificates (2025); POWR is the licence token for the platform. Adoption is of the company software.
A29: PEPE | B29: NO | C29: Searched with other memecoins: no company or government use found.
A30: DOGE, SHIB, LTC | B30: BLANK | C30: AMC (2021-22 via BitPay) and Tesla (DOGE merchandise) accepted them; dated and current status not verified.
... A38: QNT (adoption, updated) | B38: YES (weak) | C38: The Clearing House (CHIPS, EPN, RTP; >$2T a day) chose Quant to connect its On-Chain Money Initiative for tokenized deposits; 25 institutions incl. Citi, Bank of America, JPMorgan, Wells Fargo support the project (The Crypto Basic, 3 Oct 2026, relaying TCH posts on X). Caveats: not live until H1 2027; the adoption is of Quant's technology, and the article does not say QNT the token is used.
A39: L13 RECENT-NEWS SWEEP (2026-10-05)
A40: AAVE | B40: YES | C40: Aave Horizon, permissioned institutional RWA lending, in production: >$600M net deposits and ~$200M borrowed, with Circle, Ripple, Franklin Templeton and VanEck among collateral suppliers (RWA Briefing, Aug 2026; Aave and DL News on launch).
A41: RED | B41: YES (weak) | C41: Securitize, a public company (SEC S-4/S-1 filings 2026), names RedStone as its primary oracle for tokenized funds from BlackRock (BUIDL), Apollo (ACRED), Hamilton Lane and VanEck. Caveat: adoption of the oracle service; token function not shown.
A42: HYPE | B42: YES (weak) | C42: 30 Sep 2026: Hyperion DeFi, Anchorage Digital Bank (federally chartered) and HyperLend launched an institutional credit facility secured by staked HYPE held in qualified custody. Early; ETFs and treasury purchases not counted.
A43: NEAR | B43: BLANK | C43: Sweep found NEAR Intents volume and the 1 Oct exploit; no government or major-company production use found.
A44: AVAX (adoption lead) | B44: NOTE | C44: UAE TDRA (with Deca4 and Ava Labs) announced 14 Sep 2026 that UAE PASS Digital Vault (12.5M users) will use Avalanche technology, via a government-controlled L1. Not yet live. AVAX was added 2026-10-05; this is not yet production use, so L13 is not based on it.
A45: CURRENT WEIGHTS (100) | C45: L1 dilution 10; L2 new supply 5; L3 insiders 5; L4 holder value capture 5; L5 exit liquidity 10; L6 usage trend 10; L7 sentiment 5; L8 incidents 5; L9 regulatory 10; L10 admin control 5; L11 purpose 10; L12 backers 5; L13 adoption 5; L14 size 5; L15 market-share trend 5.
A46: L14 Size | B46: 5 | C46: Market cap (CoinGecko, 2026-10-05): A >=$100B, B $10B-<100B, C $1B-<10B, D $0.1B-<1B, E <$0.1B. Scored for all coins including stablecoins.
A47: L15 Market-share trend | B47: 5 | C47: 90-day change in dominance = coin market-cap growth relative to a top-20 market-cap basket (CoinGecko history; total-market history is paid). Cut-offs as for usage: A >=+10%, B 0-10%, C -10-0%, D -30 to -10%, E < -30%. NA for USDT, USDC, PAXG (their market cap follows supply, not price). Basket +33.5% over 90 days (about $2.08T to $2.78T).
A48: QNT (DropsTab, 2026-10-05) | C48: Backers: $26M raised in two 2018 token sales (Pre-TGE $15M, public sale $11M) plus a 2020 venture round (Alpha Sigma Capital, Alchemmy) -> grade B ($25M to <$100M). Purpose: QNT is the licence token for Overledger (annual licences and fees paid in QNT, e.g. 250 QNT per licence tier) -> Yes, with the caveat that enterprises can use the APIs without touching the token. Supply: max 14.88M, circulating 12.07M, no public vesting schedule, so the new-supply line stays blank (about 2.8M unreleased with no schedule). Source: dropstab.com/es/coins/quant-network.
A49: NIGHT (2026-10-05 update) | B49: L3 C, L4 E, L9 C, L11 A, L12 NA | C49: L3: Foundation 35% only (TGE entity 15.3% excluded, user decision). L4 E: no fee payout by design (DUST). L9 C: no NIGHT-specific ruling; general SEC framework (March 2026 release, Aug 2026 proposal) per HSF Kramer; no enforcement found. L11 A: DUST/smart-contract utility (midnight.network blog; CoinGecko news). L12 NA: fair launch. L13 left blank by user (Monument Bank is an announcement; node operators not counted). CoinGecko: circulating 16.607B of 24B, MC/FDV 0.69. DropsTab "10B of 10B circulating, no vesting" judged stale and not used.
A50: Backers update (company-level rounds count, user decision 2026-10-05) | B50: XRP A, BNB B, POWR B, CRO A | C50: DropsTab raise totals: XRP $790.5M, BNB $35M, POWR $29.24M, CRO $426.2M. DropsTab has no vesting data for POWR (no schedule) or NIGHT (stale).
A51: L8 recheck (2026-10-05) | B51: See sheet "L8 recheck" | C51: Hack records re-checked against DefiLlama hacks by name and chain. False positives: BTC (Bitcoin Mission), ETH (Verus bridge), USDT (unrelated staking sites), HYPE (Hyperliquid Malaysia). LTC newly scored A. Open decisions: SHIB, SAND, AAVE. BTC (refresh 2026-10-05): third-party incidents on the Bitcoin chain (Coldcard ~$116M Jul 2026 and 12 others) are listed in the evidence table for context only; Line 8 stays A on the coin's own direct loss.
A52: New coins 2026-10-05 (AVAX, HBAR, CAKE, SKY) | B52: See Update 2026-10-05 sheet | C52: Method as for the other 31 coins. Supply line (line 2) uses realized 90-day circulating-supply growth because no forward unlock schedule was retrievable. Lines 10 (admin control) blank for all four.
A53: XLM (2026-10-06 new coin) | B53: Group: Chain / protocol. L1 B, L2 B (proxy), L3 C, L4 D, L5 A, L6 B†, L7 B, L8 A, L9 A, L10 B, L11 A, L12 C, L13 A, L14 C, L15 D† | C53: L3: SDF mandate only (29.4% of 50.0B total supply). L4: 2.0% (DefiLlama holders revenue ÷ fees, user decision). L7: sentiment 100% and Galaxy 58 supplied by the user from TradingView. L8: third-party app losses (Blend/YieldBlox, Comet) not graded. L10 B by user decision (validator-quorum governance; C was the alternative). L12: DropsTab $5.02M kept as C (Stripe-only $3M would be D). L13: Franklin Templeton BENJI fund live on Stellar. L15 basket +33.5% recomputed for 2026-10-06.
A54: ENA (2026-10-06 new coin) | B54: Group: Chain / protocol. L1 B, L2 C, L3 E, L4 E, L5 B, L6 E†, L7 D, L8 A, L9 C, L10 D, L11 A, L12 A, L13 A, L14 C, L15 A. Score 57.5, rating 5.8, coverage 100%, tier Weak (2.5 below the Average/Decent line). | C54: User decisions 2026-10-06: L1 B (StablecoinX's ~3.03B ENA not counted as circulating: Foundation written consent needed to sell); L2 C; L10 D (control concentrated in a team multisig and Foundation consent rights; low rug-pull risk, custody via off-exchange providers); L13 A (Anchorage issues USDtb, reserves in BlackRock BUIDL; Aladdin integration not counted). L3 counts Core Contributors 30% + Investors 25% + Foundation 15% = 70%. L4: fee switch approved but dormant until 14-day average USDe supply exceeds $7.5B (USDe ~$4.8B). L6: fees +13.3% [A] but TVL ÷ ENA price -63.9% [E]; lower = E. Open: recheck CoinGecko/TradingView circulating supply after the Oct 5 unlock.
A55: ETH (2026-10-06 refresh) | B55: Group: Chain / protocol. L1 A, L2 A (proxy), L3 A, L4 B, L5 A, L6 D†, L7 C, L8 A, L9 A, L10 A, L11 A, L12 C, L13 A, L14 A, L15 A. Score 86.3, rating 8.6, coverage 100%, tier Strong (previous 87.5). | C55: User decisions 2026-10-06: L3 A (Early Contributor & Foundation 8.87% only; ICO buyers 44.31% not insiders; counting them would give E); L6 D† kept (native-token TVL -10.2% on date-matched points, -9.9% on the live price would be C); L7 C (sentiment 80%, Galaxy 45, supplied by user because TradingView returned 429); L12 C (DropsTab $18.66M 2014 public ICO counts, as for QNT; Tokenomist $0 tracks VC/vested allocations only; changed from NA). L4 uses the base-layer Ethereum series (32.4%); the all-apps chain aggregate gives 6.3%. L2 uses on-chain net supply growth +0.215% (CoinGecko history implies +1.18%, treated as an artifact). Basket recomputed +33.1% (2026-10-06).
A56: NIGHT/XRP/BNB/POWR/CRO update | B56: 2026-10-05 | C56: See change log in the scoring workbook. DropsTab: POWR has no vesting schedule; NIGHT page lists 10B of 10B circulating with no vesting, conflicting with CoinGecko (16.6B of 24B), so not used.
A57: L8 recheck | B57: 2026-10-05 | C57: Re-checked against DefiLlama hacks; see sheet "L8 recheck" in the scoring workbook. LTC newly scored A.
A58: AVAX, HBAR, CAKE, SKY added | B58: 2026-10-05 | C58: Four coins added (35 assets). See the scoring workbook change log for line-by-line evidence.
A59: XLM added | B59: 2026-10-06 | C59: One coin added (36 assets). See the scoring workbook change log for line-by-line evidence.
A60: ENA added | B60: 2026-10-06 | C60: One coin added (37 assets). Score 57.5, Weak. See the scoring workbook change log for line-by-line evidence.
... A62: GRASS (2026-10-07 new coin) | B62: Group: Chain / protocol. L1 B, L2 D†, L3 D, L4 blank, L5 C, L6 blank, L7 C, L8 A, L9 C, L10 C, L11 A, L12 C, L13 blank, L14 D, L15 A. Score 60.9, rating 6.1, coverage 80%, tier Average/Decent (0.9 above the Weak line). | C62: User decisions 2026-10-07: L3 D (Contributors 22% + Early Investors 25.2% = 47.2%; Foundation 22.8% excluded; counting it gives 70% = E); L4 blank (2025 buyback about $350K is stale; staker revenue share unconfirmed in primary sources; D would give 58.8 Weak); L7 C (Galaxy 57 supplied by the user; CoinGecko votes 80.0% used as a flagged stand-in because TradingView returned 429); L10 C (mint authority not revoked; Squads 2-of-4 multisig, timelock 0; program upgrade authorities not checked); L13 blank (customers unnamed; A offered as override and declined). L2: Tokenomics.com forward schedule (5.3%, 0.3 above the C/D line); DropsTab conflicting unlock figure not used. L12: $10M bridge round counted. L15 basket +31.6% recomputed for 2026-10-07. Fragility: score 60.9 sits 0.9 above the Weak line; a D or E on any of L4, L6, L13 would move GRASS to Weak (L6 = C gives 59.7).
A63: READ-ME NOTES FROM THE EVIDENCE TABLE
A64: Evidence note | C64: Sentiment (line 7) comes from the TradingView screener (sentiment % and Galaxy Score); NIGHT was missing.
A65: Evidence note | C65: BTC evidence refreshed 2026-10-05 (no grade changes); Line 8 lists third-party incidents for context only.
A66: Evidence note | C66: XLM added 2026-10-06: L7 sentiment 100% and Galaxy Score 58 were supplied by the user from TradingView (screener rate-limited); L8 third-party losses not graded; L10 B by user decision; L12 C kept by user decision.
A67: Evidence note | C67: ENA added 2026-10-06: L1 B, L2 C, L10 D and L13 A by user decision (StablecoinX's ~3.03B ENA not counted as circulating because Foundation written consent is needed to sell); L7 from TradingView (sentiment 33, Galaxy 51.9); L8 venue-level USDe depegs not graded; no caps or flags.
A68: Evidence note | C68: ETH refreshed 2026-10-06: L3 A (Foundation and early contributors 8.87%), L12 C (DropsTab $18.66M public ICO, user decision), L7 sentiment 80% / Galaxy 45 supplied by the user (TradingView 429), L6 D† borderline.
A69: Evidence note | C69: GRASS added 2026-10-07: L3 D (Contributors + Early Investors 47.2%, Foundation excluded, user decision), L7 C (Galaxy 57 from the user; CoinGecko votes 80.0% as a flagged stand-in because TradingView returned 429), L10 C (Squads 2-of-4 mint authority, no timelock), L4, L6 and L13 blank. Score 60.9, Average/Decent, coverage 80%.
A70: GRASS added | B70: 2026-10-07 | C70: One coin added (38 assets). Score 60.9, Average/Decent, coverage 80% (0.9 above the Weak line). See the scoring workbook change log for line-by-line evidence. Blank by decision: L4, L13; no usage series: L6.
A71: LINE 8 RECHECK (2026-10-05) | C71: Hack records re-checked against DefiLlama by name and chain.
A72: BTC | B72: Grade A: Consistent: none is the Bitcoin network's own direct loss; listed for context only | C72: DefiLlama: Chain=Bitcoin lists 13 third-party incidents (exchanges, wallets, bridges), largest Coldcard ~$116M Jul 2026 (wallet firmware flaw). 'Bitcoin Mission' $1.3M Apr 2025 is a false positive (a DeFi site) | Other: No network exploit, halt or loss found; CVE-2024-52911 (Bitcoin Core) disclosed May 2026, no consensus impact, no loss (2026-10-05) | Open decision: Decided 2026-10-05: third-party losses not graded; BTC stays A
A73: ETH | B73: Grade A: Consistent; false positive | C73: DefiLlama: "Verus-Ethereum Bridge" $11.5M May 2026 and $7.5M Jul 2026 (Verus bridge, not Ethereum) | Other: No halts or exploits found | Open decision: -
A74: SOL | B74: Grade A: Consistent | C74: DefiLlama: none | Other: No outage in 30 months | Open decision: -
A75: XRP | B75: Grade C: Not in DefiLlama; grade rests on news | C75: DefiLlama: none | Other: xrpl.js supply-chain compromise Apr 2025 | Open decision: -
A76: NEAR | B76: Grade C: Consistent; flag runs 90 days from remediation | C76: DefiLlama: NEAR Intents $3.8M, 2026-10-01 | Other: Funds reportedly returned 2 Oct | Open decision: -
A77: LINK | B77: Grade B: Consistent; the 2026 Moonwell oracle events deserve a check for Chainlink feed involvement | C77: DefiLlama: none | Other: Nov 2025 Moonwell feed glitch about $1M (DefiLlama lists Moonwell $1.0M 2025-11-04). DefiLlama also lists Moonwell oracle events of $1.78M (Feb 2026) and $8.7M (Aug 2026); DefiLlama does not attribute them to Chainlink, not checked further | Open decision: Were the 2026 Moonwell events caused by Chainlink feeds?
A78: UNI | B78: Grade A: Consistent | C78: DefiLlama: none | Other: Core contracts never exploited | Open decision: -
A79: AAVE | B79: Grade B (was C): Direct Aave loss at B level; C rests on Kelp bad debt, size not retrieved | C79: DefiLlama: Aave V3 $862K, 2026-03-12, fully returned; Kelp $293M 2026-04-18 (Kelp bridge spoof, Aave bad debt) | Other: Kelp bad debt Apr 2026, remediated | Open decision: Decided: B (user)
A80: ONDO | B80: Grade A: Consistent | C80: DefiLlama: none | Other: No exploit found | Open decision: -
A81: TAO | B81: Grade B: Consistent | C81: DefiLlama: none | Other: Jul 2024 theft outside window | Open decision: -
A82: BNB | B82: Grade A: Consistent | C82: DefiLlama: none | Other: Oct 2022 bridge outside window | Open decision: -
A83: RENDER | B83: Grade B: Consistent | C83: DefiLlama: none | Other: No exploit found | Open decision: -
... A104: ENA | B104: Grade A: Consistent: no direct loss of ENA/Ethena funds; venue events listed for context, not graded (2026-10-06) | C104: DefiLlama: none (no Ethena entry; text match 'Arena SocialFi', Avalanche 2023, is a false positive) | Other: Venue-level events only: USDe $0.65 on Binance Oct 10, 2025 (Binance oracle); $0.92 wick Sep 22, 2026; Bybit hack Feb 2025, Ethena exposure <$30M, no loss | Open decision: -

Sheet Change log
A1: CHANGE LOG: one dated line per grade change or evidence update, newest first. New findings go here (this replaces the research log in the reports).
A3: Date | B3: Coin | C3: Line | D3: Old grade | E3: New grade | F3: Value / evidence | G3: Source
A4: 2026-10-08 | B4: All | C4: - | F4: V7: Schedule tab added (first run: 14 held coins every 13 weeks, 24 others every 26 weeks, 2 coins a week; first reviews week of 2026-10-12). No grade changed. | G4: Restructure
A5: 2026-10-07 | B5: All | C5: - | F5: V6.1: GRASS added (38 coins), from Lean_Scoring_Workbook_V5_2_2026-10-07_GRASS and Lean_Evidence_Table_2026-10-07_GRASS; ETH Last evaluated corrected to 2026-10-07 (its refresh snapshots were taken 2026-10-07 00:16 UTC). No other grade changed. | G5: Update
A6: 2026-10-07 | B6: GRASS | C6: L1 | E6: B | F6: MC/FDV 0.70 (market cap $451.3M ÷ FDV $645.1M; circulating 699.49M of 1.0B; max supply = total supply). CoinGecko only: the TradingView FDV was not retrieved (429 on several tries). | G6: CoinGecko API; TradingView 429 | 2026-10-07
A7: 2026-10-07 | B7: GRASS | C7: L2 | E7: D | F7: Forward schedule: 12.43M on Oct 28, about 12.4M on Nov 28, about 12.4M on Dec 28 (same tranche pattern: Contributors 6.11M + Foundation 2.61M + Future Incentives 2.71M + Router Rewards 1.0M a month) = about 37.3M = 5.3% of 699.5M circulating (D; 0.3 above the 5% line †). Realized-growth proxy not used (90-day circulating growth +10.7% would be E). DropsTab shows a conflicting 31.58M unlock "in 0 days" and 664M unlocked; judged inconsistent with the vesting terms and not used (even so about 8%, still D). CoinGecko circulating is about 13.7M above the Tokenomics.com unlocked figure (685.8M). | G7: Tokenomics.com unlock schedule; DropsTab; CoinGecko history | 2026-10-07
A8: 2026-10-07 | B8: GRASS | C8: L3 | E8: D | F8: D by user decision 2026-10-07: counts Contributors (team) 22.0% + Early Investors 25.2% = 47.2%. Foundation & Ecosystem 22.8% excluded (not a traditional insider); Community pools 30% (Future Incentives 17%, Airdrop One 10%, Router Rewards 3%) excluded. Counting the Foundation, as the guide wording and the NIGHT and ENA precedents do, would give 70% = E. | G8: Tokenomics.com; DropsTab; user decision | 2026-10-07
A9: 2026-10-07 | B9: GRASS | C9: L4 | F9: NOT scored (user decision: blank). DefiLlama has no fee or holders-revenue series for Grass (dummy module; /summary/fees/grass returns not found). Grass says revenue accrues to Foundation entities (Grass DataCo), not to holders. A revenue share for stakers was reported after the July 7 call, but the Grass recap of that call does not mention it and no payout percentage is published; Stage 2 USDC rewards go to node participants, not holders (not counted). 2025 buyback of about $350K (about 5% of Q2+Q3 2025 revenue, about $7M) is a one-off and stale. Counting it as D would give 58.8 (Weak) with L13 blank. | G9: DefiLlama; grass.io July 7 recap; Grass holder call #1 (Nov 2025); Messari | 2026-10-07
A10: 2026-10-07 | B10: GRASS | C10: L5 | E10: C | F10: 2% bid depth $405.7K = 4.06x $100K: Coinbase GRASS-USD $269.4K + Kraken GRASSUSD $136.3K (500 levels; the 2% mark was reached on both). Binance.US does not list GRASS. Mid price about $0.6485. | G10: Exchange order-book APIs | 2026-10-07 11:54 UTC
A11: 2026-10-07 | B11: GRASS | C11: L6 | F11: NOT scored: no usage series. DefiLlama lists Grass (DePIN, Solana) with no TVL and no fees, and no stablecoin-on-chain series applies. Company-reported revenue ($17.0M in 2025; H1 2026 $14.53M attested, $17-18M per Grass) is not a 90-day series and was not used. | G11: DefiLlama /protocol/grass, /summary/fees/grass | 2026-10-07
A12: 2026-10-07 | B12: GRASS | C12: L7 | E12: C | F12: Galaxy Score 57 (step C) supplied by the user; sentiment is not available from TradingView (screener returned 429), so CoinGecko community votes 80.0% bullish were used as a flagged stand-in (step B, exactly on the 80% cut-off). Mean of steps B and C = 2.5, a half rounds down = C. Stays C for sentiment 75% to under 85%; B at 85% or more, D below 75%. CoinGecko votes are not the TradingView sentiment the guide specifies. | G12: CoinGecko API; Galaxy Score from user; TradingView 429 | 2026-10-07
A13: 2026-10-07 | B13: GRASS | C13: L8 | E13: A | F13: No direct loss of GRASS or Grass network funds found in 24 months. DefiLlama /hacks has no Grass or Wynd entry (matched by name and chain, Solana). Not graded (third-party or look-alike): fake "Grass airdrop" phishing sites, the unrelated GrassCall malware campaign, and a Nov 2024 user-wallet theft through a look-alike plugin. | G13: DefiLlama /hacks; PCrisk; GBHackers; SOCRadar; Medium | 2026-10-07
A14: 2026-10-07 | B14: GRASS | C14: L9 | E14: C | F14: No GRASS-specific SEC/CFTC ruling, ETF filing, commodity tag or enforcement found. Listed on Coinbase (spot trading began 2026-08-26) and Kraken. Grass paid its Season 2 airdrop in USDC citing regulatory uncertainty, and its staking terms warn of regulatory risk. Not a general-framework upgrade (guide: general SEC statements do not lift above C). | G14: Web searches; Coinbase listing notices; Grass staking terms; airdrops.io | 2026-10-07
A15: 2026-10-07 | B15: GRASS | C15: L10 | E15: C | F15: C by user decision 2026-10-07. The mint authority is NOT revoked. It is vault 0 of a Squads v4 multisig (authority 31rYartQwHeBMjAe2MgGpffGV57fQY3kug4BDN8tLGqQ; multisig C9sTdCdun5UHmK3PG9u8A3Jf2i8KnPYCbgirnBvrGEzP): threshold 2 of 4, timelock 0, no external config authority, four unlabeled member keys. Freeze authority null. On-chain supply 999,992,818 (7,182 below 1B; the token has no on-chain cap). No on-chain governance program acts on the authority. Program upgrade authorities were not checked. The flag (team key, no timelock) was not applied: team control was not shown, and it could not lower the tier below Average/Decent. | G15: Solana RPC mainnet-beta (getAccountInfo, Squads account data, transactions); grass-foundation.gitbook.io | 2026-10-07 12:26 UTC
A16: 2026-10-07 | B16: GRASS | C16: L11 | E16: A | F16: Yes: live product selling residential bandwidth and web data to AI labs. An independent attestation (Regen Financial) covers $32.1M of recorded revenue through Q2 2026, of which $27.6M traced to cash receipts; 6M+ contributors. GRASS is used for staking by delegation to routers and for governance. DefiLlama lists Grass (DePIN) with no fee or TVL series. | G16: Regen Financial attestation as reported by KuCoin and CoinGabbar; grass.io July 7 recap; Grass staking docs; DefiLlama | 2026-10-07
A17: 2026-10-07 | B17: GRASS | C17: L12 | E17: C | F17: Total raised $13.5M per DropsTab: seed $3.5M (Dec 2023) + bridge round $10M (Oct 2025, mostly a token purchase; counted under the company-level rule). Series A (Sep 2024) amount undisclosed; the pre-seed $1M per press would bring the total to about $14.5M. Multicoin Capital invested on 2026-09-29, size undisclosed. Without the $10M bridge round the confirmed total is $4.5M (D). Grass says no equity financing since token genesis. | G17: DropsTab fundraising page; crypto.news; Blockworks; Multicoin | 2026-10-07
A18: 2026-10-07 | B18: GRASS | C18: L13 | F18: NOT scored (user decision 2026-10-07: blank). Grass says its customers include Fortune 100 enterprises "including members of the Magnificent Seven" and leading AI labs, but it does not disclose names; revenue is independently attested but the counterparties are unnamed. This does not meet the documented-production-use rule, and E (none found) would mislead. A was offered as a flagged user override and declined. | G18: grass.io July 7 recap; Regen Financial attestation | 2026-10-07
A19: 2026-10-07 | B19: GRASS | C19: L14 | E19: D | F19: Market cap $451.3M | G19: CoinGecko API | 2026-10-07
A20: 2026-10-07 | B20: GRASS | C20: L15 | E20: A | F20: Market cap +88.9% in 90 days ($239.3M on 2026-07-09 to $452.1M on 2026-10-07) vs top-20 basket +31.6% (recomputed 2026-10-07 from the 20 members in share_cfg.json) = relative +43.6%. Includes newly unlocked supply (circulating supply +10.7% in the period). | G20: CoinGecko history; share_cfg.json | 2026-10-07
A21: 2026-10-07 | B21: All | C21: - | F21: V6: scoring workbook and evidence table merged into Crypto Analysis V6.xlsx; legacy sheets removed (old 10-line Score sheet, old Batch columns, legacy point values); no grade changed. Note fixes: L12 definition: source aligned with the procedure (DropsTab or Tokenomist); DOGE/SHIB purpose: unresolved note marked superseded; DOGE/SHIB purpose: 'L11 = M' corrected to 'L11 = E'; AVAX note: 'not in this project's universe' corrected. | G21: Restructure
A22: 2026-10-06 | B22: XLM | C22: L1 | E22: B | F22: MC/FDV 0.70 (market cap $7.557B ÷ FDV $10.778B on the fixed 50.0B total supply; XLM has no max supply) | G22: CoinGecko; TradingView FDV not retrieved (rate-limited 429), CoinGecko used | 2026-10-06
A23: 2026-10-06 | B23: XLM | C23: L2 | E23: B | F23: PROXY (no forward unlock schedule; SDF releases from its mandate at its discretion): realized 90-day circulating-supply growth +2.7% (34.13B to 35.06B); +2.9% for the window ending 10-05. Borderline † (3% cut-off) | G23: CoinGecko history; SDF dashboard | 2026-10-06
A24: 2026-10-06 | B24: XLM | C24: L3 | E24: C | F24: SDF mandate 14.677B ÷ 50.002B total supply = 29.4%. Counts SDF mandate only; upgrade reserve 0.259B (0.5%) and fee pool excluded (including the reserve gives 29.9%, still C) | G24: dashboard.stellar.org/api/v2/lumens | 2026-10-06
A25: 2026-10-06 | B25: XLM | C25: L4 | E25: D | F25: Holders revenue $104,004 ÷ fees $5,084,063 (30 days) = 2.0%; fees above $1M a month so no cap. User decision 2026-10-06: use 2.0% | G25: DefiLlama | 2026-10-06
A26: 2026-10-06 | B26: XLM | C26: L5 | E26: A | F26: 2% bid depth $2.016M = 20.2x $100K: Coinbase USD $1.063M + USDT $0.009M; Kraken $0.886M (500 levels); Binance.US USD $0.041M + USDT $0.017M | G26: exchange order books | 2026-10-06 10:14 UTC
A27: 2026-10-06 | B27: XLM | C27: L7 | E27: B | F27: Sentiment 100% (step A) and Galaxy Score 58 (step C); mean of steps = B | G27: TradingView; values supplied by the user because the screener returned 429 | 2026-10-06
A28: 2026-10-06 | B28: XLM | C28: L8 | E28: A | F28: No direct loss of XLM itself found in 24 months (DefiLlama hacks matched by name and chain, then news). Third-party, listed for context and NOT graded (user decision 2026-10-06): Blend/YieldBlox pool ~$10.97M, 22 Feb 2026 (oracle manipulation; ~48M XLM frozen by validators); Comet DEX $717K, 25 Aug 2026 (below $1M, not a flag). CoinEx $55M (Sep 2023) is an exchange and outside the window | G28: DefiLlama hacks; Rekt; Protos; CoinTurk | 2026-10-06
A29: 2026-10-06 | B29: XLM | C29: L9 | E29: A | F29: SEC/CFTC joint interpretation of 2026-03-17 names Stellar (XLM) a digital commodity; no enforcement found. Only a futures-based ETF (STLR, Volatility Shares, 1 Apr 2026), no spot ETF | G29: Pillsbury and DLA Piper summaries; SEC filings | 2026-10-06
A30: 2026-10-06 | B30: XLM | C30: L10 | E30: B | F30: No mint key (fixed 50.0B supply). Upgrades and freezes need a validator quorum (CAP-77 Quorum Freeze, described as live by the SDF; validators froze ~48M XLM in Feb 2026). User decision 2026-10-06: grade B (validator-quorum governance); C (disclosed freeze) was the alternative | G30: stellar.org blog; mexc/blockchain.news | 2026-10-06
A31: 2026-10-06 | B31: XLM | C31: L11 | E31: A | F31: Yes: live cross-border payments and tokenized-asset rails; Stellar chain fees $5.08M (30 days), chain TVL $265M, stablecoins $915M | G31: DefiLlama | 2026-10-06
A32: 2026-10-06 | B32: XLM | C32: L12 | E32: C | F32: Total raised $5.02M (2.65B XLM sold: Stripe seed $3M for 2B XLM plus an early public auction). Sits $0.02M above the $5M C/D line; Stripe-only $3M would be D. User decision 2026-10-06: keep C | G32: DropsTab | 2026-10-06
A33: 2026-10-06 | B33: XLM | C33: L13 | E33: A | F33: Franklin Templeton (AUM $1.68T) runs the registered Franklin OnChain U.S. Government Money Fund (BENJI) on Stellar since 2021, live; PayPal PYUSD live on Stellar. Counted as production use of the network, not a holding of XLM | G33: Franklin Templeton press release 2026-04-30; stellar.org | 2026-10-06
... A50: 2026-10-06 | B50: ENA | C50: L15 | E50: A | F50: Market cap $725.5M (2026-07-08) to $3,220.7M (2026-10-06) = +344% vs top-20 basket +33.5% (recomputed 2026-10-06, 20 coins in share_cfg.json); relative +233%. Includes unlocked supply (CoinGecko circulating 9.56B to 13.41B); the ENA price itself rose +208%, so price-only is still A. | G50: CoinGecko history; share_cfg.json | 2026-10-06
A51: 2026-10-06 | B51: ETH | C51: L1 | D51: A | E51: A | F51: MC/FDV 1.00 (market cap $329.4B = FDV; no max supply) | G51: CoinGecko API; DropsTab (FDV = market cap) | 2026-10-06
A52: 2026-10-06 | B52: ETH | C52: L2 | D52: A | E52: A | F52: Net supply +0.215% over 90 days (121,844,832 ETH on 2026-07-08 to 122,106,290 on 2026-10-07 00:16 UTC); protocol issuance ~1.08M ETH a year (~0.22% per 90 days). PROXY: realized on-chain growth, no unlock schedule. CoinGecko circulating history implies +1.18% (would be B) but looks like a data artifact; on-chain series used | G52: ultrasound.money API | 2026-10-06
A53: 2026-10-06 | B53: ETH | C53: L3 | E53: A | F53: Early Contributor & Foundation 8.87% of supply (A, <=15%). Counted: genesis allocation to early contributors and the Ethereum Foundation (~12M of the 72M genesis ETH: 3M Foundation endowment, 6M to 85 contributors, 3M developer purchase program). Not counted: ICO participants 44.31% (public crowdsale buyers, not insiders), PoW rewards 37.16%, staking rewards 9.66%. If ICO buyers were counted insiders would be 53.2% ( | G53: Tokenomist; The Block; Galaxy | 2026-10-06
A54: 2026-10-06 | B54: ETH | C54: L4 | D54: B | E54: B | F54: 32.4% of base-layer fees burned: holders revenue $5.45M ÷ fees $16.82M, 30 days to 2026-10-06 (fees above $1M, no cap). The all-apps chain aggregate (overview/fees/ethereum) gives 6.3% ($21.9M of $345.5M, D); base-layer series used, as in the earlier 31.9% | G54: DefiLlama /summary/fees/ethereum | 2026-10-06
A55: 2026-10-06 | B55: ETH | C55: L5 | D55: A | E55: A | F55: 276.6x: 2% bid depth $27.66M = Coinbase ETH-USD $12.66M + Kraken ETHUSD $13.57M (500 levels) + Binance.US ETHUSD $0.76M + ETHUSDT $0.66M (mid ~$2,698.6; 2% mark reached on all four books). One-day snapshot (540.9x on 2026-10-05) | G55: Exchange order-book APIs, snapshot 2026-10-07 00:1x UTC | 2026-10-06
A56: 2026-10-06 | B56: ETH | C56: L6 | D56: D | E56: D | F56: Price-free: stablecoin supply on Ethereum $152.39B to $147.30B = -3.3% [C]. Native-token: chain TVL $39.39B to $54.11B (+37.4%) ÷ ETH price $1,771 to $2,710 (daily points) = -10.2% [D]; against the live price -9.9% [C], and -9.5% to -10.6% across neighbouring days. Lower of the two = D. Borderline † (within 5 pts of the -10% cut-off) | G56: DefiLlama stablecoins and chain TVL; CoinGecko history | 2026-10-06
A57: 2026-10-06 | B57: ETH | C57: L7 | D57: C | E57: C | F57: TradingView sentiment 80% (step B) and Galaxy Score 45 (step D), supplied by the user 2026-10-06; mean of steps = C (no half step). Claude's four TradingView attempts returned 429. CoinGecko votes 81.1% bullish for context only. One-day snapshot (stored 2026-10-05: 79% / 62.3, C) | G57: TradingView via user; CoinGecko API | 2026-10-06
A58: 2026-10-06 | B58: ETH | C58: L8 | D58: A | E58: A | F58: No direct loss of ETH in 24 months. DefiLlama /hacks has no entry named Ethereum; 47 entries list the Ethereum chain, all apps, exchanges, wallets or bridges (e.g. Bybit $1.4B Feb 2025, Kelp $293M Apr 2026, Balancer V2 $128M Nov 2025, Bitget Sep 2026), listed for context, not graded. Verus-Ethereum Bridge is a Verus-chain bridge (false positive). Protocol context, no funds lost: Prysm v7.0.0 bug after the Fusaka upgr | G58: DefiLlama /hacks; news (low-quality reposts) | 2026-10-06
A59: 2026-10-06 | B59: ETH | C59: L9 | D59: A | E59: A | F59: Spot ETH ETFs approved (Jul 2024); staking ETFs live (Grayscale Oct 2025, BlackRock ETHB Mar 2026); SEC/CFTC joint interpretive release of 2026-03-17 names ETH among 16 digital commodities; no SEC/CFTC/DOJ enforcement against ETH found. Sources are mostly secondary (crypto media, law-firm notes); Coinbase asset tag not retrieved | G59: Web searches | 2026-10-06
A60: 2026-10-06 | B60: ETH | C60: L10 | D60: A | E60: A | F60: No admin, mint or upgrade key. Protocol changes are made off-chain through the EIP process and client-team rough consensus (not token voting); the Ethereum Foundation does not control upgrades. Judgment: social-layer concentration among client teams is not an admin path | G60: ethereum.org governance; EIP process write-ups | 2026-10-06
A61: 2026-10-06 | B61: ETH | C61: L11 | D61: A | E61: A | F61: Yes: native gas and staking asset of a live network. DefiLlama Ethereum chain fees $345.5M and base-layer fees $16.8M (30 days); chain TVL $54.1B | G61: DefiLlama | 2026-10-06
A62: 2026-10-06 | B62: ETH | C62: L12 | D62: NA | E62: C | F62: $18.66M raised in the 2014 public ICO (60M ETH at ~$0.31; ~31,591 BTC); DropsTab lists no named investors, no lock-up. C ($5M to <$25M). User decision 2026-10-06: a public crowdsale counts, as for QNT's token sales. Tokenomist shows $0 (it tracks VC rounds and vested allocations). Changed from NA | G62: DropsTab fundraising page | 2026-10-06
A63: 2026-10-06 | B63: ETH | C63: L13 | D63: A | E63: A | F63: JPMorgan Asset Management runs two tokenized money market funds on public Ethereum: MONY (launched 15 Dec 2025, qualified investors) and JLTXX (13 May 2026), about $800M combined by early Jul 2026; BlackRock BUIDL, Franklin Templeton and Fidelity also on-chain. Counted as production use of the network, not a holding of ETH (as for SOL, LINK, XLM) | G63: Crypto Briefing; Unchained; The Next Web | 2026-10-06
A64: 2026-10-06 | B64: ETH | C64: L14 | D64: A | E64: A | F64: Market cap $329.4B | G64: CoinGecko API | 2026-10-06
A65: 2026-10-06 | B65: ETH | C65: L15 | D65: A | E65: A | F65: Market cap $213.8B (2026-07-08) to $331.0B (2026-10-06) = +54.8% vs top-20 basket +33.1% (recomputed 2026-10-06 from the 20 coins in share_cfg.json; ETH is a basket member); relative +16.3%, 6 points above the A cut-off | G65: CoinGecko history; share_cfg.json | 2026-10-06
A66: 2026-10-06 | B66: XLM | C66: L6 usage trend | E66: B | F66: Price-free: stablecoin supply on Stellar +9.1% ($834.7M to $910.8M) [B]. Native-token: chain TVL ÷ XLM price +9.1% (TVL $222.3M to $271.5M; price $0.1999 to $0.2239) [B]. Lower of the two = B; borderline † (within 1 pt of the +10% cut-off). News reported DeFi TVL falling $270M to $98M after the Aug 25 Comet exploit; the DefiLlama chain series does not show it, so the chain series is used | G66: DefiLlama, stablecoins.llama.fi, CoinGecko
A67: 2026-10-06 | B67: XLM | C67: L11 | E67: A | F67: Yes: live cross-border payments and tokenized-asset rails; Stellar chain fees $5.08M (30 days), chain TVL $265M, stablecoins $915M | G67: DefiLlama
A68: 2026-10-06 | B68: XLM | C68: L12 | E68: C | F68: Total raised $5.02M (2.65B XLM sold: Stripe seed $3M for 2B XLM plus an early public auction). Sits $0.02M above the $5M C/D line; Stripe-only $3M would be D. User decision 2026-10-06: keep C | G68: dropstab.com (stellar)
A69: 2026-10-06 | B69: XLM | C69: L13 | E69: A | F69: Franklin Templeton (AUM $1.68T) runs the registered Franklin OnChain U.S. Government Money Fund (BENJI) on Stellar since 2021, live; PayPal PYUSD live on Stellar. Counted as production use of the network, not a holding of XLM | G69: Franklin Templeton press release 2026-04-30
A70: 2026-10-06 | B70: XLM | C70: L14 | E70: C | F70: Market cap $7.557B | G70: CoinGecko
A71: 2026-10-06 | B71: XLM | C71: L15 | E71: D | F71: Market cap +17.3% in 90 days vs top-20 basket +33.5% (recomputed 2026-10-06; XLM is itself a basket member, ex-XLM basket also +33.5%); relative -12.1%; borderline † (within 5 pts of the -10% cut-off) | G71: CoinGecko history
A72: 2026-10-06 | B72: ENA | C72: L6 usage trend | E72: E | F72: Price-free: ethena-usde 30-day fees $18.34M (ending 2026-10-05) vs $16.18M (ending 2026-07-07) = +13.3% [A]. Native-token: TVL ÷ ENA price: TVL $4.41B to $4.91B (+11.2%), ENA price $0.0783 to $0.2413 (+208%) = -63.9% [E]. Lower of the two = E. Borderline † (fee measure within 5 pts of the +10% cut-off). The native-token measure binds because the ENA price tripled. | G72: DefiLlama protocol and fees series; CoinGecko history
A73: 2026-10-06 | B73: ENA | C73: L11 | E73: A | F73: Yes: live USDe and USDtb products; DefiLlama Ethena USDe TVL $4.97B, 30-day fees $18.3M. ENA is the governance and staking (sENA) token (governance is advisory). Scored on the documented live product and the token's governance and staking role. | G73: DefiLlama; CoinGecko; Ethena docs
A74: 2026-10-06 | B74: ENA | C74: L12 | E74: A | F74: Total raised $182.5M per DropsTab: seed $6.5M (Jul 2023), seed extension $14M (Feb 2024), private sale $100M (Feb 2025), strategic $16M + $16M (Feb-Mar 2025) and $30M (Oct 2025, MEXC). One $16M round may be double-counted ($166.5M), still A. Company-level rounds count. StablecoinX PIPE not counted as an Ethena raise. Tokenomist page not retrieved. | G74: DropsTab fundraising page
A75: 2026-10-06 | B75: ENA | C75: L13 | E75: A | F75: A (user confirmed 2026-10-06): Anchorage Digital Bank (OCC-chartered) is the live US issuer of USDtb, whose reserves are held in BlackRock's BUIDL fund (DefiLlama USDtb TVL $488.6M). Counted as production use of the Ethena product, not a holding of ENA. Not counted: BlackRock Aladdin integration (announced by Ethena; BlackRock has not published a matching statement), Coinbase Ventures and Janus Henderson (investments), StablecoinX. A stricter reading would be E. | G75: Ethena whitelabel and USDtb sites; DefiLlama; CoinDesk; BeInCrypto
A76: 2026-10-06 | B76: ENA | C76: L14 | E76: C | F76: Market cap $3.222B (CoinGecko, includes StablecoinX); adjusted about $2.8B (11.8B × $0.2403). C either way. | G76: CoinGecko
A77: 2026-10-06 | B77: ENA | C77: L15 | E77: A | F77: Market cap $725.5M (2026-07-08) to $3,220.7M (2026-10-06) = +344% vs top-20 basket +33.5% (recomputed 2026-10-06, 20 coins in share_cfg.json); relative +233%. Includes unlocked supply (CoinGecko circulating 9.56B to 13.41B); the ENA price itself rose +208%, so price-only is still A. | G77: CoinGecko history; share_cfg.json
... A85: 2026-10-05 | B85: ETH | C85: L6 | E85: A | F85: chain TVL +37.2% (90d) | G85: DefiLlama 2026-10-05
A86: 2026-10-05 | B86: ETH | C86: L4 | D86: A | E86: B | F86: 31.9% of fees burned | G86: DefiLlama 30-day fees vs holders revenue
A87: 2026-10-05 | B87: SOL | C87: L6 | D87: B | E87: A | F87: chain TVL +30.3% (90d) | G87: DefiLlama 2026-10-05
A88: 2026-10-05 | B88: SOL | C88: L4 | D88: B | E88: C | F88: 11.5% of fees burned | G88: DefiLlama 30-day fees vs holders revenue
A89: 2026-10-05 | B89: XRP | C89: L6 | E89: A | F89: XRPL DEX TVL +33.8% (90d) | G89: DefiLlama 2026-10-05
A90: 2026-10-05 | B90: NEAR | C90: L6 | E90: A | F90: chain TVL +99.8% (90d) | G90: DefiLlama 2026-10-05
A91: 2026-10-05 | B91: LINK | C91: L6 | E91: A | F91: TVL +32.1% (90d) | G91: DefiLlama 2026-10-05
A92: 2026-10-05 | B92: LINK | C92: L4 | E92: A | F92: 98.6% of fees to holders | G92: DefiLlama 30-day fees vs holders revenue
A93: 2026-10-05 | B93: UNI | C93: L6 | E93: A | F93: TVL +34.1% (90d) | G93: DefiLlama 2026-10-05
A94: 2026-10-05 | B94: UNI | C94: L4 | D94: B | E94: D | F94: 8.0% of fees to holders | G94: DefiLlama 30-day fees vs holders revenue
A95: 2026-10-05 | B95: AAVE | C95: L6 | D95: B | E95: A | F95: TVL +46.2% (90d) | G95: DefiLlama 2026-10-05
A96: 2026-10-05 | B96: ONDO | C96: L6 | D96: B | E96: C | F96: fees -0.6% (90d) | G96: DefiLlama 2026-10-05
A97: 2026-10-05 | B97: TAO | C97: L6 | E97: A | F97: chain TVL +1309% (90d) | G97: DefiLlama 2026-10-05
A98: 2026-10-05 | B98: BNB | C98: L5 | E98: A | F98: 19.6x ($1.96M within 2%, Coinbase+Kraken+Binance.US) | G98: Live order books 2026-10-05
A99: 2026-10-05 | B99: BNB | C99: L6 | D99: B | E99: A | F99: BSC TVL +17.2% (90d) | G99: DefiLlama 2026-10-05
A100: 2026-10-05 | B100: BNB | C100: L4 | D100: B | E100: C | F100: 10.0% of fees burned | G100: DefiLlama 30-day fees vs holders revenue
A101: 2026-10-05 | B101: RENDER | C101: L6 | E101: A | F101: BME fees +259% (90d), tiny base | G101: DefiLlama 2026-10-05
A102: 2026-10-05 | B102: SAND | C102: L5 | D102: E | E102: B | F102: 5.7x ($0.57M within 2%, Coinbase+Kraken+Binance.US) | G102: Live order books 2026-10-05
A103: 2026-10-05 | B103: XMR | C103: L6 | E103: A | F103: chain fees +35.0% (90d) | G103: DefiLlama 2026-10-05
A104: 2026-10-05 | B104: ZEC | C104: L6 | D104: B | E104: A | F104: chain fees +381% / TVL +79.5% (90d) | G104: DefiLlama 2026-10-05
A105: 2026-10-05 | B105: DOGE | C105: L6 | E105: B | F105: chain fees +6.2% (90d) | G105: DefiLlama 2026-10-05
A106: 2026-10-05 | B106: SHIB | C106: L5 | D106: C | E106: B | F106: 9.1x ($0.91M within 2%, Coinbase+Kraken+Binance.US) | G106: Live order books 2026-10-05
A107: 2026-10-05 | B107: SHIB | C107: L6 | E107: A | F107: ShibaSwap TVL +43.2% (90d), tiny base | G107: DefiLlama 2026-10-05
A108: 2026-10-05 | B108: USDC | C108: L6 | D108: C | E108: B | F108: supply +1.5% (90d) | G108: DefiLlama 2026-10-05
A109: 2026-10-05 | B109: USDT | C109: L6 | D109: B | E109: C | F109: supply -0.2% (90d) | G109: DefiLlama 2026-10-05
A110: 2026-10-05 | B110: LTC | C110: L6 | E110: A | F110: chain fees +53.0% (90d), tiny base | G110: DefiLlama 2026-10-05
A111: 2026-10-05 | B111: HYPE | C111: L6 | D111: C | E111: D | F111: L1 TVL -18.8% (90d); note perps fees +23.7% | G111: DefiLlama 2026-10-05
A112: 2026-10-05 | B112: IMX | C112: L6 | E112: B | F112: zkEVM TVL +2.1% (90d), tiny base | G112: DefiLlama 2026-10-05
A113: 2026-10-05 | B113: RED | C113: L5 | E113: D | F113: 1.3x ($0.13M within 2%, Coinbase+Kraken) | G113: Live order books 2026-10-05
A114: 2026-10-05 | B114: RAY | C114: L5 | E114: C | F114: 4.0x ($0.40M within 2%, Coinbase+Kraken) | G114: Live order books 2026-10-05
A115: 2026-10-05 | B115: RAY | C115: L6 | E115: A | F115: TVL +46.5% (90d) | G115: DefiLlama 2026-10-05
A116: 2026-10-05 | B116: NIGHT | C116: L5 | E116: A | F116: 11.4x ($1.14M within 2%, Kraken) | G116: Live order books 2026-10-05
A117: 2026-10-05 | B117: POWR | C117: L5 | E117: E | F117: 0.6x ($0.06M within 2%, Coinbase+Kraken) | G117: Live order books 2026-10-05
A118: 2026-10-05 | B118: PEPE | C118: L5 | D118: B | E118: A | F118: 18.8x ($1.88M within 2%, Coinbase+Kraken+Binance.US) | G118: Live order books 2026-10-05
A119: 2026-10-05 | B119: CRO | C119: L6 | E119: E | F119: chain TVL -37.0% (90d) | G119: DefiLlama 2026-10-05
A120: 2026-10-05 | B120: NIGHT | C120: L7 | E120: B | F120: Galaxy Score 67.8 (user-supplied from TradingView, 2026-10-05); sentiment not available, so Galaxy step only | G120: User, TradingView
A121: 2026-10-05 | B121: RAY | C121: L2 | E121: A | F121: Tokenomist: unlock schedule ended 2024, no upcoming unlocks (page updated 2026-10-05). Caveat: Tokenomist shows 48.6% circulating, mining reserve 34% | G121: Tokenomist 2026-10-05
A122: 2026-10-05 | B122: NIGHT | C122: L7 | D122: B | E122: B | F122: CoinGecko API community votes 90.3% bullish (user quoted 89%) + Galaxy 67.8. Sentiment step A, Galaxy step B, mean rounds down to B: no change. Note: CoinGecko votes are not the TradingView sentiment the guide specifies | G122: CoinGecko API 2026-10-05
A123: 2026-10-05 | B123: ETH | C123: L6 | D123: A | E123: D | F123: 90-day TVL in native token terms -11.1% (dollar TVL +34.8%): price-neutral re-score | G123: DefiLlama TVL ÷ CoinGecko token price, 2026-10-05
A124: 2026-10-05 | B124: SOL | C124: L6 | D124: A | E124: D | F124: 90-day TVL in native token terms -11.7% (dollar TVL +31.1%): price-neutral re-score | G124: DefiLlama TVL ÷ CoinGecko token price, 2026-10-05
...

Sheet Settings
A1: SETTINGS: the rules in numbers. Formulas on the Grades sheet read this sheet.
A3: Grade | B3: % of a line's points
A4: A | B4: 1
A5: B | B5: 0.75
A6: C | B6: 0.5
A7: D | B7: 0.25
A8: E | B8: 0
A10: THE FIFTEEN LINES (100 points)
A11: Line | B11: Name | C11: Points | D11: Cut-offs | E11: Sources
A12: L1 | B12: Supply dilution (MC/FDV) | C12: 10 | D12: A ≥0.80 | B 0.60–0.79 | C 0.40–0.59 | D 0.20–0.39 | E <0.20 | E12: CoinGecko, TradingView (FDV on max supply)
A13: L2 | B13: New supply in next 90 days (% of circulating) | C13: 5 | D13: A ≤1% | B >1–3% | C >3–5% | D >5–10% | E >10% (proxy: realized 90-day circulating growth if no schedule) | E13: Tokenomist, Tokenomics.com, DropsTab, CoinGecko history
A14: L3 | B14: Insider share (team, investors, foundation) | C14: 5 | D14: A ≤15% or fair launch | B >15–25% | C >25–40% | D >40–50% | E >50% | E14: Tokenomist, Tokenomics.com
A15: L4 | B15: Holder value capture (fees burned, bought back or paid out) | C15: 5 | D15: A ≥50% | B 25–49% | C 10–24% | D 1–9% | E 0% (under 1% but above 0 = E); capped at C if fees < $1M a month | E15: DefiLlama holders revenue ÷ fees, 30 days
A16: L5 | B16: US exit liquidity (2% bid depth ÷ $100K) | C16: 10 | D16: A ≥10× | B 5–<10× | C 3–<5× | D 1–<3× | E <1× | E16: Coinbase, Kraken, Binance.US order books
A17: L6 | B17: Usage trend (90-day) | C17: 10 | D17: A ≥+10% | B 0 to +10% | C −10 to 0% | D −30 to −10% | E <−30% (30-day: +5/0/−5/−15). Lower of the price-free and native-token measures | E17: DefiLlama, stablecoins.llama.fi, CoinGecko
A18: L7 | B18: Social sentiment | C18: 5 | D18: Mean of two steps, a half rounds down: sentiment 85/80/75/70 and Galaxy Score 70/60/50/40 | E18: TradingView (CoinGecko votes only if flagged)
A19: L8 | B19: Incident record (24 months) | C19: 5 | D19: A none found | B ≤$1M remediated | C $1–10M remediated | D >$10M remediated | E unremediated. Coin's own direct loss only | E19: DefiLlama /hacks, news
A20: L9 | B20: US regulatory status | C20: 10 | D20: A ETF-approved or commodity, no action | B regulated issuer or clear | C unclear, no action | D restricted | E active enforcement | E20: Coinbase tags, SEC/CFTC, web search
A21: L10 | B21: Admin control | C21: 5 | D21: A immutable or no admin path | B timelocked multisig or DAO | C multisig without timelock or disclosed freeze | D single key or foundation | E unverified mint/upgrade | E21: Project docs, DefiLlama
A22: L11 | B22: Purpose: use beyond trading in a live product | C22: 10 | D22: Yes = A | No = E | blank if no named source | E22: DefiLlama fees/TVL, CoinGecko, project docs
A23: L12 | B23: Backers: raised from outside investors | C23: 5 | D23: A ≥$100M | B $25–<100M | C $5–<25M | D >$0–<5M | NA where no raise is recorded (company-level rounds count) | E23: DropsTab, Tokenomist
... A26: L15 | B26: Market-share trend (90-day dominance vs top-20 basket) | C26: 5 | D26: Same cut-offs as line 6 on (1 + coin change) ÷ (1 + basket change) − 1. NA for USDT, USDC, PAXG | E26: CoinGecko history; basket below
B27: Total | C27: =SUM(C12:C26) -> 100
A29: GROUP RULES: 1 = the line must be NA for this group (removed from the denominator). A coin with no recorded raise also has L12 = NA.
A30: Group | B30: L1 | C30: L2 | D30: L3 | E30: L4 | F30: L5 | G30: L6 | H30: L7 | I30: L8 | J30: L9 | K30: L10 | L30: L11 | M30: L12 | N30: L13 | O30: L14 | P30: L15
A31: Chain / protocol | B31: 0 | C31: 0 | D31: 0 | E31: 0 | F31: 0 | G31: 0 | H31: 0 | I31: 0 | J31: 0 | K31: 0 | L31: 0 | M31: 0 | N31: 0 | O31: 0 | P31: 0
A32: Money coin | B32: 0 | C32: 0 | D32: 0 | E32: 1 | F32: 0 | G32: 0 | H32: 0 | I32: 0 | J32: 0 | K32: 0 | L32: 0 | M32: 0 | N32: 0 | O32: 0 | P32: 0
A33: Memecoin | B33: 0 | C33: 0 | D33: 0 | E33: 1 | F33: 0 | G33: 0 | H33: 0 | I33: 0 | J33: 0 | K33: 0 | L33: 0 | M33: 0 | N33: 0 | O33: 0 | P33: 0
A34: Stablecoin / RWA | B34: 1 | C34: 1 | D34: 1 | E34: 1 | F34: 0 | G34: 0 | H34: 0 | I34: 0 | J34: 0 | K34: 0 | L34: 0 | M34: 1 | N34: 0 | O34: 0 | P34: 1
A35: Memecoin: tier held at Average/Decent automatically.
A38: Threshold | B38: Value
A39: Exceptional: minimum score | B39: 90
A40: Strong: minimum score | B40: 75
A41: Average/Decent: minimum score | B41: 60
A42: Minimum coverage to print a tier | B42: 0.7
A45: CAP COLUMN on Grades (enter only for a retrieved fact)
A46: 3 | B46: Flag: the tier drops at most one step below what the score gives, never below Average/Decent. Flags: active SEC/CFTC/DOJ enforcement; material incident in the last 90 days, remediated, loss > $1M (90 days run from remediation); team-controlled mint/upgrade key with no timelock; top-10 non-exchange wallets > 60%; stablecoin depeg > 5% for > 24 h; privacy coin banned or delisted.
A47: 4 | B47: Cap 4 (Weak): unresolved exploit, unbacked minting, or stablecoin/RWA reserves shown not independently verified.
A50: MARKET-SHARE BASKET (line 15): top-20 by market cap, CoinGecko IDs. Basket 90-day change +33.5% on 2026-10-05; recompute it for any other date and write the figure and date in the evidence.
A51: 1 | B51: bitcoin
A52: 2 | B52: ethereum
A53: 3 | B53: tether
A54: 4 | B54: binancecoin
A55: 5 | B55: ripple
A56: 6 | B56: usd-coin
A57: 7 | B57: solana
A58: 8 | B58: tron
A59: 9 | B59: figure-heloc
A60: 10 | B60: zcash
A61: 11 | B61: hyperliquid
A62: 12 | B62: dogecoin
... A70: 20 | B70: stellar
